Workbook

Sheet 2023
B1: Zarewa Aluminium And Plastics Ltd Kaduna | G1: Zarewa Aluminium And Plastics Ltd Kaduna | L1: Zarewa Aluminium And Plastics Ltd Kaduna | Q1: Zarewa Aluminium And Plastics Ltd Kaduna | V1: Zarewa Aluminium And Plastics Ltd Kaduna | AA1: Zarewa Aluminium And Plastics Ltd Kaduna | AF1: Zarewa Aluminium And Plastics Ltd Kaduna | AK1: Zarewa Aluminium And Plastics Ltd Kaduna
B2: Production Account for the month end May | G2: Production Account for the month end June | L2: Production Account for the month end July | Q2: Production Account for the month end August | V2: Production Account for the month end September | AA2: Production Account for the month end October | AF2: Production Account for the month end November | AK2: Production Account for the month end December
B3: Opening Stock | D3: 64643620 | G3: Opening Stock | I3: =C7 -> 122151270 | L3: Opening Stock | N3: =H7 -> 110032510 | Q3: Opening Stock | S3: =M7 -> 119085150 | V3: Opening Stock | X3: =R7 -> 109700300 | AA3: Opening Stock | AC3: =W7 -> 85764250 | AF3: Opening Stock | AH3: =AB7 -> 96485000 | AK3: Opening Stock | AM3: =AG7 -> 100928250
B4: Purchases | D4: 118594890 | G4: Purchases | I4: 48249230 | L4: Purchases | N4: 55512380 | Q4: Purchases | S4: 49559700 | V4: Purchases | X4: 27896591 | AA4: Purchases | AC4: 59739006 | AF4: Purchases | AH4: 29724603 | AK4: Purchases | AM4: 53505400
B5: Carriage Inward | D5: 1040000 | G5: Carriage Inward | I5: 454000 | L5: Carriage Inward | N5: 648500 | Q5: Carriage Inward | S5: 610000 | V5: Carriage Inward | X5: 453000 | AA5: Carriage Inward | AC5: 590200 | AF5: Carriage Inward | AH5: 270050 | AK5: Carriage Inward | AM5: 463000
D6: =SUM(D3:D5) -> 184278510 | I6: =SUM(I3:I5) -> 170854500 | N6: =SUM(N3:N5) -> 166193390 | S6: =SUM(S3:S5) -> 169254850 | X6: =SUM(X3:X5) -> 138049891 | AC6: =SUM(AC3:AC5) -> 146093456 | AH6: =SUM(AH3:AH5) -> 126479653 | AM6: =SUM(AM3:AM5) -> 154896650
B7: Closing Stock | C7: 122151270 | G7: Closing Stock | H7: 110032510 | L7: Closing Stock | M7: 119085150 | Q7: Closing Stock | R7: 109700300 | V7: Closing Stock | W7: 85764250 | AA7: Closing Stock | AB7: =96485000 -> 96485000 | AF7: Closing Stock | AG7: 100928250 | AK7: Closing Stock | AL7: 101533360
D8: =D6-C7 -> 62127240 | I8: =I6-H7 -> 60821990 | N8: =N6-M7 -> 47108240 | S8: =S6-R7 -> 59554550 | X8: =X6-W7 -> 52285641 | AC8: =AC6-AB7 -> 49608456 | AH8: =AH6-AG7 -> 25551403 | AM8: =AM6-AL7 -> 53363290
B10: Factory Overhead | G10: Factory Overhead | L10: Factory Overhead | Q10: Factory Overhead | V10: Factory Overhead | AA10: Factory Overhead | AF10: Factory Overhead | AK10: Factory Overhead
B11: Wages | C11: 196878.67 | G11: Wages | H11: 230000 | L11: Wages | M11: 239878.67 | Q11: Wages | R11: 326712 | V11: Wages | W11: 309212 | AA11: Wages | AB11: 398065.6 | AF11: Wages | AG11: 398065.6 | AK11: Wages | AL11: 398065.6
B12: Fuel & Lubricant | C12: 335400 | G12: Fuel & Lubricant | H12: 155000 | L12: Fuel & Lubricant | M12: 19500 | Q12: Fuel & Lubricant | R12: 248000 | V12: Fuel & Lubricant | W12: 210000 | AA12: Fuel & Lubricant | AB12: 204000 | AF12: Fuel & Lubricant | AG12: 255000 | AK12: Fuel & Lubricant | AL12: 38000
B13: Electricity Bill | C13: 9100 | G13: Electricity Bill | H13: 12700 | L13: Electricity Bill | M13: 13000 | Q13: Electricity Bill | R13: 15000 | V13: Electricity Bill | W13: 17000 | AA13: Electricity Bill | AB13: 14000 | AF13: Electricity Bill | AG13: 25500 | AK13: Electricity Bill | AL13: 30000
B14: Maintainace | C14: 495870 | G14: Maintainace | H14: 97000 | L14: Maintainace | M14: 988650 | Q14: Maintainace | R14: 834500 | V14: Maintainace | W14: 538400 | AA14: Maintainace | AB14: 1083600 | AF14: Maintainace | AG14: 130500 | AK14: Maintainace | AL14: 142800
B15: Depreciation | C15: 110000 | G15: Depreciation | H15: 110000 | L15: Depreciation | M15: 110000 | Q15: Depreciation | R15: 110000 | V15: Depreciation | W15: 110000 | AA15: Depreciation | AB15: 110000 | AF15: Depreciation | AG15: 110000 | AK15: Depreciation | AL15: 110000
C16: =SUM(C11:C15) -> 1147248.7 | H16: =SUM(H11:H15) -> 604700 | M16: =SUM(M11:M15) -> 1371028.7 | R16: =SUM(R11:R15) -> 1534212 | W16: =SUM(W11:W15) -> 1184612 | AB16: =SUM(AB11:AB15) -> 1809665.6 | AG16: =SUM(AG11:AG15) -> 919065.6 | AL16: =SUM(AL11:AL15) -> 718865.6
D17: =D8+C16 -> 63274489 | I17: =I8+H16 -> 61426690 | N17: =N8+M16 -> 48479269 | S17: =S8+R16 -> 61088762 | X17: =X8+W16 -> 53470253 | AC17: =AC8+AB16 -> 51418122 | AH17: =AH8+AG16 -> 26470469 | AM17: =AM8+AL16 -> 54082156
B23: Zarewa Aluminium And Plastics Ltd Kaduna | G23: Zarewa Aluminium And Plastics Ltd Kaduna | L23: Zarewa Aluminium And Plastics Ltd Kaduna | Q23: Zarewa Aluminium And Plastics Ltd Kaduna | V23: Zarewa Aluminium And Plastics Ltd Kaduna | AA23: Zarewa Aluminium And Plastics Ltd Kaduna | AF23: Zarewa Aluminium And Plastics Ltd Kaduna | AK23: Zarewa Aluminium And Plastics Ltd Kaduna
B24: Profit and Lost Account for the month end May | G24: Profit and Lost Account for the month end June | L24: Profit and Lost Account for the month end July | Q24: Profit and Lost Account for the month end Agust | V24: Profit and Lost Account for the month end September | AA24: Profit and Lost Account for the month end October | AF24: Profit and Lost Account for the month end November | AK24: Profit and Lost Account for the month end November
B25: Opening Stock | G25: Opening Stock | L25: Opening Stock | Q25: Opening Stock | V25: Opening Stock | AA25: Opening Stock | AF25: Opening Stock | AK25: Opening Stock
B26: Sales | D26: 86357548 | G26: Sales | I26: 62723747 | L26: Sales | N26: 56990608 | Q26: Sales | S26: 74826072 | V26: Sales | X26: 58468327 | AA26: Sales | AC26: 62757181 | AF26: Sales | AH26: 41604347 | AK26: Sales | AM26: 58501640
B27: Refund | C27: 8308581.2 | G27: Refund | H27: 6820595 | L27: Refund | M27: 5149904 | Q27: Refund | R27: 8725755 | V27: Refund | W27: 3474605 | AA27: Refund | AB27: 4351875 | AF27: Refund | AG27: 3626054 | AK27: Refund | AL27: 8313258
B28: Net Sales | D28: =D26-C27 -> 78048967 | G28: Net Sales | I28: =I26-H27 -> 55903152 | L28: Net Sales | N28: =N26-M27 -> 51840704 | Q28: Net Sales | S28: =S26-R27 -> 66100318 | V28: Net Sales | X28: =X26-W27 -> 54993722 | AA28: Net Sales | AC28: =AC26-AB27 -> 58405306 | AF28: Net Sales | AH28: =AH26-AG27 -> 37978293 | AK28: Net Sales | AM28: =AM26-AL27 -> 50188382
B29: Production Cost | C29: =D17 -> 63274489 | G29: Production Cost | H29: =I17 -> 61426690 | L29: Production Cost | M29: =N17 -> 48479269 | Q29: Production Cost | R29: =S17 -> 61088762 | V29: Production Cost | W29: =X17 -> 53470253 | AA29: Production Cost | AB29: =AC17 -> 51418122 | AF29: Production Cost | AG29: =AH17 -> 26470469 | AK29: Production Cost | AL29: =AM17 -> 54082156
B30: Closing Stock | C30: 0 | G30: Closing Stock | H30: 0 | L30: Closing Stock | M30: 0 | Q30: Closing Stock | R30: 0 | V30: Closing Stock | W30: 0 | AA30: Closing Stock | AB30: 0 | AF30: Closing Stock | AG30: 0 | AK30: Closing Stock | AL30: 0
C31: =SUM(C29:C30) -> 63274489 | H31: =SUM(H29:H30) -> 61426690 | M31: =SUM(M29:M30) -> 48479269 | R31: =SUM(R29:R30) -> 61088762 | W31: =SUM(W29:W30) -> 53470253 | AB31: =SUM(AB29:AB30) -> 51418122 | AG31: =SUM(AG29:AG30) -> 26470469 | AL31: =SUM(AL29:AL30) -> 54082156
B32: Gross Profit | D32: =D28-C31 -> 14774478 | G32: Gross Profit | I32: =I28-H31 -> -5523538 | L32: Gross Profit | N32: =N28-M31 -> 3361435.3 | Q32: Gross Profit | S32: =S28-R31 -> 5011555.5 | V32: Gross Profit | X32: =X28-W31 -> 1523469 | AA32: Gross Profit | AC32: =AC28-AB31 -> 6987184.4 | AF32: Gross Profit | AH32: =AH28-AG31 -> 11507824 | AK32: Gross Profit | AM32: =AM28-AL31 -> -3893774.1
B34: Admin Expenses | G34: Admin Expenses | L34: Admin Expenses | Q34: Admin Expenses | V34: Admin Expenses | AA34: Admin Expenses | AF34: Admin Expenses | AK34: Admin Expenses
B35: Admin exp | C35: 56000 | G35: Admin exp | H35: 15000 | L35: Admin exp | M35: 10000 | Q35: Admin exp | R35: 62000 | V35: Admin exp | W35: 195000 | AA35: Admin exp | AB35: 27500 | AF35: Admin exp | AG35: 204700 | AK35: Admin exp | AL35: 0
B36: Admin Salary | C36: 526921.13 | G36: Admin Salary | H36: 584847 | L36: Admin Salary | M36: 536556.8 | Q36: Admin Salary | R36: 398065.6 | V36: Admin Salary | W36: 398065 | AA36: Admin Salary | AB36: 313878.67 | AF36: Admin Salary | AG36: 313878.67 | AK36: Admin Salary | AL36: 313878.67
B37: Bank Charge | C37: 126939.29 | G37: Bank Charge | H37: 0 | L37: Bank Charge | M37: 73004.69 | Q37: Bank Charge | R37: 82076.99 | V37: Bank Charge | W37: 45702.39 | AA37: Bank Charge | AB37: 78074.19 | AF37: Bank Charge | AG37: 46724.7 | AK37: Bank Charge | AL37: 25873.35
B38: Office Expenses | C38: 47000 | G38: Office Expenses | H38: 652200 | L38: Office Expenses | M38: 300675 | Q38: Office Expenses | R38: 69300 | V38: Office Expenses | W38: 119400 | AA38: Office Expenses | AB38: 76200 | AF38: Office Expenses | AG38: 91900 | AK38: Office Expenses | AL38: 224000
B39: Professional Fee | C39: 230000 | G39: Professional Fee | H39: 290000 | L39: Professional Fee | M39: 0 | Q39: Professional Fee | R39: 50000 | V39: Professional Fee | W39: 0 | AA39: Professional Fee | AB39: 0 | AF39: Professional Fee | AG39: 150000 | AK39: Professional Fee | AL39: 20000
B40: Tax | C40: 386302.31 | G40: Tax | H40: 176064.93 | L40: Tax | M40: 170000 | Q40: Tax | R40: 170000 | V40: Tax | W40: 540577 | AA40: Tax | AB40: 0 | AF40: Tax | AG40: 197000 | AK40: Tax | AL40: 5420000
B41: Pension | C41: 0 | G41: Pension | H41: 0 | L41: Pension | M41: 0 | Q41: Pension | R41: 0 | V41: Pension | W41: 0 | AA41: Pension | AB41: 0 | AF41: Pension | AG41: 0 | AK41: Pension | AL41: 52130
B42: Security | C42: 60000 | G42: Security | H42: 60000 | L42: Security | M42: 40000 | Q42: Security | R42: 25000 | V42: Security | W42: 25000 | AA42: Security | AB42: 25000 | AF42: Security | AG42: 25000 | AK42: Security | AL42: 25000
B43: Intrest | C43: 0 | G43: Intrest | H43: 0 | L43: Intrest | M43: 0 | Q43: Intrest | R43: 0 | V43: Intrest | W43: 0 | AA43: Intrest | AB43: 0 | AF43: Intrest | AG43: 0 | AK43: Intrest | AL43: 0
B44: Welfare | C44: 0 | G44: Welfare | H44: 0 | L44: Welfare | M44: 0 | Q44: Welfare | R44: 0 | V44: Welfare | W44: 0 | AA44: Welfare | AB44: 0 | AF44: Welfare | AG44: 0 | AK44: Welfare | AL44: 473000
B45: Zakat & Sallah | C45: 0 | G45: Zakat & Sallah | H45: 0 | L45: Zakat & Sallah | M45: 0 | Q45: Zakat & Sallah | R45: 0 | V45: Zakat & Sallah | W45: 0 | AA45: Zakat & Sallah | AB45: 0 | AF45: Zakat & Sallah | AG45: 0 | AK45: Zakat & Sallah | AL45: 0
C46: =SUM(C35:C45) -> 1433162.7 | H46: =SUM(H35:H45) -> 1778111.9 | M46: =SUM(M35:M45) -> 1130236.5 | R46: =SUM(R35:R45) -> 856442.59 | W46: =SUM(W35:W45) -> 1323744.4 | AB46: =SUM(AB35:AB45) -> 520652.86 | AG46: =SUM(AG35:AG45) -> 1029203.4 | AL46: =SUM(AL35:AL45) -> 6553882
B47: Net Profit | D47: =D32-C46 -> 13341316 | G47: Net Profit | I47: =I32-H46 -> -7301649.9 | L47: Net Profit | N47: =N32-M46 -> 2231198.8 | Q47: Net Profit | S47: =S32-R46 -> 4155112.9 | V47: Net Profit | X47: =X32-W46 -> 199724.61 | AA47: Net Profit | AC47: =AC32-AB46 -> 6466531.5 | AF47: Net Profit | AH47: =AH32-AG46 -> 10478621 | AK47: Net Profit | AM47: =AM32-AL46 -> -10447656
B49: HQ | C49: 400000 | G49: HQ | H49: 800000 | L49: HQ | M49: 0 | Q49: HQ | R49: 800000 | V49: HQ | W49: 1100000 | AA49: HQ | AB49: 600000 | AF49: HQ | AG49: 600000 | AK49: HQ | AL49: 600000
B50: Chairman Withdrawal | C50: 41800 | G50: Chairman Withdrawal | H50: 170000 | L50: Chairman Withdrawal | M50: 31000 | Q50: Chairman Withdrawal | R50: 118500 | V50: Chairman Withdrawal | W50: 413500 | AA50: Chairman Withdrawal | AB50: 41500 | AF50: Chairman Withdrawal | AG50: 148000 | AK50: Chairman Withdrawal | AL50: 63000
B51: Mining | C51: 86000 | G51: Mining | H51: 40000 | L51: Mining | M51: 816000 | Q51: Mining | R51: 230000 | V51: Mining | W51: 564200 | AA51: truck | AB51: 302000 | AF51: truck | AG51: 151000 | AK51: truck | AL51: 10000
C52: =SUM(C49:C51) -> 527800 | H52: =SUM(H49:H51) -> 1010000 | M52: =SUM(M49:M51) -> 847000 | R52: =SUM(R49:R51) -> 1148500 | W52: =SUM(W49:W51) -> 2077700 | AA52: Mining | AB52: 134500 | AF52: Mining | AG52: 41000 | AK52: Mining | AL52: 41000
D53: =D47-C52 -> 12813516 | I53: =I47-H52 -> -8311649.9 | N53: =N47-M52 -> 1384198.8 | S53: =S47-R52 -> 3006612.9 | X53: =X47-W52 -> -1877975.4 | AB53: =SUM(AB49:AB52) -> 1078000 | AG53: =SUM(AG49:AG52) -> 940000 | AL53: =SUM(AL49:AL52) -> 714000
AC54: =AC47-AB53 -> 5388531.5 | AH54: =AH47-AG53 -> 9538621 | AM54: =AM47-AL53 -> -11161656 | AO54: =SUM(D53,I53,N53,S53,X53,AC54,AH54,AM54) -> 10780199
B59: Zarewa Aluminium And Plastics Ltd Kaduna | G59: Zarewa Aluminium And Plastics Ltd Kaduna | L59: Zarewa Aluminium And Plastics Ltd Kaduna | Q59: Zarewa Aluminium And Plastics Ltd Kaduna | V59: Zarewa Aluminium And Plastics Ltd Kaduna
B60: Asset and liability Account for the month end May | G60: Asset and liability Account for the month end May | L60: Asset and liability Account for the month end july | Q60: Asset and liability Account for the month end july | V60: Asset and liability Account for the month end September | AA60: Zarewa Aluminium And Plastics Ltd Kaduna | AF60: Zarewa Aluminium And Plastics Ltd Kaduna | AK60: Zarewa Aluminium And Plastics Ltd Kaduna
B61: ClosinG Stock | C61: =C7 -> 122151270 | G61: ClosinG Stock | H61: =H7 -> 110032510 | L61: ClosinG Stock | M61: =M7 -> 119085150 | Q61: ClosinG Stock | R61: =R7 -> 109700300 | V61: ClosinG Stock | W61: =W7 -> 85764250 | AA61: Asset and liability Account for the month end Octorber | AF61: Asset and liability Account for the month end Octorber | AK61: Asset and liability Account for the month end Octorber
B62: Cash at hand | C62: 1979513 | G62: Cash at hand | H62: 1233557 | L62: Cash at hand | M62: 1337731 | Q62: Cash at hand | R62: 153298 | V62: Cash at hand | W62: 372833 | AA62: ClosinG Stock | AB62: =AB7 -> 96485000 | AF62: ClosinG Stock | AG62: =AG7 -> 100928250 | AK62: ClosinG Stock | AL62: =AL7 -> 101533360
B63: Gt Bank | C63: 5075239 | G63: Gt Bank | H63: 7175579 | L63: Gt Bank | M63: 8081592.7 | Q63: Gt Bank | R63: 10228494 | V63: Gt Bank | W63: 4488995.2 | AA63: Cash at hand | AB63: -588992 | AF63: Cash at hand | AG63: 346358 | AK63: Cash at hand | AL63: 2409100
B64: Eco Bank | C64: 2034376.4 | G64: Eco Bank | H64: 640685.63 | L64: Eco Bank | M64: 2667762 | Q64: Eco Bank | R64: 6751974.1 | V64: Eco Bank | W64: 1737380.9 | AA64: Gt Bank | AB64: 488923.12 | AF64: Gt Bank | AG64: 399334.34 | AK64: Gt Bank | AL64: 330539.02
B65: Jaiz Bank | C65: 278042 | G65: Jaiz Bank | H65: 278042 | L65: Jaiz Bank | M65: 278042 | Q65: Jaiz Bank | R65: 278042 | V65: Jaiz Bank | W65: 278042 | AA65: Eco Bank | AB65: 1552348.9 | AF65: Eco Bank | AG65: 197979.86 | AK65: Eco Bank | AL65: 306118.02
D66: =SUM(C61:C65) -> 1.3151844e+08 | I66: =SUM(H61:H65) -> 1.1936037e+08 | N66: =SUM(M61:M65) -> 1.3145028e+08 | S66: =SUM(R61:R65) -> 1.2711211e+08 | X66: =SUM(W61:W65) -> 92641501 | AA66: Jaiz Bank | AB66: 278042 | AF66: Jaiz Bank | AG66: 278042 | AK66: Jaiz Bank | AL66: 278042
B67: Customer Debth | G67: Customer Debth | L67: Customer Debth | Q67: Customer Debth | V67: Customer Debth | AC67: =SUM(AB62:AB66) -> 98215322 | AF67: Taj bank | AG67: 308172.5 | AK67: Taj bank | AL67: 5011160
B68: Abdul Bawa | C68: 500000 | G68: Abdul Bawa | H68: 500000 | L68: Abdul Bawa | M68: 500000 | Q68: Abdul Bawa | R68: 500000 | V68: Abdul Bawa | W68: 500000 | AA68: Customer Debth | AH68: =SUM(AG62:AG67) -> 1.0245814e+08 | AM68: =SUM(AL62:AL67) -> 1.0986832e+08
B69: Jamil Sani | C69: 101300 | G69: Jamil Sani | H69: 101300 | L69: Jamil Sani | M69: 101300 | Q69: Jamil Sani | R69: 101300 | V69: Jamil Sani | W69: 101300 | AA69: Abdul Bawa | AB69: 500000 | AF69: Customer Debth | AK69: Customer Debth
B70: Alh sani Katsina | C70: 50000 | G70: Alh sani Katsina | H70: 50000 | L70: Alh sani Katsina | M70: 50000 | Q70: Alh sani Katsina | R70: 50000 | V70: Alh sani Katsina | W70: 50000 | AA70: Jamil Sani | AB70: 101300 | AF70: Abdul Bawa | AG70: 500000 | AK70: Abdul Bawa | AL70: 500000
B71: Rabiu Capenter | C71: 919300 | G71: Rabiu Capenter | H71: 919300 | L71: Rabiu Capenter | M71: 919300 | S71: =SUM(R68:R70) -> 651300 | X71: =SUM(W68:W70) -> 651300 | AA71: Alh sani Katsina | AB71: 50000 | AF71: Jamil Sani | AG71: 101300 | AK71: Jamil Sani | AL71: 101300
D72: =SUM(C68:C71) -> 1570600 | I72: =SUM(H68:H71) -> 1570600 | N72: =SUM(M68:M71) -> 1570600 | Q72: Staff Loan | V72: Staff Loan | AC72: =SUM(AB69:AB71) -> 651300 | AF72: Alh sani Katsina | AG72: 50000 | AK72: Alh sani Katsina | AL72: 50000
B73: Staff Loan | G73: Staff Loan | L73: Staff Loan | Q73: Alh Bala Muazu | R73: 982370 | V73: Alh Bala Muazu | W73: 942370 | AA73: Staff Loan | AH73: =SUM(AG70:AG72) -> 651300 | AM73: =SUM(AL70:AL72) -> 651300
B74: Alh Bala Muazu | C74: 1062370 | G74: Alh Bala Muazu | H74: 1062370 | L74: Alh Bala Muazu | M74: 1022370 | Q74: Haruna | R74: 100000 | V74: Haruna | W74: 90000 | AA74: Alh Bala Muazu | AB74: 902370 | AF74: Staff Loan | AK74: Staff Loan
B75: Umar sikeri | C75: 20000 | G75: Umar sikeri | H75: 0 | L75: Umar sikeri | M75: 0 | Q75: Hannatu | R75: 53840 | V75: Hannatu | W75: 53840 | AA75: Haruna | AB75: 80000 | AF75: Alh Bala Muazu | AG75: 902370 | AK75: Alh Bala Muazu | AL75: 902370
B76: Hannatu | C76: 53840 | G76: Hannatu | H76: 53840 | L76: Hannatu | M76: 53840 | Q76: Mal Amadu | R76: 90000 | V76: Mal Amadu | W76: 90000 | AA76: Hannatu | AB76: 53840 | AF76: Haruna | AG76: 70000 | AK76: Haruna | AL76: 60000
B77: Mal Amadu | C77: 26000 | G77: Mal Amadu | H77: 100000 | L77: Mal Amadu | M77: 90000 | Q77: Sani | R77: 50000 | V77: Sani | W77: 50000 | AA77: Mal Amadu | AB77: 90000 | AF77: Hannatu | AG77: 53840 | AK77: Hannatu | AL77: 53840
B78: Sani | C78: 44000 | G78: Sani | H78: 34000 | L78: Sani | M78: 34000 | Q78: Aliyu Sec | R78: 10000 | V78: Aliyu Sec | W78: 5000 | AA78: Sani | AB78: 50000 | AF78: Mal Amadu | AG78: 90000 | AK78: Mal Amadu | AL78: 90000
B79: Bagobiri | C79: 10000 | G79: Aliyu Sec | H79: 20000 | L79: Aliyu Sec | M79: 15000 | Q79: Ayo | R79: 40000 | V79: Ayo | W79: 35000 | AA79: Samuel | AB79: 30000 | AF79: Sani | AG79: 50000 | AK79: yauba | AL79: 50000
B80: Ado | C80: 5000 | G80: Douglas | H80: 40000 | L80: Ayo | M80: 45000 | Q80: Douglas | R80: 30000 | V80: Douglas | W80: 25000 | AA80: Laraba | AB80: 30000 | AF80: Samuel | AG80: 30000 | AK80: Sani | AL80: 50000
D81: =SUM(C74:C80) -> 1221210 | I81: =SUM(H74:H80) -> 1310210 | L81: Douglas | M81: 35000 | S81: =SUM(R73:R80) -> 1356210 | V81: isya | W81: 42500 | AA81: Ayo | AB81: 30000 | AF81: Laraba | AG81: 30000 | AK81: Laraba | AL81: 30000
B82: Others | G82: Others | N82: =SUM(M74:M81) -> 1295210 | Q82: Others | X82: =SUM(W73:W81) -> 1333710 | AA82: Douglas | AB82: 20000 | AF82: Ayo | AG82: 30000 | AK82: Ayo | AL82: 30000
B83: Fak Project | C83: 6408765 | G83: Fak Project | H83: 6408765 | L83: Others | Q83: Fak Project | R83: 6408765 | V83: Others | AA83: isya | AB83: 35000 | AF83: Douglas | AG83: 15000 | AK83: Douglas | AL83: 15000
B84: Zarewa Motors | C84: 149500 | G84: Zarewa Motors | H84: 149500 | L84: Fak Project | M84: 6408765 | Q84: Zarewa Motors | R84: 149500 | V84: Fak Project | W84: 6408765 | AC84: =SUM(AB74:AB83) -> 1321210 | AF84: Dahiru | AG84: 124000 | AK84: Auwal Bakari | AL84: 100000
B85: Nurul Siraj | C85: 8930616 | G85: Nurul Siraj | H85: 8930616 | L85: Zarewa Motors | M85: 149500 | Q85: Nurul Siraj | R85: 8930616 | V85: Zarewa Motors | W85: 149500 | AA85: Others | AF85: isya | AG85: 27500 | AK85: Dahiru | AL85: 124000
B86: Mining & Truck | G86: Mining (conzonite) | H86: 2750000 | L86: Nurul Siraj | M86: 8930616 | Q86: Mining (conzonite) | R86: 2750000 | V86: Nurul Siraj | W86: 8930616 | AA86: Fak Project | AB86: 6408765 | AH86: =SUM(AG75:AG85) -> 1422710 | AK86: isya | AL86: 20000
B87: Almadina Hospital | G87: Almadina Hospital | L87: Mining (conzonite) | M87: 2750000 | Q87: Almadina Hospital | V87: Mining (conzonite) | W87: 2750000 | AA87: Zarewa Motors | AB87: 149500 | AF87: Others | AM87: =SUM(AL75:AL86) -> 1525210
B88: Maiduguri | C88: 20620881 | G88: Maiduguri | H88: 20620881 | L88: Almadina Hospital | Q88: Maiduguri | R88: 19470881 | V88: Almadina Hospital | AA88: Nurul Siraj | AB88: 8930616 | AF88: Fak Project | AG88: 6408765 | AK88: Others
D89: =SUM(C83:C88) -> 36109762 | I89: =SUM(H83:H88) -> 38859762 | L89: Maiduguri | M89: 19470881 | O89: =H88-M89 -> 1150000 | S89: =SUM(R83:R88) -> 37709762 | V89: Stromsheild | W89: 2840530 | AA89: Mining (conzonite) | AB89: 2750000 | AF89: Zarewa Motors | AG89: 149500 | AK89: Fak Project | AL89: 6408765
B90: Fix Asset | G90: Fix Asset | N90: =SUM(M84:M89) -> 37709762 | Q90: Fix Asset | V90: Maiduguri | W90: 19470881 | AA90: Almadina Hospital | AF90: Nurul Siraj | AG90: 8930616 | AK90: Zarewa Motors | AL90: 149500
B91: Land and Building | C91: 92242000 | G91: Land and Building | H91: 92242000 | L91: Fix Asset | Q91: Land and Building | R91: 92242000 | X91: =SUM(W84:W90) -> 40550292 | AA91: Global Marori | AB91: 600900 | AF91: Mining (conzonite) | AG91: 2750000 | AK91: Nurul Siraj | AL91: 8930616
B92: Plant and machineries | C92: 6972416 | G92: Plant and machineries | H92: 6972416 | L92: Land and Building | M92: 92242000 | Q92: Plant and machineries | R92: 6972416 | V92: Fix Asset | AA92: Maiduguri | AB92: 19470881 | AF92: Almadina Hospital | AK92: Mining (conzonite) | AL92: 2750000
B93: Furnitures & fittings | C93: 56448 | G93: Furnitures & fittings | H93: 56448 | L93: Plant and machineries | M93: 6972416 | Q93: Furnitures & fittings | R93: 56448 | V93: Land and Building | W93: 92242000 | AC93: =SUM(AB86:AB92) -> 38310662 | AF93: Global Marori | AG93: 600900 | AK93: Almadina Hospital
B94: New machine(steptiles) | C94: 5625000 | G94: New machine(steptiles) | H94: 5625000 | L94: Furnitures & fittings | M94: 56448 | Q94: New machine(steptiles) | R94: 5625000 | V94: Plant and machineries | W94: 6972416 | AA94: Fix Asset | AF94: Maiduguri | AG94: 19470881 | AK94: Global Marori | AL94: 600900
B95: Generator | C95: 534750 | G95: Generator | H95: 534750 | L95: New machine(steptiles) | M95: 5625000 | Q95: Generator | R95: 534750 | V95: Furnitures & fittings | W95: 56448 | AA95: Land and Building | AB95: 92242000 | AH95: =SUM(AG88:AG94) -> 38310662 | AK95: Maiduguri | AL95: 19470881
D96: =SUM(C91:C95) -> 105430614 | I96: =SUM(H91:H95) -> 105430614 | L96: Generator | M96: 534750 | S96: =SUM(R91:R95) -> 105430614 | V96: New machine(steptiles) | W96: 5625000 | AA96: Plant and machineries | AB96: 6972416 | AF96: Fix Asset | AM96: =SUM(AL89:AL95) -> 38310662
D97: =SUM(D66:D96) -> 2.7585063e+08 | I97: =SUM(I61:I96) -> 2.6653156e+08 | N97: =SUM(M92:M96) -> 105430614 | S97: =SUM(S61:S96) -> 2.7225999e+08 | V97: Generator | W97: 534750 | AA97: Furnitures & fittings | AB97: 56448 | AF97: Land and Building | AG97: 92242000 | AK97: Fix Asset
B98: Creditors | G98: Creditors | N98: =SUM(N61:N97) -> 2.7745646e+08 | Q98: Creditors | X98: =SUM(W93:W97) -> 105430614 | AA98: New machine(steptiles) | AB98: 5625000 | AF98: Plant and machineries | AG98: 6972416 | AK98: Land and Building | AL98: 92242000
B99: BOI | D99: 77513411 | G99: BOI | I99: 77513411 | L99: Creditors | Q99: BOI | S99: 76130471 | X99: =SUM(X61:X98) -> 2.4060742e+08 | AA99: Generator | AB99: 534750 | AF99: Furnitures & fittings | AG99: 56448 | AK99: Plant and machineries | AL99: 6972416
B100: Jalingo Branch | D100: 4176893 | G100: Jalingo Branch | I100: 4176893 | L100: BOI | N100: 77513411 | Q100: Jalingo Branch | S100: 2776893 | V100: Creditors | AC100: =SUM(AB95:AB99) -> 105430614 | AF100: New machine(steptiles) | AG100: 5625000 | AK100: Furnitures & fittings | AL100: 56448
B101: Mustapha Sali | D101: 2000000 | G101: Mustapha Sali | I101: 2000000 | L101: Jalingo Branch | N101: 4176893 | Q101: Mustapha Sali | S101: 2000000 | V101: BOI | X101: 74750531 | AC101: =SUM(AC62:AC100) -> 2.4392911e+08 | AF101: Generator | AG101: 534750 | AK101: New machine(steptiles) | AL101: 5625000
B102: Ibrahim Abubakar | D102: 317200 | G102: Ibrahim Abubakar | I102: 317200 | L102: Mustapha Sali | N102: 2000000 | Q102: Ibrahim Abubakar | S102: 317200 | V102: Jalingo Branch | X102: 2776893 | AA102: Creditors | AH102: =SUM(AG97:AG101) -> 105430614 | AK102: Generator | AL102: 534750
B103: Bawa Nafiu | D103: 750000 | G103: Bawa Nafiu | I103: 750000 | L103: Ibrahim Abubakar | N103: 317200 | Q103: Bawa Nafiu | S103: 750000 | V103: Ibrahim Abubakar | X103: 317200 | AA103: BOI | AC103: 74750531 | AH103: =SUM(AH62:AH102) -> 2.4827342e+08 | AM103: =SUM(AL98:AL102) -> 105430614
B104: Strong Kano | D104: 22142100 | G104: Strong Kano | I104: 15898000 | L104: Bawa Nafiu | N104: 750000 | Q104: Strong Kano | S104: 3516700 | V104: Bawa Nafiu | X104: 750000 | AA104: Jalingo Branch | AC104: 2776893 | AF104: Creditors | AM104: =SUM(AM62:AM103) -> 2.5578611e+08
B105: BAWA Abubakar | D105: 300000 | G105: BAWA Abubakar | I105: 300000 | L105: Strong Kano | N105: 14552750 | Q105: BAWA Abubakar | S105: 300000 | V105: Strong Kano | X105: 8302480 | AA105: Ibrahim Abubakar | AC105: 317200 | AF105: BOI | AH105: 74750531 | AK105: Creditors
B106: Global Marori | D106: 17345493 | G106: Global Marori | I106: 17345493 | L106: BAWA Abubakar | N106: 300000 | Q106: Global Marori | S106: 6505043.3 | V106: BAWA Abubakar | X106: 300000 | AA106: Bawa Nafiu | AC106: 750000 | AF106: Jalingo Branch | AH106: 2776893 | AK106: BOI | AM106: 74750531
B107: 5N Ventures | D107: 1000000 | G107: Engr Ozize | I107: 659600 | L107: Global Marori | N107: 6905043.3 | Q107: Engr Ozize | S107: 659600 | V107: Global Marori | X107: 6355043 | AA107: Strong Kano | AC107: 6231520 | AF107: Yola Branch | AH107: 3800000 | AK107: Jalingo Branch | AM107: 2776893
D108: =SUM(D99:D107) -> 1.255451e+08 | G108: Yola Branch | I108: 3800000 | L108: Engr Ozize | N108: 659600 | Q108: Yola Branch | S108: 3800000 | V108: Engr Ozize | X108: 659600 | AA108: Dechimex | AC108: 1174300 | AF108: Ibrahim Abubakar | AH108: 317200 | AK108: Yola Branch | AM108: 3800000
D109: =D97-D108 -> 1.5030553e+08 | G109: Global Scafold | I109: 600000 | L109: Yola Branch | N109: 3800000 | Q109: Obumeck | S109: 5286700 | V109: Yola Branch | X109: 3800000 | AA109: BAWA Abubakar | AC109: 300000 | AF109: Bawa Nafiu | AH109: 750000 | AK109: Ibrahim Abubakar | AM109: 317200
I110: =SUM(I99:I109) -> 1.233606e+08 | L110: Global Scafold | N110: 200000 | Q110: Aisha | S110: 500000 | V110: Aisha | X110: 500000 | AA110: Global Marori | AC110: 5858043 | AF110: Strong Kano | AH110: 0 | AK110: Bawa Nafiu | AM110: 750000
I111: =I97-I110 -> 1.4317096e+08 | L111: Aisha | N111: 500000 | Q111: hon felex | S111: 1000000 | V111: hon felex | X111: 1000000 | AA111: Engr Ozize | AC111: 659600 | AF111: BAWA Abubakar | AH111: 300000 | AK111: Strong Kano | AM111: 4712853
L112: hon felex | N112: 1000000 | Q112: tanko muktar | S112: 190000 | V112: Capricon digital | X112: 2000000 | AA112: Yola Branch | AC112: 3800000 | AF112: Global Marori | AH112: 5858043 | AK112: BAWA Abubakar | AM112: 300000
...

Sheet 2024
AW1: Zarewa Aluminium And Plastics Ltd Kaduna
A2: Zarewa Aluminium And Plastics Ltd Kaduna | E2: Zarewa Aluminium And Plastics Ltd Kaduna | I2: Zarewa Aluminium And Plastics Ltd Kaduna | M2: Zarewa Aluminium And Plastics Ltd Kaduna | Q2: Zarewa Aluminium And Plastics Ltd Kaduna | U2: Zarewa Aluminium And Plastics Ltd Kaduna | Y2: Zarewa Aluminium And Plastics Ltd Kaduna | AC2: Zarewa Aluminium And Plastics Ltd Kaduna | AH2: Zarewa Aluminium And Plastics Ltd Kaduna | AM2: Zarewa Aluminium And Plastics Ltd Kaduna | AR2: Zarewa Aluminium And Plastics Ltd Kaduna | AW2: Production Account for the month end December
A3: Production Account for the month end January | E3: Production Account for the month end Febuary | I3: Production Account for the month end MARCH | M3: Production Account for the month end April | Q3: Production Account for the month end May | U3: Production Account for the month end June | Y3: Production Account for the month end JuLY | AC3: Production Account for the month end August | AH3: Production Account for the month end September | AM3: Production Account for the month end October | AR3: Production Account for the month end Novemebr | AW3: Opening Stock | AY3: =AS8 -> 177934700
A4: Opening Stock | C4: =101533360 -> 101533360 | E4: Opening Stock | G4: =B8 -> 106588500 | I4: Opening Stock | K4: =F8 -> 104326450 | M4: Opening Stock | O4: =J8 -> 172746600 | Q4: Opening Stock | S4: =N8 -> 182105250 | U4: Opening Stock | W4: =R8 -> 219791680 | Y4: Opening Stock | AA4: =V8 -> 198432160 | AC4: Opening Stock | AE4: =Z8 -> 139718400 | AH4: Opening Stock | AJ4: =AD8 -> 165682950 | AM4: Opening Stock | AO4: =AI8 -> 183265550 | AR4: Opening Stock | AT4: =AN8 -> 170146900 | AW4: Purchases | AY4: 87160616
A5: Purchases | C5: 44129250 | E5: Purchases | G5: 67998481 | I5: Purchases | K5: 1.5343349e+08 | M5: Purchases | O5: 90532903 | Q5: Purchases | S5: 152256400 | U5: Purchases | W5: 54118402 | Y5: Purchases | AA5: 64288213 | AC5: Purchases | AE5: 118853610 | AH5: Purchases | AJ5: 153116585 | AM5: Purchases | AO5: 75093586 | AR5: Purchases | AT5: 185001035 | AW5: Accessories | AY5: 1001800
A6: Carriage Inward | C6: 508500 | E6: Carriage Inward | G6: 1421800 | I6: Carriage Inward | K6: 1350000 | M6: Carriage Inward | O6: 1870000 | Q6: Carriage Inward | S6: 1251000 | U6: Carriage Inward | W6: 335000 | Y6: Carriage Inward | AA6: 512500 | AC6: Carriage Inward | AE6: 1309800 | AH6: Carriage Inward | AJ6: 1714000 | AM6: Carriage Inward | AO6: 1640675 | AR6: Carriage Inward | AT6: 1496000 | AW6: Carriage Inward | AY6: 1167000
C7: =SUM(C4:C6) -> 146171110 | G7: =SUM(G4:G6) -> 176008781 | K7: =SUM(K4:K6) -> 2.5910994e+08 | O7: =SUM(O4:O6) -> 265149503 | S7: =SUM(S4:S6) -> 335612650 | W7: =SUM(W4:W6) -> 274245082 | AA7: =SUM(AA4:AA6) -> 263232873 | AE7: =SUM(AE4:AE6) -> 259881810 | AJ7: =SUM(AJ4:AJ6) -> 320513535 | AO7: =SUM(AO4:AO6) -> 259999811 | AT7: =SUM(AT4:AT6) -> 356643935 | AY7: =SUM(AY3:AY6) -> 267264116
A8: Closing Stock | B8: 106588500 | E8: Closing Stock | F8: 104326450 | I8: Closing Stock | J8: 172746600 | M8: Closing Stock | N8: 182105250 | Q8: Closing Stock | R8: =Stock!U144 -> 219791680 | U8: Closing Stock | V8: =Stock!AC145 -> 198432160 | Y8: Closing Stock | Z8: =Stock!AK135 -> 139718400 | AC8: Closing Stock | AD8: =Stock!AR145 -> 165682950 | AH8: Closing Stock | AI8: =Stock!AY142 -> 183265550 | AM8: Closing Stock | AN8: =Stock!BF136 -> 170146900 | AR8: Closing Stock | AS8: =Stock!BM114 -> 177934700 | AW8: Closing Stock | AX8: =Stock!BT112 -> 122651950
C9: =C7-B8 -> 39582610 | G9: =G7-F8 -> 71682331 | K9: =K7-J8 -> 86363337 | O9: =O7-N8 -> 83044253 | S9: =S7-R8 -> 115820970 | W9: =W7-V8 -> 75812922 | AA9: =AA7-Z8 -> 123514473 | AE9: =AE7-AD8 -> 94198860 | AJ9: =AJ7-AI8 -> 137247985 | AO9: =AO7-AN8 -> 89852911 | AT9: =AT7-AS8 -> 178709235 | AY9: =AY7-AX8 -> 144612166
A11: Factory Overhead | E11: Factory Overhead | I11: Factory Overhead | M11: Factory Overhead | Q11: Factory Overhead | U11: Factory Overhead | Y11: Factory Overhead | AC11: Factory Overhead | AH11: Factory Overhead | AM11: Factory Overhead | AR11: Factory Overhead | AW11: Factory Overhead
A12: Wages | B12: 253678.67 | E12: Wages | F12: 278680 | I12: Wages | J12: 281378.67 | M12: Wages | N12: 281378 | Q12: Wages | R12: 281378 | U12: Wages | V12: 281378 | Y12: Wages | Z12: 281378 | AC12: Wages | AD12: 281378 | AH12: Wages | AI12: 281378 | AM12: Wages | AN12: 281378 | AR12: Wages | AS12: 400000 | AW12: Wages | AX12: 420000
A13: Fuel & Lubricant | B13: 282500 | E13: Fuel & Lubricant | F13: 223000 | I13: Fuel & Lubricant | J13: 672000 | M13: Fuel & Lubricant | N13: 380500 | Q13: Fuel & Lubricant | R13: 384500 | U13: Fuel & Lubricant | V13: 433000 | Y13: Fuel & Lubricant | Z13: 480000 | AC13: Fuel & Lubricant | AD13: 647000 | AH13: Fuel & Lubricant | AI13: 560000 | AM13: Fuel & Lubricant | AN13: 400000 | AR13: Fuel & Lubricant | AS13: 515000 | AW13: Fuel & Lubricant | AX13: 555000
A14: Electricity Bill | B14: 20000 | E14: Electricity Bill | F14: 12500 | I14: Electricity Bill | J14: 15500 | M14: Electricity Bill | N14: 11000 | Q14: Electricity Bill | R14: 16000 | U14: Electricity Bill | V14: 62000 | Y14: Electricity Bill | Z14: 45000 | AC14: Electricity Bill | AD14: 5000 | AH14: Electricity Bill | AI14: 0 | AM14: Electricity Bill | AN14: 35000 | AR14: Electricity Bill | AS14: 0 | AW14: Electricity Bill | AX14: 0
A15: Maintainace | B15: 105500 | E15: Maintainace | F15: 302500 | I15: Maintainace | J15: 682600 | M15: Maintainace | N15: 684500 | Q15: Maintainace | R15: 1325650 | U15: Maintainace | V15: 659600 | Y15: Maintainace | Z15: 425000 | AC15: Maintainace | AD15: 612200 | AH15: Maintainace | AI15: 771576 | AM15: Maintainace | AN15: 514700 | AR15: Maintainace | AS15: 93000 | AW15: Maintainace | AX15: 937500
A16: Depreciation | B16: 110000 | E16: Depreciation | F16: 110000 | I16: Depreciation | J16: 110000 | M16: Depreciation | N16: 110000 | Q16: Depreciation | R16: 110000 | U16: Depreciation | V16: 110000 | Y16: Depreciation | Z16: 110000 | AC16: Depreciation | AD16: 110000 | AH16: Depreciation | AI16: 110000 | AM16: Depreciation | AN16: 110000 | AR16: Depreciation | AS16: 110000 | AW16: Depreciation | AX16: 110000
B17: =SUM(B12:B16) -> 771678.67 | F17: =SUM(F12:F16) -> 926680 | J17: =SUM(J12:J16) -> 1761478.7 | N17: =SUM(N12:N16) -> 1467378 | R17: =SUM(R12:R16) -> 2117528 | V17: =SUM(V12:V16) -> 1545978 | Z17: =SUM(Z12:Z16) -> 1341378 | AD17: =SUM(AD12:AD16) -> 1655578 | AI17: =SUM(AI12:AI16) -> 1722954 | AN17: =SUM(AN12:AN16) -> 1341078 | AS17: =SUM(AS12:AS16) -> 1118000 | AX17: =SUM(AX12:AX16) -> 2022500
C18: =C9+B17 -> 40354289 | G18: =G9+F17 -> 72609011 | K18: =K9+J17 -> 88124816 | O18: =O9+N17 -> 84511631 | S18: =S9+R17 -> 117938498 | W18: =W9+V17 -> 77358900 | AA18: =AA9+Z17 -> 124855851 | AE18: =AE9+AD17 -> 95854438 | AJ18: =AJ9+AI17 -> 138970939 | AO18: =AO9+AN17 -> 91193989 | AT18: =AT9+AS17 -> 179827235 | AY18: =AY9+AX17 -> 146634666
A20: Zarewa Aluminium And Plastics Ltd Kaduna | E20: Zarewa Aluminium And Plastics Ltd Kaduna | I20: Zarewa Aluminium And Plastics Ltd Kaduna | M20: Zarewa Aluminium And Plastics Ltd Kaduna | Q20: Zarewa Aluminium And Plastics Ltd Kaduna | U20: Zarewa Aluminium And Plastics Ltd Kaduna | Y20: Zarewa Aluminium And Plastics Ltd Kaduna | AC20: Zarewa Aluminium And Plastics Ltd Kaduna | AH20: Zarewa Aluminium And Plastics Ltd Kaduna | AM20: Zarewa Aluminium And Plastics Ltd Kaduna | AR20: Zarewa Aluminium And Plastics Ltd Kaduna | AW20: Zarewa Aluminium And Plastics Ltd Kaduna
A21: Profit and Lost Account for the month end Janaury | E21: Profit and Lost Account for the month end Febuary | I21: Profit and Lost Account for the month end Febuary | M21: Profit and Lost Account for the month end April | Q21: Profit and Lost Account for the month end May | U21: Profit and Lost Account for the month end June | Y21: Profit and Lost Account for the month end June | AC21: Profit and Lost Account for the month end August | AH21: Profit and Lost Account for the month end September | AM21: Profit and Lost Account for the month end Octorber | AR21: Profit and Lost Account for the month end Novemeber | AW21: Profit and Lost Account for the month end Decemebr
A22: Opening Stock | E22: Opening Stock | I22: Opening Stock | M22: Opening Stock | Q22: Opening Stock | U22: Opening Stock | Y22: Opening Stock | AC22: Opening Stock | AH22: Opening Stock | AM22: Opening Stock | AR22: Opening Stock | AW22: Opening Stock
A23: Sales | C23: 53323698 | E23: Sales | G23: 104795105 | I23: Sales | K23: 1.236522e+08 | M23: Sales | O23: 95528700 | Q23: Sales | S23: 163001075 | U23: Sales | W23: 84341891 | Y23: Sales | AA23: 152000000 | AC23: Sales | AE23: 130134588 | AH23: Sales | AJ23: 157461273 | AM23: Sales | AO23: 102424103 | AR23: Sales | AT23: 231774332 | AW23: Sales | AY23: 172755778
A24: Refund | B24: 4697544 | E24: Refund | F24: 7973518 | I24: Refund | J24: 11245242 | M24: Refund | N24: 8153703 | Q24: Refund | R24: 6426503 | U24: Refund | V24: 10779777 | Y24: Refund | Z24: 15848223 | AC24: Refund | AD24: 18137530 | AH24: Refund | AI24: 17842400 | AM24: Refund | AN24: 12640800 | AR24: Refund | AS24: 33183934 | AW24: Refund | AX24: 23930230
A25: Net Sales | C25: =C23-B24 -> 48626154 | E25: Net Sales | G25: =G23-F24 -> 96821587 | I25: Net Sales | K25: =K23-J24 -> 1.1240695e+08 | M25: Net Sales | O25: =O23-N24 -> 87374997 | Q25: Net Sales | S25: =S23-R24 -> 156574572 | U25: Net Sales | W25: =W23-V24 -> 73562114 | Y25: Net Sales | AA25: =AA23-Z24 -> 136151777 | AC25: Net Sales | AE25: =AE23-AD24 -> 111997058 | AH25: Net Sales | AJ25: =AJ23-AI24 -> 139618873 | AM25: Net Sales | AO25: =AO23-AN24 -> 89783303 | AR25: Net Sales | AT25: =AT23-AS24 -> 198590398 | AW25: Net Sales | AY25: =AY23-AX24 -> 148825548
A26: Production Cost | B26: =C18 -> 40354289 | E26: Production Cost | F26: =G18 -> 72609011 | I26: Production Cost | J26: =K18 -> 88124816 | M26: Production Cost | N26: =O18 -> 84511631 | Q26: Production Cost | R26: =S18 -> 117938498 | U26: Production Cost | V26: =W18 -> 77358900 | Y26: Production Cost | Z26: =AA18 -> 124855851 | AC26: Production Cost | AD26: =AE18 -> 95854438 | AH26: Production Cost | AI26: =AJ18 -> 138970939 | AM26: Production Cost | AN26: =AO18 -> 91193989 | AR26: Production Cost | AS26: =AT18 -> 179827235 | AW26: Production Cost | AX26: =AY18 -> 146634666
A27: Closing Stock | B27: 0 | E27: Closing Stock | F27: 0 | I27: Closing Stock | J27: 0 | M27: Closing Stock | N27: 0 | Q27: Closing Stock | R27: 0 | U27: Closing Stock | V27: 0 | Y27: Closing Stock | Z27: 0 | AC27: Closing Stock | AD27: 0 | AH27: Closing Stock | AI27: 0 | AM27: Closing Stock | AN27: 0 | AR27: Closing Stock | AS27: 0 | AW27: Closing Stock | AX27: 0
B28: =SUM(B26:B27) -> 40354289 | F28: =SUM(F26:F27) -> 72609011 | J28: =SUM(J26:J27) -> 88124816 | N28: =SUM(N26:N27) -> 84511631 | R28: =SUM(R26:R27) -> 117938498 | V28: =SUM(V26:V27) -> 77358900 | Z28: =SUM(Z26:Z27) -> 124855851 | AD28: =SUM(AD26:AD27) -> 95854438 | AI28: =SUM(AI26:AI27) -> 138970939 | AN28: =SUM(AN26:AN27) -> 91193989 | AS28: =SUM(AS26:AS27) -> 179827235 | AX28: =SUM(AX26:AX27) -> 146634666
A29: Gross Profit | C29: =C25-B28 -> 8271865.3 | E29: Gross Profit | G29: =G25-F28 -> 24212576 | I29: Gross Profit | K29: =K25-J28 -> 24282138 | M29: Gross Profit | O29: =O25-N28 -> 2863366 | Q29: Gross Profit | S29: =S25-R28 -> 38636074 | U29: Gross Profit | W29: =W25-V28 -> -3796786 | Y29: Gross Profit | AA29: =AA25-Z28 -> 11295926 | AC29: Gross Profit | AE29: =AE25-AD28 -> 16142620 | AH29: Gross Profit | AJ29: =AJ25-AI28 -> 647934 | AM29: Gross Profit | AO29: =AO25-AN28 -> -1410686 | AR29: Gross Profit | AT29: =AT25-AS28 -> 18763163 | AW29: Gross Profit | AY29: =AY25-AX28 -> 2190882
A31: Admin Expenses | E31: Admin Expenses | I31: Admin Expenses | M31: Admin Expenses | Q31: Admin Expenses | U31: Admin Expenses | Y31: Admin Expenses | AC31: Admin Expenses | AH31: Admin Expenses | AM31: Admin Expenses | AR31: Admin Expenses | AW31: Admin Expenses
A32: Admin exp | B32: 0 | E32: Admin exp | F32: 0 | I32: Admin exp | J32: 0 | M32: Admin exp | N32: 70000 | Q32: Admin exp | R32: 75000 | U32: Admin exp | V32: 82000 | Y32: Admin exp | Z32: 70000 | AC32: Admin exp | AD32: 100000 | AH32: Admin exp | AI32: 74000 | AM32: Admin exp | AN32: 10000 | AR32: Admin exp | AS32: 15000 | AW32: Admin exp | AX32: 95000
A33: Admin Salary | B33: 377465.6 | E33: Admin Salary | F33: 337465.6 | I33: Admin Salary | J33: 398065.6 | M33: Admin Salary | N33: 398000 | Q33: Admin Salary | R33: 398000 | U33: Admin Salary | V33: 398000 | Y33: Admin Salary | Z33: 398000 | AC33: Admin Salary | AD33: 398000 | AH33: Admin Salary | AI33: 398000 | AM33: Admin Salary | AN33: 410000 | AR33: Admin Salary | AS33: 750000 | AW33: Admin Salary | AX33: 750000
A34: Bank Charge | B34: 5678.18 | E34: Bank Charge | F34: 0 | I34: Bank Charge | J34: 35475 | M34: Bank Charge | N34: 0 | Q34: Bank Charge | R34: 22827 | U34: Bank Charge | Y34: Bank Charge | AC34: Bank Charge | AH34: Bank Charge | AM34: Bank Charge | AR34: Bank Charge | AS34: 4312 | AW34: Bank Charge | AX34: 5331.2
A35: Office Expenses | B35: 56000 | E35: Office Expenses | F35: 99000 | I35: Office Expenses | J35: 74150 | M35: Office Expenses | N35: 55500 | Q35: Office Expenses | R35: 201000 | U35: Office Expenses | V35: 88500 | Y35: Office Expenses | Z35: 205000 | AC35: Office Expenses | AD35: 58000 | AH35: Office Expenses | AI35: 59000 | AM35: Office Expenses | AN35: 125654 | AR35: Office Expenses | AS35: 107000 | AW35: Office Expenses | AX35: 377200
A36: Professional Fee | B36: 361000 | E36: Professional Fee | F36: 50000 | I36: Professional Fee | J36: 0 | M36: Professional Fee | N36: 0 | Q36: Professional Fee | R36: 0 | U36: Professional Fee | V36: 150000 | Y36: Professional Fee | Z36: 150000 | AC36: Professional Fee | AD36: 167000 | AH36: Professional Fee | AM36: Professional Fee | AR36: Professional Fee | AS36: 150000 | AW36: Professional Fee | AX36: 0
A37: Tax | B37: 0 | E37: Tax | F37: 872000 | I37: Tax | J37: 0 | M37: Tax | N37: 366205 | Q37: Tax | R37: 10000 | U37: Tax | V37: 52500 | Y37: Tax | Z37: 593000 | AC37: Tax | AD37: 0 | AH37: Tax | AI37: 425000 | AM37: Tax | AN37: 650000 | AR37: Tax | AS37: 880841 | AW37: Tax | AX37: 377186
A38: Pension | B38: 53900 | E38: Pension | F38: 0 | I38: Pension | J38: 0 | M38: Pension | N38: 0 | Q38: Pension | R38: 0 | U38: Pension | Y38: Pension | AC38: Pension | AH38: Pension | AM38: Pension | AN38: 1000000 | AR38: Pension | AW38: Pension | AX38: 0
A39: Security | B39: 0 | E39: Security | F39: 25000 | I39: Security | J39: 25000 | M39: Security | N39: 0 | Q39: Security | R39: 0 | U39: Security | Y39: Security | AC39: Security | AH39: Security | AM39: Security | AR39: Security | AS39: 30000 | AW39: Security | AX39: 210000
A40: Intrest | B40: 0 | E40: Intrest | F40: 0 | I40: Intrest | J40: 0 | M40: Intrest | N40: 0 | Q40: Intrest | R40: 0 | U40: Intrest | Y40: Intrest | AC40: Intrest | AH40: Intrest | AM40: Intrest | AR40: Intrest | AW40: Intrest
A41: Welfare | B41: 182800 | E41: Welfare | F41: 125000 | I41: Welfare | J41: 887000 | M41: Welfare | N41: 0 | Q41: Welfare | R41: 0 | U41: Welfare | Y41: Welfare | AC41: Welfare | AH41: Welfare | AM41: Welfare | AR41: Welfare | AW41: Welfare | AX41: 300000
A42: Zakat & Sallah | B42: 0 | E42: Zakat & Sallah | F42: 0 | I42: Zakat & Sallah | J42: 541527 | M42: Zakat & Sallah | N42: 120000 | Q42: Zakat & Sallah | R42: 0 | U42: Zakat & Sallah | V42: 400000 | Y42: Zakat & Sallah | Z42: 0 | AC42: Zakat & Sallah | AD42: 0 | AH42: Zakat & Sallah | AI42: 0 | AM42: Zakat & Sallah | AN42: 0 | AR42: Zakat & Sallah | AW42: Zakat & Sallah
B43: =SUM(B32:B42) -> 1036843.8 | F43: =SUM(F32:F42) -> 1508465.6 | J43: =SUM(J32:J42) -> 1961217.6 | N43: =SUM(N32:N42) -> 1009705 | R43: =SUM(R32:R42) -> 706827 | V43: =SUM(V32:V42) -> 1171000 | Z43: =SUM(Z32:Z42) -> 1416000 | AD43: =SUM(AD32:AD42) -> 723000 | AI43: =SUM(AI32:AI42) -> 956000 | AN43: =SUM(AN32:AN42) -> 2195654 | AS43: =SUM(AS32:AS42) -> 1937153 | AX43: =SUM(AX32:AX42) -> 2114717.2
A44: Net Profit | C44: =C29-B43 -> 7235021.5 | E44: Net Profit | G44: =G29-F43 -> 22704110 | I44: Net Profit | K44: =K29-J43 -> 22320921 | M44: Net Profit | O44: =O29-N43 -> 1853661 | Q44: Net Profit | S44: =S29-R43 -> 37929247 | U44: Net Profit | W44: =W29-V43 -> -4967786 | Y44: Net Profit | AA44: =AA29-Z43 -> 9879926 | AC44: Net Profit | AE44: =AE29-AD43 -> 15419620 | AH44: Net Profit | AJ44: =AJ29-AI43 -> -308066 | AM44: Net Profit | AO44: =AO29-AN43 -> -3606340 | AR44: Net Profit | AT44: =AT29-AS43 -> 16826010 | AW44: Net Profit | AY44: =AY29-AX43 -> 76164.8
A46: HQ | B46: 500000 | E46: HQ | F46: 900000 | I46: HQ | J46: 500000 | M46: HQ | N46: 500000 | Q46: HQ | R46: 500000 | U46: HQ | V46: 500000 | Y46: HQ | Z46: 500000 | AC46: HQ | AD46: 500000 | AH46: HQ | AI46: 500000 | AM46: HQ | AN46: 706000 | AR46: HQ | AW46: HQ
A47: Chairman Withdrawal | B47: 377000 | E47: Chairman Withdrawal | F47: 269600 | I47: Chairman Withdrawal | J47: 335000 | M47: Chairman Withdrawal | N47: 2337000 | Q47: Chairman Withdrawal | R47: 1154000 | U47: Chairman Withdrawal | V47: 330000 | Y47: Chairman Withdrawal | Z47: 162000 | AC47: Chairman Withdrawal | AD47: 2348000 | AH47: Chairman Withdrawal | AI47: 48500 | AM47: Chairman Withdrawal | AN47: 190000 | AR47: Chairman Withdrawal | AS47: 2315000 | AW47: Chairman Withdrawal | AX47: 678000
A48: truck | B48: 39000 | E48: truck | F48: 86000 | I48: truck | J48: 306000 | M48: truck | N48: 127500 | Q48: truck | R48: 36000 | U48: truck | V48: 60000 | Y48: truck | Z48: 61000 | AC48: truck | AD48: 0 | AH48: truck | AI48: 1126000 | AM48: truck &mining | AN48: 1000000 | AR48: truck &mining | AW48: truck &mining
A49: Mining | B49: 69000 | E49: Mining | F49: 39000 | I49: Mining | J49: 0 | M49: Mining | N49: 0 | Q49: Security Room | R49: 1213750 | U49: ASHRAF FEES | V49: 600000 | Z49: 0 | AD49: 0 | AI49: 0 | AN49: 0 | AS49: 0 | AX49: 0
B50: =SUM(B46:B49) -> 985000 | F50: =SUM(F46:F49) -> 1294600 | J50: =SUM(J46:J49) -> 1141000 | N50: =SUM(N46:N49) -> 2964500 | R50: =SUM(R46:R49) -> 2903750 | V50: =SUM(V46:V49) -> 1490000 | Z50: =SUM(Z46:Z49) -> 723000 | AD50: =SUM(AD46:AD49) -> 2848000 | AI50: =SUM(AI46:AI49) -> 1674500 | AN50: =SUM(AN46:AN49) -> 1896000 | AS50: =SUM(AS46:AS49) -> 2315000 | AX50: =SUM(AX46:AX49) -> 678000
C51: =C44-B50 -> 6250021.5 | G51: =G44-F50 -> 21409510 | K51: =K44-J50 -> 21179921 | O51: =O44-N50 -> -1110839 | S51: =S44-R50 -> 35025497 | W51: =W44-V50 -> -6457786 | AA51: =AA44-Z50 -> 9156926 | AE51: =AE44-AD50 -> 12571620 | AJ51: =AJ44-AI50 -> -1982566 | AO51: =AO44-AN50 -> -5502340 | AT51: =AT44-AS50 -> 14511010 | AY51: =AY44-AX50 -> -601835.2
A53: Zarewa Aluminium And Plastics Ltd Kaduna | E53: Zarewa Aluminium And Plastics Ltd Kaduna | I53: Zarewa Aluminium And Plastics Ltd Kaduna | M53: Zarewa Aluminium And Plastics Ltd Kaduna | Q53: Zarewa Aluminium And Plastics Ltd Kaduna | U53: Zarewa Aluminium And Plastics Ltd Kaduna | Y53: Zarewa Aluminium And Plastics Ltd Kaduna | AC53: Zarewa Aluminium And Plastics Ltd Kaduna | AH53: Zarewa Aluminium And Plastics Ltd Kaduna | AM53: Zarewa Aluminium And Plastics Ltd Kaduna | AR53: Zarewa Aluminium And Plastics Ltd Kaduna | AW53: Zarewa Aluminium And Plastics Ltd Kaduna
A54: Asset and liability Account for the month end January | E54: Asset and liability Account for the month end Febuary | I54: Asset and liability Account for the month end Febuary | M54: Asset and liability Account for the month end April | Q54: Asset and liability Account for the month end may | U54: Asset and liability Account for the month end June | Y54: Asset and liability Account for the month end June | AC54: Asset and liability Account for the month end August | AH54: Asset and liability Account for the month end September | AM54: Asset and liability Account for the month end October | AR54: Asset and liability Account for the month end November | AW54: Asset and liability Account for the month end Decemebr
A55: ClosinG Stock | B55: =B8 -> 106588500 | E55: ClosinG Stock | F55: =F8 -> 104326450 | I55: ClosinG Stock | J55: =J8 -> 172746600 | M55: ClosinG Stock | N55: =N8 -> 182105250 | Q55: ClosinG Stock | R55: =R8 -> 219791680 | U55: ClosinG Stock | V55: =V8 -> 198432160 | Y55: ClosinG Stock | Z55: =Z8 -> 139718400 | AC55: ClosinG Stock | AD55: =AD8 -> 165682950 | AH55: ClosinG Stock | AI55: =AI8 -> 183265550 | AM55: ClosinG Stock | AN55: =AN8 -> 170146900 | AR55: ClosinG Stock | AS55: =AS8 -> 177934700 | AW55: ClosinG Stock | AX55: =AX8 -> 122651950
A56: Cash at hand | B56: 72342 | E56: Cash at hand | F56: 2296420 | I56: Cash at hand | J56: 733900 | M56: Cash at hand | N56: 1929615 | Q56: Cash at hand | R56: -1304605 | U56: Cash at hand | V56: -204311 | Y56: Cash at hand | Z56: 1866137 | AC56: Cash at hand | AD56: 1180511 | AH56: Cash at hand | AI56: 3750822 | AM56: Cash at hand | AN56: 3750822 | AR56: Cash at hand | AS56: 3838067 | AW56: Cash at hand | AX56: 410040
A57: Gt Bank | B57: 5233045 | E57: Gt Bank | F57: 12645180 | I57: Gt Bank | J57: 2882789.6 | M57: Gt Bank | N57: 7039303 | Q57: Gt Bank | R57: 1158 | U57: Gt Bank | V57: 78360 | Y57: Gt Bank | Z57: 1825337 | AC57: Gt Bank | AD57: 1846922 | AH57: Gt Bank | AI57: 298715 | AM57: Gt Bank | AN57: 2711241 | AR57: Gt Bank | AS57: 555919 | AW57: Gt Bank | AX57: 3497611
A58: Eco Bank | B58: 0 | E58: Eco Bank | F58: 5866825.2 | I58: Eco Bank | J58: 754096 | M58: Eco Bank | N58: 3803189 | Q58: Eco Bank | R58: 38000 | U58: Eco Bank | V58: 2151225 | Y58: Eco Bank | Z58: 184000 | AC58: Eco Bank | AD58: 0 | AH58: Eco Bank | AI58: 0 | AM58: Eco Bank | AN58: 0 | AR58: Eco Bank | AS58: 282572.09 | AW58: Eco Bank | AX58: 1249021.3
A59: Jaiz Bank | B59: 278042 | E59: Jaiz Bank | F59: 278042 | I59: Jaiz Bank | J59: 278042 | M59: Jaiz Bank | N59: 278042 | Q59: Jaiz Bank | R59: 278042 | U59: Jaiz Bank | V59: 278042 | Y59: Jaiz Bank | Z59: 278042 | AC59: Jaiz Bank | AD59: 278042 | AH59: Jaiz Bank | AI59: 278042 | AM59: Jaiz Bank | AN59: 278042 | AR59: Jaiz Bank | AS59: 278042 | AW59: Jaiz Bank | AX59: 278042
A60: Taj bank | B60: 8523888 | E60: Taj bank | F60: 19465000 | I60: Taj bank | J60: 5883466 | M60: Taj bank | N60: 7039303.7 | Q60: Taj bank | R60: 6080056 | U60: Taj bank | V60: 872086 | Y60: Taj bank | Z60: 15500509 | AC60: Taj bank | AD60: 4045193 | AH60: Taj bank | AI60: 7822514 | AM60: Taj bank | AN60: 5137683 | AR60: Taj bank | AS60: 15006209 | AW60: Taj bank | AX60: 21448722
C61: =SUM(B55:B60) -> 120695817 | G61: =SUM(F55:F60) -> 1.4487792e+08 | K61: =SUM(J55:J60) -> 1.8327889e+08 | O61: =SUM(N55:N60) -> 2.021947e+08 | S61: =SUM(R55:R60) -> 224884331 | W61: =SUM(V55:V60) -> 201607562 | AA61: =SUM(Z55:Z60) -> 159372425 | AE61: =SUM(AD55:AD60) -> 173033618 | AJ61: =SUM(AI55:AI60) -> 195415643 | AO61: =SUM(AN55:AN60) -> 182024688 | AT61: =SUM(AS55:AS60) -> 1.9789551e+08 | AY61: =SUM(AX55:AX60) -> 1.4953539e+08
A62: Customer Debth | E62: Customer Debth | I62: Customer Debth | M62: Customer Debth | Q62: Customer Debth | U62: Customer Debth | Y62: Customer Debth | AC62: Customer Debth | AH62: Customer Debth | AM62: Customer Debth | AR62: Customer Debth | AW62: Customer Debth
A63: Abdul Bawa | B63: 500000 | E63: Abdul Bawa | F63: 500000 | I63: Abdul Bawa | J63: 500000 | M63: Abdul Bawa | N63: 500000 | Q63: Abdul Bawa | R63: 500000 | U63: Abdul Bawa | V63: 500000 | Y63: Abdul Bawa | Z63: 500000 | AC63: Abdul Bawa | AD63: 500000 | AH63: Abdul Bawa | AI63: 500000 | AM63: Abdul Bawa | AN63: 500000 | AR63: Abdul Bawa | AS63: 500000 | AW63: Abdul Bawa | AX63: 500000
A64: Jamil Sani | B64: 101300 | E64: Jamil Sani | F64: 101300 | I64: Jamil Sani | J64: 101300 | M64: Jamil Sani | N64: 101300 | Q64: Jamil Sani | R64: 101300 | U64: Jamil Sani | V64: 101300 | Y64: Jamil Sani | Z64: 101300 | AC64: Jamil Sani | AD64: 101300 | AH64: Jamil Sani | AI64: 101300 | AM64: Jamil Sani | AN64: 101300 | AR64: Jamil Sani | AS64: 101300 | AW64: Jamil Sani | AX64: 101300
A65: Alh sani Katsina | B65: 50000 | E65: Alh sani Katsina | F65: 50000 | I65: Alh sani Katsina | J65: 50000 | M65: Alh sani Katsina | N65: 50000 | Q65: Alh sani Katsina | R65: 50000 | U65: Alh sani Katsina | V65: 50000 | Y65: Alh sani Katsina | Z65: 50000 | AC65: Alh sani Katsina | AD65: 50000 | AH65: Alh sani Katsina | AI65: 50000 | AM65: Alh sani Katsina | AN65: 50000 | AR65: Alh sani Katsina | AS65: 50000 | AW65: Alh sani Katsina | AX65: 50000
C66: =SUM(B63:B65) -> 651300 | G66: =SUM(F63:F65) -> 651300 | K66: =SUM(J63:J65) -> 651300 | O66: =SUM(N63:N65) -> 651300 | S66: =SUM(R63:R65) -> 651300 | W66: =SUM(V63:V65) -> 651300 | AA66: =SUM(Z63:Z65) -> 651300 | AE66: =SUM(AD63:AD65) -> 651300 | AJ66: =SUM(AI63:AI65) -> 651300 | AO66: =SUM(AN63:AN65) -> 651300 | AT66: =SUM(AS63:AS65) -> 651300 | AY66: =SUM(AX63:AX65) -> 651300
A67: Staff Loan | E67: Staff Loan | I67: Staff Loan | M67: Staff Loan | Q67: Staff Loan | U67: Staff Loan | Y67: Staff Loan | AC67: Staff Loan | AH67: Staff Loan | AM67: Staff Loan | AR67: Staff Loan | AW67: Staff Loan
A68: Alh Bala Muazu | B68: 800000 | E68: Alh Bala Muazu | F68: 760000 | I68: Alh Bala Muazu | J68: 710000 | M68: Alh Bala Muazu | N68: 670000 | Q68: Alh Bala Muazu | R68: 630000 | U68: Alh Bala Muazu | V68: 590000 | Y68: Alh Bala Muazu | Z68: 800000 | AC68: Alh Bala Muazu | AD68: 760000 | AH68: Alh Bala Muazu | AI68: 720000 | AM68: Alh Bala Muazu | AN68: 680000 | AR68: Alh Bala Muazu | AS68: 640000 | AW68: Alh Bala Muazu | AX68: 600000
A69: Haruna | B69: 50000 | E69: Haruna | F69: 40000 | I69: Haruna | J69: 30000 | M69: Haruna | N69: 20000 | Q69: Haruna | R69: 30000 | U69: Haruna | V69: 20000 | Y69: Haruna | Z69: 10000 | AC69: Bilyaminu maiha | AD69: 300000 | AH69: Bilyaminu maiha | AI69: 300000 | AM69: Bilyaminu maiha | AN69: 300000 | AR69: Bilyaminu maiha | AS69: 300000 | AW69: Bilyaminu maiha | AX69: 300000
A70: Hannatu | B70: 0 | E70: Mal Amadu | F70: 90000 | I70: Mal Amadu | J70: 90000 | M70: Mal Amadu | N70: 80000 | Q70: Mal Amadu | R70: 80000 | U70: Mal Amadu | V70: 80000 | Y70: Mal Amadu | Z70: 80000 | AC70: Mal Amadu | AD70: 80000 | AH70: Mal Amadu | AI70: 80000 | AM70: Mal Amadu | AN70: 50000 | AO70: paid | AR70: Dahiru | AS70: 150000 | AW70: Dahiru | AX70: 150000
A71: Mal Amadu | B71: 90000 | E71: Laraba | F71: 20000 | I71: Laraba | J71: 15000 | M71: Laraba | N71: 10000 | Q71: Laraba | R71: 5000 | U71: Yauba | V71: 50000 | Y71: Yauba | Z71: 50000 | AC71: Yauba | AD71: 30000 | AH71: Yauba | AI71: 20000 | AM71: Yauba | AN71: 10000 | AR71: Haruna | AS71: 100000 | AW71: Haruna | AX71: 20000
A72: Laraba | B72: 25000 | E72: Ayo | F72: 15000 | I72: Ayo | J72: 5000 | M72: Ayo | N72: 0 | Q72: Emma | R72: 20000 | U72: Emma | V72: 15000 | Y72: Emma | Z72: 10000 | AC72: Emma | AD72: 5000 | AH72: Emma | AI72: 0 | AM72: Abdulnasir | AN72: 30000 | AR72: Sani Truck Driver | AS72: 30000 | AW72: Sani Truck Driver | AX72: 30000
A73: Ayo | B73: 25000 | E73: Douglas | F73: 5000 | I73: Abdulnasir | J73: 60000 | M73: Abdulnasir | N73: 30000 | Q73: Abdulnasir | R73: 20000 | U73: Abdulnasir | V73: 10000 | Y73: Abdulnasir | Z73: 0 | AC73: Abdulnasir | AD73: 50000 | AH73: Abdulnasir | AI73: 40000 | AM73: Saadu | AN73: 24500 | AR73: Laraba | AS73: 10000 | AW73: Laraba | AX73: 10000
A74: Douglas | B74: 10000 | E74: Baban Abdallah | F74: 100000 | I74: Saadu | J74: 24500 | M74: Saadu | N74: 24500 | Q74: Saadu | R74: 24500 | U74: Saadu | V74: 24500 | Y74: Saadu | Z74: 24500 | AC74: Saadu | AD74: 24500 | AH74: Saadu | AI74: 24500 | AM74: Baban Abdallah | AN74: 20000 | AR74: Abdulnasir | AS74: 20000 | AW74: Abdulnasir | AX74: 1000
A75: Baban Abdallah | B75: 100000 | E75: Dahiru | F75: 95000 | I75: Baban Abdallah | J75: 90000 | M75: Baban Abdallah | N75: 80000 | Q75: Baban Abdallah | R75: 70000 | U75: Baban Abdallah | V75: 60000 | Y75: Baban Abdallah | Z75: 50000 | AC75: Baban Abdallah | AD75: 40000 | AH75: Baban Abdallah | AI75: 30000 | AM75: Engr Ayo | AN75: 90000 | AR75: Saadu | AS75: 24500 | AW75: Saadu | AX75: 24500
A76: Dahiru | B76: 110000 | E76: isya | F76: 5000 | I76: Dahiru | J76: 80000 | M76: Dahiru | N76: 65000 | Q76: Dahiru | R76: 50000 | U76: Dahiru | V76: 35000 | Y76: Dahiru | Z76: 20000 | AC76: Dahiru | AD76: 5000 | AH76: Engr Ayo | AI76: 100000 | AM76: Ali Manager | AN76: 100000 | AR76: Baban Abdallah | AS76: 10000 | AW76: Engr Ayo | AX76: 70000
A77: isya | B77: 12500 | G77: =SUM(F68:F76) -> 1130000 | I77: Maryam | J77: 100000 | M77: Maryam | N77: 100000 | Q77: Maryam | R77: 100000 | U77: JJ | V77: 30000 | Y77: JJ | Z77: 0 | AC77: Ali Manager | AD77: 100000 | AH77: Ali Manager | AI77: 100000 | AM77: Maryam | AN77: 100000 | AR77: Engr Ayo | AS77: 80000 | AW77: Ali Manager | AX77: 100000
C78: =SUM(B68:B77) -> 1222500 | E78: Others | K78: =SUM(J68:J77) -> 1204500 | O78: =SUM(N68:N77) -> 1079500 | S78: =SUM(R68:R77) -> 1029500 | U78: Maryam | V78: 100000 | Y78: Maryam | Z78: 100000 | AC78: Maryam | AD78: 100000 | AH78: Maryam | AI78: 100000 | AO78: =SUM(AN68:AN77) -> 1404500 | AR78: Ali Manager | AS78: 100000 | AW78: Maryam | AX78: 100000
A79: Others | E79: Fak Project | F79: 6408765 | I79: Others | M79: Others | Q79: Others | W79: =SUM(V68:V78) -> 1014500 | AA79: =SUM(Z68:Z78) -> 1144500 | AE79: =SUM(AD68:AD78) -> 1494500 | AJ79: =SUM(AI68:AI78) -> 1514500 | AM79: Others | AR79: Maryam | AS79: 100000 | AY79: =SUM(AX68:AX78) -> 1405500
A80: Lagos 0.7 | B80: 25000000 | E80: Zarewa Motors | F80: 149500 | I80: Fak Project | J80: 6408765 | M80: Fak Project | N80: 6408765 | Q80: Fak Project | R80: 6408765 | U80: Others | Y80: Others | AC80: Others | AH80: Others | AM80: Fak Project | AN80: 6408765 | AT80: =SUM(AS68:AS79) -> 1564500 | AW80: Others
A81: Ali Assesories | B81: 1456000 | E81: Nurul Siraj | F81: 8930616 | I81: Zarewa Motors | J81: 149500 | M81: Zarewa Motors | N81: 149500 | Q81: Zarewa Motors | R81: 149500 | U81: Fak Project | V81: 6408765 | Y81: Fak Project | Z81: 6408765 | AC81: Fak Project | AD81: 6408765 | AH81: Fak Project | AI81: 6408765 | AM81: Zarewa Motors | AN81: 149500 | AR81: Others | AW81: Fak Project | AX81: 6408765
A82: Fak Project | B82: 6408765 | E82: Mining (conzonite) | F82: 2750000 | I82: Nurul Siraj | J82: 8930616 | M82: Nurul Siraj | N82: 8930616 | Q82: Nurul Siraj | R82: 8930616 | U82: Zarewa Motors | V82: 149500 | Y82: Zarewa Motors | Z82: 149500 | AC82: Zarewa Motors | AD82: 149500 | AH82: Zarewa Motors | AI82: 149500 | AM82: Nurul Siraj | AN82: 8930616 | AR82: Fak Project | AS82: 6408765 | AW82: Zarewa Motors | AX82: 149500
A83: Zarewa Motors | B83: 149500 | E83: Almadina Hospital | I83: Mining (conzonite) | J83: 2750000 | M83: Mining (conzonite) | N83: 2750000 | Q83: Mining (conzonite) | R83: 2750000 | U83: Nurul Siraj | V83: 8930616 | Y83: Nurul Siraj | Z83: 8930616 | AC83: Nurul Siraj | AD83: 8930616 | AH83: Nurul Siraj | AI83: 8930616 | AM83: Mining (conzonite) | AN83: 2750000 | AR83: Zarewa Motors | AS83: 149500 | AW83: Nurul Siraj | AX83: 8930616
A84: Nurul Siraj | B84: 8930616 | E84: yahuza | F84: 94000 | I84: Almadina Hospital | M84: Almadina Hospital | Q84: Almadina Hospital | U84: Mining (conzonite) | V84: 2750000 | Y84: Mining (conzonite) | Z84: 2750000 | AC84: Mining (conzonite) | AD84: 2750000 | AH84: Mining (conzonite) | AI84: 2750000 | AM84: Qualitec | AN84: 27000000 | AR84: Nurul Siraj | AS84: 8930616 | AW84: Mining (conzonite) | AX84: 2750000
A85: Mining (conzonite) | B85: 2750000 | E85: Global Marori | F85: 600900 | I85: Global Marori | J85: 600900 | M85: Global Marori | N85: 600900 | Q85: Global Marori | R85: 600900 | U85: Almadina Hospital | Y85: Almadina Hospital | AC85: Almadina Hospital | AH85: Almadina Hospital | AM85: Global Marori | AN85: 600900 | AR85: Mining (conzonite) | AS85: 2750000 | AW85: uche Lagos | AX85: 10000000
A86: Almadina Hospital | E86: Maiduguri | F86: 19470881 | G86: =SUM(F79:F86) -> 38404662 | I86: Maiduguri | J86: 19470881 | K86: =SUM(J80:J86) -> 38310662 | M86: Maiduguri | N86: 19470881 | O86: =SUM(N80:N86) -> 38310662 | Q86: Maiduguri | R86: 19470881 | S86: =SUM(R80:R86) -> 38310662 | U86: Global Marori | V86: 600900 | Y86: Bamboo | Z86: 5192433 | AC86: Bamboo | AH86: Bamboo | AM86: Maiduguri | AN86: 13152729 | AO86: =SUM(AN80:AN86) -> 58992510 | AR86: uche Lagos | AS86: 15000000 | AW86: Qualitec | AX86: 30528000
A87: Global Marori | B87: 600900 | U87: Maiduguri | V87: 19470881 | W87: =SUM(V81:V87) -> 38310662 | Y87: Global Marori | Z87: 600900 | AC87: Global Marori | AD87: 600900 | AH87: Global Marori | AI87: 600900 | AR87: Ebest PG 0.7 | AS87: 4000000 | AW87: Global Marori | AX87: 600900
A88: Maiduguri | B88: 19470881 | E88: Fix Asset | I88: Fix Asset | M88: Fix Asset | Q88: Fix Asset | Y88: Maiduguri | Z88: 19470881 | AA88: =SUM(Z81:Z88) -> 43503095 | AC88: Maiduguri | AD88: 19470881 | AE88: =SUM(AD81:AD88) -> 38310662 | AH88: Maiduguri | AI88: 13152729 | AJ88: =SUM(AI81:AI88) -> 31992510 | AM88: Fix Asset | AR88: Qualitec | AS88: 30528000 | AW88: Maiduguri | AX88: 13152729 | AY88: =SUM(AX81:AX88) -> 72520510
C89: =SUM(B80:B88) -> 64766662 | E89: Land and Building | F89: 92242000 | I89: Land and Building | J89: 92242000 | M89: Land and Building | N89: 92242000 | Q89: Land and Building | R89: 92242000 | U89: Fix Asset | AM89: Land and Building | AN89: 93242000 | AR89: Global Marori | AS89: 600900
A90: Fix Asset | E90: Plant and machineries | F90: 6972416 | I90: Plant and machineries | J90: 6972416 | M90: Plant and machineries | N90: 6972416 | Q90: Plant and machineries | R90: 6972416 | U90: Land and Building | V90: 92242000 | Y90: Fix Asset | AC90: Fix Asset | AH90: Fix Asset | AM90: Plant and machineries | AN90: 6972416 | AR90: Maiduguri | AS90: 13152729 | AT90: =SUM(AS82:AS90) -> 81520510 | AW90: Fix Asset
A91: Land and Building | B91: 92242000 | E91: Furnitures & fittings | F91: 56448 | I91: Furnitures & fittings | J91: 56448 | M91: Furnitures & fittings | N91: 56448 | Q91: Furnitures & fittings | R91: 56448 | U91: Plant and machineries | V91: 6972416 | Y91: Land and Building | Z91: 93242000 | AC91: Land and Building | AD91: 93242000 | AH91: Land and Building | AI91: 93242000 | AM91: Furnitures & fittings | AN91: 56448 | AW91: Land and Building | AX91: 93242000
A92: Plant and machineries | B92: 6972416 | E92: New machine(steptiles) | F92: 5625000 | I92: New machine(steptiles) | J92: 5625000 | M92: New machine(steptiles) | N92: 5625000 | Q92: New machine(steptiles) | R92: 5625000 | U92: Furnitures & fittings | V92: 56448 | Y92: Plant and machineries | Z92: 6972416 | AC92: Plant and machineries | AD92: 6972416 | AH92: Plant and machineries | AI92: 6972416 | AM92: New machine(steptiles) | AN92: 5625000 | AR92: Fix Asset | AW92: Plant and machineries | AX92: 6972416
A93: Furnitures & fittings | B93: 56448 | E93: Generator | F93: 534750 | G93: =SUM(F89:F93) -> 105430614 | I93: Generator | J93: 534750 | K93: =SUM(J89:J93) -> 105430614 | M93: Generator | N93: 534750 | O93: =SUM(N89:N93) -> 105430614 | Q93: Generator | R93: 534750 | S93: =SUM(R89:R93) -> 105430614 | U93: New machine(steptiles) | V93: 5625000 | Y93: Furnitures & fittings | Z93: 56448 | AC93: Furnitures & fittings | AD93: 56448 | AH93: Furnitures & fittings | AI93: 56448 | AM93: Generator | AN93: 534750 | AO93: =SUM(AN89:AN93) -> 106430614 | AR93: Land and Building | AS93: 93242000 | AW93: Furnitures & fittings | AX93: 56448
A94: New machine(steptiles) | B94: 5625000 | G94: =SUM(G55:G93) -> 2.9049449e+08 | K94: =SUM(K55:K93) -> 3.2887597e+08 | O94: =SUM(O55:O93) -> 3.4766678e+08 | S94: =SUM(S55:S93) -> 370306407 | U94: Generator | V94: 534750 | W94: =SUM(V90:V94) -> 105430614 | Y94: New machine(steptiles) | Z94: 5625000 | AC94: New machine(steptiles) | AD94: 5625000 | AH94: New machine(steptiles) | AI94: 5625000 | AO94: =SUM(AO55:AO93) -> 349503612 | AR94: Plant and machineries | AS94: 6972416 | AW94: New machine(steptiles) | AX94: 5625000
A95: Generator | B95: 534750 | W95: =SUM(W55:W94) -> 347014638 | Y95: Generator | Z95: 534750 | AA95: =SUM(Z91:Z95) -> 106430614 | AC95: Generator | AD95: 534750 | AE95: =SUM(AD91:AD95) -> 106430614 | AH95: Generator | AI95: 534750 | AJ95: =SUM(AI91:AI95) -> 106430614 | AR95: Furnitures & fittings | AS95: 56448 | AW95: Generator | AX95: 534750 | AY95: =SUM(AX91:AX95) -> 106430614
C96: =SUM(B91:B95) -> 105430614 | E96: Creditors | I96: Creditors | M96: Creditors | Q96: Creditors | AA96: =SUM(AA55:AA95) -> 311101934 | AE96: =SUM(AE55:AE95) -> 319920694 | AJ96: =SUM(AJ55:AJ95) -> 336004567 | AM96: Creditors | AR96: New machine(steptiles) | AS96: 5625000 | AY96: =SUM(AY55:AY95) -> 3.3054331e+08
C97: =SUM(C55:C96) -> 292766893 | E97: BOI | G97: 70969500 | I97: BOI | K97: 70969500 | M97: BOI | O97: 70969500 | Q97: BOI | S97: 70969500 | U97: Creditors | AM97: BOI | AO97: 69969500 | AR97: Generator | AS97: 534750 | AT97: =SUM(AS93:AS97) -> 106430614
A98: Creditors | E98: Jalingo Branch | G98: 2776893 | I98: Jalingo Branch | K98: 1966293 | M98: Jalingo Branch | O98: 1966293 | Q98: Jalingo Branch | S98: 1966293 | U98: BOI | W98: 70969500 | Y98: Creditors | AC98: Creditors | AH98: Creditors | AM98: Strong Kano | AO98: 14410000 | AT98: =SUM(AT55:AT97) -> 3.8806243e+08 | AW98: Creditors
A99: BOI | C99: 74750531 | E99: Yola Branch | G99: 3800000 | I99: Yola Branch | K99: 3800000 | M99: Yola Branch | O99: 3800000 | Q99: Yola Branch | S99: 3800000 | U99: Jalingo Branch | W99: 1966293 | Y99: BOI | AA99: 70969500 | AC99: BOI | AE99: 70969500 | AH99: BOI | AJ99: 70969500 | AM99: Jalingo Branch | AO99: 1966293 | AW99: BOI | AY99: 69969500
A100: Jalingo Branch | C100: 2776893 | E100: Ibrahim Abubakar | G100: 317200 | I100: Ibrahim Abubakar | K100: 317200 | M100: Ibrahim Abubakar | O100: 317200 | Q100: Ibrahim Abubakar | S100: 317200 | U100: Yola Branch | W100: 3800000 | Y100: Jalingo Branch | AA100: 1966293 | AC100: Jalingo Branch | AE100: 1966293 | AH100: Strong Kano | AJ100: 11298160 | AK100: P | AM100: Yola Branch | AO100: 15818000 | AR100: Creditors | AW100: Strong Kano | AY100: 0
A101: Yola Branch | C101: 3800000 | E101: BAWA Abubakar | G101: 300000 | I101: BAWA Abubakar | K101: 300000 | M101: BAWA Abubakar | O101: 300000 | Q101: BAWA Abubakar | S101: 300000 | U101: Ibrahim Abubakar | W101: 317200 | Y101: Yola Branch | AA101: 3800000 | AC101: Yola Branch | AE101: 3800000 | AH101: Jalingo Branch | AJ101: 1966293 | AM101: Ibrahim Abubakar | AO101: 317200 | AR101: BOI | AT101: 69969500 | AW101: Jalingo Branch | AY101: 1966293
A102: Ibrahim Abubakar | C102: 317200 | E102: Mamia 0.7 | G102: 6336329 | I102: Global Marori | K102: 2628500 | M102: Global Marori | O102: 2628500 | Q102: Global Marori | S102: 2128000 | U102: BAWA Abubakar | W102: 300000 | Y102: Ibrahim Abubakar | AA102: 317200 | AC102: Ibrahim Abubakar | AE102: 317200 | AH102: Yola Branch | AJ102: 3800000 | AM102: BAWA Abubakar | AO102: 300000 | AR102: Strong Kano | AT102: 43171060 | AW102: Yola Branch | AY102: 15818000
A103: BAWA Abubakar | C103: 300000 | E103: Global Marori | G103: 2628500 | I103: Engr Ozize | K103: 659600 | M103: Engr Ozize | O103: 659600 | Q103: Engr Ozize | S103: 659600 | U103: Strong Standard | W103: 50781520 | Y103: BAWA Abubakar | AA103: 300000 | AC103: BAWA Abubakar | AE103: 300000 | AH103: Ibrahim Abubakar | AJ103: 317200 | AM103: Linda sabo(stone coated) | AO103: 1600000 | AR103: Jalingo Branch | AT103: 1966293 | AW103: Ibrahim Abubakar | AY103: 317200
A104: Mamia 0.7 | C104: 38838042 | E104: Engr Ozize | G104: 659600 | I104: Sarkin Labar | K104: 12110000 | M104: Sarkin Labar | O104: 12110000 | Q104: Sarkin Labar | S104: 12110000 | U104: Engr Ozize | W104: 659600 | Y104: Linda sabo(stone coated) | AA104: 1600000 | AC104: Linda sabo(stone coated) | AE104: 1600000 | AH104: BAWA Abubakar | AJ104: 300000 | AM104: Jubril (samila haladu) | AO104: 2000000 | AR104: Yola Branch | AT104: 15818000 | AW104: BAWA Abubakar | AY104: 300000
A105: Global Marori | C105: 4858043 | E105: Sarkin Labar | G105: 12110000 | I105: hon felex | K105: 1000000 | M105: hon felex | O105: 1000000 | Q105: hon felex | S105: 1000000 | U105: Sarkin Labar | W105: 12110000 | Y105: Millano red | AA105: 6516300 | AC105: Jubril (samila haladu) | AE105: 4900000 | AH105: Linda sabo(stone coated) | AJ105: 1600000 | AM105: Patrick | AO105: 503000 | AR105: Ibrahim Abubakar | AT105: 317200 | AW105: Linda sabo(stone coated) | AY105: 1600000
...

Sheet 2025
A2: Zarewa Aluminium And Plastics Ltd Kaduna | E2: Zarewa Aluminium And Plastics Ltd Kaduna | I2: Zarewa Aluminium And Plastics Ltd Kaduna | M2: Zarewa Aluminium And Plastics Ltd Kaduna | Q2: Zarewa Aluminium And Plastics Ltd Kaduna | U2: Zarewa Aluminium And Plastics Ltd Kaduna | Y2: Zarewa Aluminium And Plastics Ltd Kaduna | AC2: Zarewa Aluminium And Plastics Ltd Kaduna | AG2: Zarewa Aluminium And Plastics Ltd Kaduna | AK2: Zarewa Aluminium And Plastics Ltd Kaduna | AO2: Zarewa Aluminium And Plastics Ltd Kaduna | AS2: Zarewa Aluminium And Plastics Ltd Kaduna
A3: Production Account for the month end january | E3: Production Account for the month end Febaury | I3: Production Account for the month end March | M3: Production Account for the month end April | Q3: Production Account for the month end May | U3: Production Account for the month end june | Y3: Production Account for the month end july | AC3: Production Account for the month end August | AG3: Production Account for the month end September | AK3: Production Account for the month end October | AO3: Production Account for the month end November | AS3: Production Account for the month end December
A4: Opening Stock | C4: ='2024'!AX8 -> 122651950 | E4: Opening Stock | G4: =B9 -> 131675600 | I4: Opening Stock | K4: =F9 -> 139361880 | M4: Opening Stock | O4: =J9 -> 111633000 | Q4: Opening Stock | S4: =N9 -> 86993000 | U4: Opening Stock | W4: =R9 -> 134491100 | Y4: Opening Stock | AA4: =V9 -> 105456800 | AC4: Opening Stock | AE4: =Z9 -> 134156060 | AG4: Opening Stock | AI4: =AD9 -> 200668660 | AK4: Opening Stock | AM4: =AH9 -> 162596190 | AO4: Opening Stock | AQ4: =AL9 -> 162871360 | AS4: Opening Stock | AU4: =AP9 -> 179392750
A5: Purchases | C5: 124853410 | E5: Purchases | G5: 101428439 | I5: Purchases | K5: 57596660 | M5: Purchases | O5: 128120230 | Q5: Purchases | S5: 179354850 | U5: Purchases | W5: 172892658 | Y5: Purchases | AA5: 194843909 | AC5: Purchases | AE5: 269287184 | AG5: Purchases | AI5: 122939000 | AK5: Purchases | AM5: 124487050 | AO5: Purchases | AQ5: 206010999 | AS5: Purchases | AU5: 63804275
A6: Accessories | C6: 1532000 | E6: Accessories | G6: 691500 | I6: Accessories | K6: 1027500 | M6: Accessories | O6: 680600 | Q6: Accessories | S6: 1339620 | U6: Accessories | W6: 1299200 | Y6: Accessories | AA6: 2228500 | AC6: Accessories | AE6: 3519000 | AG6: Accessories | AI6: 7368020 | AK6: Accessories | AM6: 1883020 | AO6: Accessories | AQ6: 1824500 | AS6: Accessories | AU6: 677220
A7: Carriage Inward | C7: 1560000 | E7: Carriage Inward | G7: 1140000 | I7: Carriage Inward | K7: 609500 | M7: Carriage Inward | O7: 1755000 | Q7: Carriage Inward | S7: 1115000 | U7: Carriage Inward | W7: 1744000 | Y7: Carriage Inward | AA7: 3252000 | AC7: Carriage Inward | AE7: 3857000 | AG7: Carriage Inward | AI7: 2910500 | AK7: Carriage Inward | AM7: 1850500 | AO7: Carriage Inward | AQ7: 4226500 | AS7: Carriage Inward | AU7: 425000
C8: =SUM(C4:C7) -> 250597360 | G8: =SUM(G4:G7) -> 234935539 | K8: =SUM(K4:K7) -> 198595540 | O8: =SUM(O4:O7) -> 242188830 | S8: =SUM(S4:S7) -> 268802470 | W8: =SUM(W4:W7) -> 310426958 | AA8: =SUM(AA4:AA7) -> 305781209 | AE8: =SUM(AE4:AE7) -> 410819244 | AI8: =SUM(AI4:AI7) -> 333886180 | AM8: =SUM(AM4:AM7) -> 290816760 | AQ8: =SUM(AQ4:AQ7) -> 374933359 | AU8: =SUM(AU4:AU7) -> 244299245
A9: Closing Stock | B9: 131675600 | E9: Closing Stock | F9: 139361880 | I9: Closing Stock | J9: 111633000 | M9: Closing Stock | N9: =Stock!CA102 -> 86993000 | Q9: Closing Stock | R9: =Stock!CH103 -> 134491100 | U9: Closing Stock | V9: =Stock!CO98 -> 105456800 | Y9: Closing Stock | Z9: =Stock!CV110 -> 134156060 | AC9: Closing Stock | AD9: =Stock!DC123 -> 200668660 | AG9: Closing Stock | AH9: =Stock!DJ128 -> 162596190 | AK9: Closing Stock | AL9: =Stock!DQ128 -> 162871360 | AO9: Closing Stock | AP9: =Stock!DX148 -> 179392750 | AS9: Closing Stock | AT9: =Stock!EE136 -> 152704600
C10: =C8-B9 -> 118921760 | G10: =G8-F9 -> 95573659 | K10: =K8-J9 -> 86962540 | O10: =O8-N9 -> 155195830 | S10: =S8-R9 -> 134311370 | W10: =W8-V9 -> 204970158 | AA10: =AA8-Z9 -> 171625149 | AE10: =AE8-AD9 -> 210150584 | AI10: =AI8-AH9 -> 171289990 | AM10: =AM8-AL9 -> 127945400 | AQ10: =AQ8-AP9 -> 195540609 | AU10: =AU8-AT9 -> 91594645
A12: Factory Overhead | E12: Factory Overhead | I12: Factory Overhead | M12: Factory Overhead | Q12: Factory Overhead | U12: Factory Overhead | Y12: Factory Overhead | AC12: Factory Overhead | AG12: Factory Overhead | AK12: Factory Overhead | AO12: Factory Overhead | AS12: Factory Overhead
A13: Wages | B13: 420000 | E13: Wages | F13: 420000 | I13: Wages | J13: 420000 | M13: Wages | N13: 450000 | Q13: Wages | R13: 450000 | U13: Wages | V13: 450000 | Y13: Wages | Z13: 450000 | AC13: Wages | AD13: 450000 | AG13: Wages | AH13: 450000 | AK13: Wages | AL13: 450000 | AO13: Wages | AP13: 450000 | AS13: Wages | AT13: 450000
A14: Fuel & Lubricant | B14: 655811 | E14: Fuel & Lubricant | F14: 575000 | I14: Fuel & Lubricant | J14: 330000 | M14: Fuel & Lubricant | N14: 274420 | Q14: Fuel & Lubricant | R14: 1105000 | U14: Fuel & Lubricant | V14: 1006000 | Y14: Fuel & Lubricant | Z14: 917500 | AC14: Fuel & Lubricant | AD14: 749000 | AG14: Fuel & Lubricant | AH14: 639000 | AK14: Fuel & Lubricant | AL14: 260000 | AO14: Fuel & Lubricant | AP14: 595000 | AS14: Fuel & Lubricant | AT14: 507695
A15: Electricity Bill | B15: 0 | E15: Electricity Bill | F15: 0 | I15: Electricity Bill | J15: 0 | M15: Electricity Bill | N15: 0 | Q15: Electricity Bill | R15: 0 | U15: Electricity Bill | Y15: Electricity Bill | AC15: Electricity Bill | AG15: Electricity Bill | AK15: Outside currugation | AL15: 529120 | AO15: Outside currugation | AP15: 171000 | AS15: Outside currugation
A16: Maintainace | B16: 377800 | E16: Maintainace | F16: 981500 | I16: Maintainace | J16: 48000 | M16: Maintainace | N16: 370000 | Q16: Maintainace | R16: 1058000 | U16: Maintainace | V16: 1378000 | Y16: Maintainace | Z16: 617000 | AC16: Maintainace | AD16: 309100 | AG16: Maintainace | AH16: 129500 | AK16: Maintainace | AL16: 473000 | AO16: Maintainace | AP16: 300900 | AS16: Maintainace | AT16: 465300
A17: Depreciation | B17: 110000 | E17: Depreciation | F17: 110000 | I17: Depreciation | J17: 110000 | M17: Depreciation | N17: 110000 | Q17: Depreciation | R17: 110000 | U17: Depreciation | V17: 110000 | Y17: Depreciation | Z17: 110000 | AC17: Depreciation | AD17: 110000 | AG17: Depreciation | AH17: 110000 | AK17: Depreciation | AL17: 110000 | AO17: Depreciation | AP17: 110000 | AS17: Depreciation | AT17: 110000
B18: =SUM(B13:B17) -> 1563611 | F18: =SUM(F13:F17) -> 2086500 | J18: =SUM(J13:J17) -> 908000 | N18: =SUM(N13:N17) -> 1204420 | R18: =SUM(R13:R17) -> 2723000 | V18: =SUM(V13:V17) -> 2944000 | Z18: =SUM(Z13:Z17) -> 2094500 | AD18: =SUM(AD13:AD17) -> 1618100 | AH18: =SUM(AH13:AH17) -> 1328500 | AL18: =SUM(AL13:AL17) -> 1822120 | AP18: =SUM(AP13:AP17) -> 1626900 | AT18: =SUM(AT13:AT17) -> 1532995
C19: =C10+B18 -> 120485371 | G19: =G10+F18 -> 97660159 | K19: =K10+J18 -> 87870540 | O19: =O10+N18 -> 156400250 | S19: =S10+R18 -> 137034370 | W19: =W10+V18 -> 207914158 | AA19: =AA10+Z18 -> 173719649 | AE19: =AE10+AD18 -> 211768684 | AI19: =AI10+AH18 -> 172618490 | AM19: =AM10+AL18 -> 129767520 | AQ19: =AQ10+AP18 -> 197167509 | AU19: =AU10+AT18 -> 93127640
A21: Zarewa Aluminium And Plastics Ltd Kaduna | E21: Zarewa Aluminium And Plastics Ltd Kaduna | I21: Zarewa Aluminium And Plastics Ltd Kaduna | M21: Zarewa Aluminium And Plastics Ltd Kaduna | Q21: Zarewa Aluminium And Plastics Ltd Kaduna | U21: Zarewa Aluminium And Plastics Ltd Kaduna | Y21: Zarewa Aluminium And Plastics Ltd Kaduna | AC21: Zarewa Aluminium And Plastics Ltd Kaduna | AG21: Zarewa Aluminium And Plastics Ltd Kaduna | AK21: Zarewa Aluminium And Plastics Ltd Kaduna | AO21: Zarewa Aluminium And Plastics Ltd Kaduna | AS21: Zarewa Aluminium And Plastics Ltd Kaduna
A22: Profit and Lost Account for the month end January | E22: Profit and Lost Account for the month end Feb | I22: Profit and Lost Account for the month end Feb | M22: Profit and Lost Account for the month end may | Q22: Profit and Lost Account for the month end may | U22: Profit and Lost Account for the month end june | Y22: Profit and Lost Account for the month end july | AC22: Profit and Lost Account for the month end Agust | AG22: Profit and Lost Account for the month end September | AK22: Profit and Lost Account for the month end October | AO22: Profit and Lost Account for the month end November | AS22: Profit and Lost Account for the month end November
A23: Opening Stock | E23: Opening Stock | I23: Opening Stock | M23: Opening Stock | Q23: Opening Stock | U23: Opening Stock | Y23: Opening Stock | AC23: Opening Stock | AG23: Opening Stock | AK23: Opening Stock | AO23: Opening Stock | AS23: Opening Stock
A24: Sales | C24: 135829763 | E24: Sales | G24: 104097648 | I24: Sales | K24: 101071816 | M24: Sales | O24: 175194444 | Q24: Sales | S24: 157781840 | U24: Sales | W24: 268750154 | Y24: Sales | AA24: 204269779 | AC24: Sales | AE24: 273198040 | AG24: Sales | AI24: 197873718 | AK24: Sales | AM24: 174627389 | AO24: Sales | AQ24: 230293875 | AS24: Sales | AU24: 127427926
A25: Refund | B25: 14490272 | E25: Refund | F25: 7814104 | I25: Refund | J25: 8969253 | M25: Refund | N25: 12077151 | Q25: Refund | R25: 17065392 | U25: Refund | V25: 48492193 | Y25: Refund | Z25: 19277043 | AC25: Refund | AD25: 31949300 | AG25: Refund | AH25: 20496111 | AK25: Refund | AL25: 19326225 | AO25: Refund | AP25: 27219479 | AS25: Refund | AT25: 21337575
A26: Net Sales | C26: =C24-B25 -> 121339491 | E26: Net Sales | G26: =G24-F25 -> 96283544 | I26: Net Sales | K26: =K24-J25 -> 92102563 | M26: Net Sales | O26: =O24-N25 -> 163117293 | Q26: Net Sales | S26: =S24-R25 -> 140716448 | U26: Net Sales | W26: =W24-V25 -> 220257961 | Y26: Net Sales | AA26: =AA24-Z25 -> 184992736 | AC26: Net Sales | AE26: =AE24-AD25 -> 241248740 | AG26: Net Sales | AI26: =AI24-AH25 -> 177377607 | AK26: Net Sales | AM26: =AM24-AL25 -> 155301164 | AO26: Net Sales | AQ26: =AQ24-AP25 -> 203074396 | AS26: Net Sales | AU26: =AU24-AT25 -> 106090351
A27: Production Cost | B27: =C19 -> 120485371 | E27: Production Cost | F27: =G19 -> 97660159 | I27: Production Cost | J27: =K19 -> 87870540 | M27: Production Cost | N27: =O19 -> 156400250 | Q27: Production Cost | R27: =S19 -> 137034370 | U27: Production Cost | V27: =W19 -> 207914158 | Y27: Production Cost | Z27: =AA19 -> 173719649 | AC27: Production Cost | AD27: =AE19 -> 211768684 | AG27: Production Cost | AH27: =AI19 -> 172618490 | AK27: Production Cost | AL27: =AM19 -> 129767520 | AO27: Production Cost | AP27: =AQ19 -> 197167509 | AS27: Production Cost | AT27: =AU19 -> 93127640
A28: Closing Stock | B28: 0 | E28: Closing Stock | F28: 0 | I28: Closing Stock | J28: 0 | M28: Closing Stock | N28: 0 | Q28: Closing Stock | R28: 0 | U28: Closing Stock | V28: 0 | Y28: Closing Stock | Z28: 0 | AC28: Closing Stock | AD28: 0 | AG28: Closing Stock | AH28: 0 | AK28: Closing Stock | AL28: 0 | AO28: Closing Stock | AP28: 0 | AS28: Closing Stock | AT28: 0
B29: =SUM(B27:B28) -> 120485371 | F29: =SUM(F27:F28) -> 97660159 | J29: =SUM(J27:J28) -> 87870540 | N29: =SUM(N27:N28) -> 156400250 | R29: =SUM(R27:R28) -> 137034370 | V29: =SUM(V27:V28) -> 207914158 | Z29: =SUM(Z27:Z28) -> 173719649 | AD29: =SUM(AD27:AD28) -> 211768684 | AH29: =SUM(AH27:AH28) -> 172618490 | AL29: =SUM(AL27:AL28) -> 129767520 | AP29: =SUM(AP27:AP28) -> 197167509 | AT29: =SUM(AT27:AT28) -> 93127640
A30: Gross Profit | C30: =C26-B29 -> 854120 | E30: Gross Profit | G30: =G26-F29 -> -1376615 | I30: Gross Profit | K30: =K26-J29 -> 4232023 | M30: Gross Profit | O30: =O26-N29 -> 6717043 | Q30: Gross Profit | S30: =S26-R29 -> 3682078 | U30: Gross Profit | W30: =W26-V29 -> 12343803 | Y30: Gross Profit | AA30: =AA26-Z29 -> 11273087 | AC30: Gross Profit | AE30: =AE26-AD29 -> 29480056 | AG30: Gross Profit | AI30: =AI26-AH29 -> 4759117 | AK30: Gross Profit | AM30: =AM26-AL29 -> 25533644 | AO30: Gross Profit | AQ30: =AQ26-AP29 -> 5906887 | AS30: Gross Profit | AU30: =AU26-AT29 -> 12962711
A32: Admin Expenses | E32: Admin Expenses | I32: Admin Expenses | M32: Admin Expenses | Q32: Admin Expenses | U32: Admin Expenses | Y32: Admin Expenses | AC32: Admin Expenses | AG32: Admin Expenses | AK32: Admin Expenses | AO32: Admin Expenses | AS32: Admin Expenses
A33: Admin exp | B33: 20000 | E33: Admin exp | F33: 30000 | I33: Admin exp | J33: 0 | M33: Admin exp | N33: 202000 | Q33: Admin exp | R33: 120000 | U33: Admin exp | V33: 122500 | Y33: Admin exp | Z33: 325000 | AC33: Admin exp | AD33: 111000 | AG33: Admin exp | AH33: 275000 | AK33: Admin exp | AL33: 110400 | AO33: Admin exp | AP33: 105000 | AS33: Admin exp | AT33: 115000
A34: Admin Salary | B34: 750000 | E34: Admin Salary | F34: 750000 | I34: Admin Salary | J34: 750000 | M34: Admin Salary | N34: 550000 | Q34: Admin Salary | R34: 750000 | U34: Admin Salary | V34: 750000 | Y34: Admin Salary | Z34: 750000 | AC34: Admin Salary | AD34: 750000 | AG34: Admin Salary | AH34: 750000 | AK34: Admin Salary | AL34: 750000 | AO34: Admin Salary | AP34: 750000 | AS34: Admin Salary | AT34: 1150000
A35: Bank Charge | B35: 0 | E35: Bank Charge | F35: 8265.85 | I35: Bank Charge | J35: 10510 | M35: Bank Charge | N35: 0 | Q35: Bank Charge | R35: 5636 | U35: Bank Charge | V35: 7777 | Y35: Bank Charge | Z35: 7900 | AC35: Bank Charge | AD35: 5393.25 | AG35: Bank Charge | AH35: 187318.42 | AK35: Bank Charge | AL35: 51638.1 | AO35: Bank Charge | AP35: 87879.75 | AS35: Bank Charge | AT35: 6087
A36: Office Expenses | B36: 126800 | E36: Office Expenses | F36: 39600 | I36: Office Expenses | J36: 140000 | M36: Office Expenses | N36: 74000 | Q36: Office Expenses | R36: 16000 | U36: Office Expenses | V36: 53200 | Y36: Office Expenses | Z36: 29020 | AC36: Office Expenses | AD36: 622700 | AG36: Office Expenses | AH36: 197400 | AK36: Office Expenses | AL36: 1585400 | AO36: Office Expenses | AP36: 1041100 | AS36: Office Expenses | AT36: 686400
A37: Professional Fee | B37: 0 | E37: Professional Fee | F37: 0 | I37: Professional Fee | J37: 0 | M37: Professional Fee | N37: 0 | Q37: Professional Fee | R37: 150000 | U37: Professional Fee | Y37: Professional Fee | AC37: Professional Fee | AG37: Professional Fee | AK37: Professional Fee | AL37: 25000 | AO37: Professional Fee | AP37: 150000 | AS37: Professional Fee | AT37: 495000
A38: Tax | B38: 538800 | E38: Tax | F38: 194000 | I38: Tax | J38: 175000 | M38: Tax | N38: 745000 | Q38: Tax | R38: 70000 | U38: Tax | Y38: Tax | Z38: 666590 | AC38: Tax | AD38: 1348037 | AG38: Tax | AK38: Tax | AO38: Tax | AS38: Tax
A39: Pension | B39: 0 | E39: Pension | F39: 0 | I39: Pension | J39: 0 | M39: Pension | N39: 0 | Q39: Pension | R39: 0 | U39: Pension | Y39: Pension | AC39: Pension | AG39: Pension | AK39: Pension | AO39: Pension | AS39: Pension
A40: Security | B40: 135000 | E40: Security | F40: 115000 | I40: Security | J40: 115000 | M40: Security | N40: 131000 | Q40: Security | R40: 115000 | U40: Security | V40: 107500 | Y40: Security | Z40: 100000 | AC40: Security | AD40: 150000 | AG40: Security | AH40: 100000 | AK40: Security | AL40: 100000 | AO40: Security | AP40: 100000 | AS40: Security | AT40: 100000
A41: Intrest | E41: Intrest | I41: Intrest | M41: Intrest | Q41: Intrest | U41: Intrest | Y41: Intrest | AC41: Intrest | AG41: Intrest | AK41: Intrest | AO41: Intrest | AS41: Intrest
A42: Welfare | B42: 0 | E42: Welfare | F42: 0 | I42: Welfare | J42: 0 | M42: Welfare | N42: 0 | Q42: Welfare | R42: 0 | U42: Welfare | Y42: Welfare | AC42: Welfare | AG42: Welfare | AK42: Welfare | AO42: Welfare | AS42: Welfare
A43: Zakat & Sallah | E43: Zakat & Sallah | F43: 1000000 | I43: Zakat & Sallah | J43: 2150000 | M43: Zakat & Sallah | N43: 0 | Q43: Zakat & Sallah | R43: 800000 | U43: Zakat & Sallah | Y43: Zakat & Sallah | AC43: Zakat & Sallah | AG43: Zakat & Sallah | AK43: Zakat & Sallah | AO43: Zakat & Sallah | AS43: Zakat & Sallah
B44: =SUM(B33:B43) -> 1570600 | F44: =SUM(F33:F43) -> 2136865.9 | J44: =SUM(J33:J43) -> 3340510 | N44: =SUM(N33:N43) -> 1702000 | R44: =SUM(R33:R43) -> 2026636 | V44: =SUM(V33:V43) -> 1040977 | Z44: =SUM(Z33:Z43) -> 1878510 | AD44: =SUM(AD33:AD43) -> 2987130.2 | AH44: =SUM(AH33:AH43) -> 1509718.4 | AL44: =SUM(AL33:AL43) -> 2622438.1 | AP44: =SUM(AP33:AP43) -> 2233979.8 | AT44: =SUM(AT33:AT43) -> 2552487
A45: Net Profit | C45: =C30-B44 -> -716480 | E45: Net Profit | G45: =G30-F44 -> -3513480.9 | I45: Net Profit | K45: =K30-J44 -> 891513 | M45: Net Profit | O45: =O30-N44 -> 5015043 | Q45: Net Profit | S45: =S30-R44 -> 1655442 | U45: Net Profit | W45: =W30-V44 -> 11302826 | Y45: Net Profit | AA45: =AA30-Z44 -> 9394577 | AC45: Net Profit | AE45: =AE30-AD44 -> 26492926 | AG45: Net Profit | AI45: =AI30-AH44 -> 3249398.6 | AK45: Net Profit | AM45: =AM30-AL44 -> 22911206 | AO45: Net Profit | AQ45: =AQ30-AP44 -> 3672907.2 | AS45: Net Profit | AU45: =AU30-AT44 -> 10410224
A47: HQ | E47: HQ | I47: HQ | M47: HQ | N47: 400000 | Q47: HQ | R47: 200000 | U47: HQ | V47: 200000 | Y47: HQ | Z47: 200000 | AC47: HQ | AD47: 200000 | AG47: HQ | AH47: 200000 | AK47: HQ | AL47: 200000 | AO47: HQ | AP47: 200000 | AS47: HQ | AT47: 200000
A48: Chairman Withdrawal | B48: 288000 | E48: Chairman Withdrawal | F48: 3375000 | I48: Chairman Withdrawal | J48: 1385000 | M48: Chairman Withdrawal | N48: 2450000 | Q48: Chairman Withdrawal | R48: 164000 | U48: Chairman Withdrawal | V48: 864350 | Y48: Chairman Withdrawal | Z48: 552000 | AC48: Chairman Withdrawal | AD48: 1563000 | AG48: Chairman Withdrawal | AH48: 1373000 | AK48: Chairman Withdrawal | AL48: 427600 | AO48: Chairman Withdrawal | AP48: 0 | AS48: Chairman Withdrawal | AT48: 7345100
A49: truck &mining | B49: 15000 | E49: truck &mining | I49: truck &mining | J49: 1000000 | M49: truck &mining | N49: 0 | Q49: truck &mining | U49: truck &mining | V49: 500000 | Y49: truck &mining | AC49: truck &mining | AD49: 120000 | AG49: truck &mining | AK49: truck &mining | AL49: 20100 | AO49: truck &mining | AP49: 86000 | AS49: truck &mining
B50: 0 | F50: 0 | J50: 0 | N50: 0 | R50: 0 | AC50: emma | AD50: 1300000
B51: =SUM(B47:B50) -> 303000 | F51: =SUM(F47:F50) -> 3375000 | J51: =SUM(J47:J50) -> 2385000 | N51: =SUM(N47:N50) -> 2850000 | R51: =SUM(R47:R50) -> 364000 | V51: =SUM(V47:V50) -> 1564350 | Z51: =SUM(Z47:Z50) -> 752000 | AD51: =SUM(AD47:AD50) -> 3183000 | AH51: =SUM(AH47:AH50) -> 1573000 | AL51: =SUM(AL47:AL50) -> 647700 | AP51: =SUM(AP47:AP50) -> 286000 | AT51: =SUM(AT47:AT50) -> 7545100
C52: =C45-B51 -> -1019480 | G52: =G45-F51 -> -6888480.8 | K52: =K45-J51 -> -1493487 | O52: =O45-N51 -> 2165043 | S52: =S45-R51 -> 1291442 | W52: =W45-V51 -> 9738476 | AA52: =AA45-Z51 -> 8642577 | AE52: =AE45-AD51 -> 23309926 | AI52: =AI45-AH51 -> 1676398.6 | AM52: =AM45-AL51 -> 22263506 | AQ52: =AQ45-AP51 -> 3386907.2 | AU52: =AU45-AT51 -> 2865124
A54: Zarewa Aluminium And Plastics Ltd Kaduna | E54: Zarewa Aluminium And Plastics Ltd Kaduna | I54: Zarewa Aluminium And Plastics Ltd Kaduna | M54: Zarewa Aluminium And Plastics Ltd Kaduna | Q54: Zarewa Aluminium And Plastics Ltd Kaduna | U54: Zarewa Aluminium And Plastics Ltd Kaduna | Y54: Zarewa Aluminium And Plastics Ltd Kaduna | AC54: Zarewa Aluminium And Plastics Ltd Kaduna | AG54: Zarewa Aluminium And Plastics Ltd Kaduna | AK54: Zarewa Aluminium And Plastics Ltd Kaduna | AO54: Zarewa Aluminium And Plastics Ltd Kaduna | AS54: Zarewa Aluminium And Plastics Ltd Kaduna
A55: Asset and liability Account for the month end Janauary | E55: Asset and liability Account for the month end FEB | I55: Asset and liability Account for the month end FEB | M55: Asset and liability Account for the month end FEB | Q55: Asset and liability Account for the month end may | U55: Asset and liability Account for the month end june | Y55: Asset and liability Account for the month end july | AC55: Asset and liability Account for the month end August | AG55: Asset and liability Account for the month end September | AK55: Asset and liability Account for the month end October | AO55: Asset and liability Account for the month end November | AS55: Asset and liability Account for the month end November
A56: ClosinG Stock | B56: 131675600 | E56: ClosinG Stock | F56: =F9 -> 139361880 | I56: ClosinG Stock | J56: =J9 -> 111633000 | M56: ClosinG Stock | N56: =N9 -> 86993000 | Q56: ClosinG Stock | R56: =R9 -> 134491100 | U56: ClosinG Stock | V56: =V9 -> 105456800 | Y56: ClosinG Stock | Z56: =Z9 -> 134156060 | AC56: ClosinG Stock | AD56: =AD9 -> 200668660 | AG56: ClosinG Stock | AH56: =AH9 -> 162596190 | AK56: ClosinG Stock | AL56: =AL9 -> 162871360 | AO56: ClosinG Stock | AP56: =AP9 -> 179392750 | AS56: ClosinG Stock | AT56: =AT9 -> 152704600
A57: Cash at hand | B57: 4221000 | E57: Cash at hand | F57: 3031152 | I57: Cash at hand | J57: 3031152 | M57: Cash at hand | N57: 3031152 | Q57: Cash at hand | R57: 5676453 | U57: Cash at hand | V57: 2244150 | Y57: Cash at hand | Z57: 4262692 | AC57: Cash at hand | AD57: 4932812 | AG57: Cash at hand | AH57: 6895561 | AK57: Cash at hand | AL57: 828434 | AO57: Cash at hand | AP57: 9704216 | AS57: Cash at hand | AT57: 10536337
A58: Gt Bank | B58: 1928588 | E58: Gt Bank | F58: 132862 | I58: Gt Bank | J58: 132862 | M58: Gt Bank | N58: 132862 | Q58: Gt Bank | R58: 5057627 | U58: Gt Bank | V58: 52179.21 | Y58: Gt Bank | AC58: Gt Bank | AD58: 92395 | AG58: Gt Bank | AH58: 25191457 | AK58: Gt Bank | AL58: 79862880 | AO58: Gt Bank | AP58: 448236.4 | AS58: Gt Bank | AT58: 42765
A59: Eco Bank | B59: 1249021 | E59: Eco Bank | F59: 0 | I59: Eco Bank | J59: 0 | M59: Eco Bank | N59: 0 | Q59: Eco Bank | R59: 0 | U59: Eco Bank | V59: 0 | Y59: Eco Bank | Z59: 0 | AC59: Eco Bank | AG59: Eco Bank | AK59: Eco Bank | AO59: Eco Bank | AS59: Eco Bank
A60: Jaiz Bank | B60: 278042 | E60: Jaiz Bank | F60: 278042 | I60: Jaiz Bank | J60: 278042 | M60: Jaiz Bank | N60: 278042 | Q60: Jaiz Bank | R60: 278042 | U60: Jaiz Bank | V60: 278000 | Y60: Jaiz Bank | Z60: 278000 | AC60: Jaiz Bank | AD60: 278000 | AG60: Jaiz Bank | AH60: 278000 | AK60: Jaiz Bank | AL60: 278000 | AO60: Jaiz Bank | AP60: 278000 | AS60: Jaiz Bank | AT60: 278000
A61: Taj bank | B61: 14412000 | E61: Taj bank | F61: 457670 | I61: Taj bank | J61: 457670 | M61: Taj bank | N61: 457670 | Q61: Taj bank | R61: 6877590 | U61: Taj bank | V61: 32859667 | Y61: Taj bank | Z61: 6961859 | AC61: Taj bank | AD61: 9650931 | AG61: Taj bank | AH61: 20527303 | AK61: Taj bank | AL61: 162957.05 | AO61: Taj bank | AP61: 9888672.2 | AS61: Taj bank | AT61: 37738239
C62: =SUM(B56:B61) -> 153764251 | G62: =SUM(F56:F61) -> 143261606 | K62: =SUM(J56:J61) -> 115532726 | O62: =SUM(N56:N61) -> 90892726 | S62: =SUM(R56:R61) -> 152380812 | W62: =SUM(V56:V61) -> 1.408908e+08 | AA62: =SUM(Z56:Z61) -> 145658611 | AE62: =SUM(AD56:AD61) -> 215622798 | AI62: =SUM(AH56:AH61) -> 215488511 | AM62: =SUM(AL56:AL61) -> 2.4400363e+08 | AQ62: =SUM(AP56:AP61) -> 1.9971187e+08 | AU62: =SUM(AT56:AT61) -> 201299941
A63: Customer Debth | E63: Customer Debth | I63: Customer Debth | M63: Customer Debth | Q63: Customer Debth | U63: Customer Debth | Y63: Customer Debth | AC63: Customer Debth | AG63: Customer Debth | AK63: Customer Debth | AO63: Customer Debth | AS63: Customer Debth
A64: Abdul Bawa | B64: 500000 | E64: Abdul Bawa | F64: 500000 | I64: Abdul Bawa | J64: 500000 | M64: Abdul Bawa | N64: 500000 | Q64: Abdul Bawa | R64: 500000 | U64: Abdul Bawa | V64: 500000 | Y64: Abdul Bawa | Z64: 500000 | AC64: Abdul Bawa | AD64: 500000 | AG64: Abdul Bawa | AH64: 500000 | AK64: Abdul Bawa | AL64: 500000 | AO64: Abdul Bawa | AP64: 500000 | AS64: Abdul Bawa | AT64: 500000
A65: Jamil Sani | B65: 101300 | E65: Jamil Sani | F65: 101300 | I65: Jamil Sani | J65: 101300 | M65: Jamil Sani | N65: 101300 | Q65: Jamil Sani | R65: 101300 | U65: Jamil Sani | V65: 101300 | Y65: Jamil Sani | Z65: 101300 | AC65: Jamil Sani | AD65: 101300 | AG65: Jamil Sani | AH65: 101300 | AK65: Jamil Sani | AL65: 101300 | AO65: Jamil Sani | AP65: 101300 | AS65: Jamil Sani | AT65: 101300
A66: Alh sani Katsina | B66: 50000 | E66: Alh sani Katsina | F66: 50000 | I66: Alh sani Katsina | J66: 50000 | M66: Alh sani Katsina | N66: 50000 | Q66: Alh sani Katsina | R66: 50000 | U66: Alh sani Katsina | V66: 50000 | Y66: Alh sani Katsina | Z66: 50000 | AC66: Alh sani Katsina | AD66: 50000 | AG66: Alh sani Katsina | AH66: 50000 | AK66: Alh sani Katsina | AL66: 50000 | AO66: Alh sani Katsina | AP66: 50000 | AS66: Alh sani Katsina | AT66: 50000
C67: =SUM(B64:B66) -> 651300 | G67: =SUM(F64:F66) -> 651300 | K67: =SUM(J64:J66) -> 651300 | O67: =SUM(N64:N66) -> 651300 | S67: =SUM(R64:R66) -> 651300 | W67: =SUM(V64:V66) -> 651300 | AA67: =SUM(Z64:Z66) -> 651300 | AE67: =SUM(AD64:AD66) -> 651300 | AI67: =SUM(AH64:AH66) -> 651300 | AM67: =SUM(AL64:AL66) -> 651300 | AQ67: =SUM(AP64:AP66) -> 651300 | AU67: =SUM(AT64:AT66) -> 651300
A68: Staff Loan | E68: Staff Loan | I68: Staff Loan | M68: Staff Loan | Q68: Staff Loan | U68: Staff Loan | Y68: Staff Loan | AC68: Staff Loan | AG68: Staff Loan | AK68: Staff Loan | AO68: Staff Loan | AS68: Staff Loan
A69: Alh Bala Muazu | B69: 600000 | E69: Alh Bala Muazu | F69: 560000 | I69: Alh Bala Muazu | J69: 520000 | M69: Alh Bala Muazu | N69: 810000 | Q69: Alh Bala Muazu | R69: 770000 | U69: Alh Bala Muazu | V69: 730000 | Y69: Alh Bala Muazu | Z69: 940000 | AC69: Alh Bala Muazu | AD69: 960000 | AG69: Alh Bala Muazu | AH69: 1315000 | AK69: Alh Bala Muazu | AL69: 720000 | AO69: Alh Bala Muazu | AP69: 270000 | AS69: Alh Bala Muazu | AT69: 330000
A70: Bilyaminu maiha | B70: 300000 | E70: Bilyaminu maiha | F70: 300000 | I70: Bilyaminu maiha | J70: 300000 | M70: Bilyaminu maiha | N70: 300000 | Q70: Bilyaminu maiha | R70: 300000 | U70: Bilyaminu maiha | V70: 300000 | Y70: Bilyaminu maiha | Z70: 300000 | AC70: Bilyaminu maiha | AD70: 300000 | AG70: Bilyaminu maiha | AH70: 300000 | AK70: Bilyaminu maiha | AL70: 300000 | AO70: Bilyaminu maiha | AP70: 300000 | AS70: Bilyaminu maiha | AT70: 300000
A71: Dahiru | B71: 150000 | E71: Dahiru | F71: 130000 | I71: Dahiru | J71: 110000 | M71: Dahiru | N71: 90000 | Q71: Dahiru | R71: 70000 | U71: Dahiru | V71: 550000 | Y71: Dahiru | Z71: 520000 | AC71: Dahiru | AD71: 490000 | AG71: Dahiru | AH71: 460000 | AK71: Dahiru | AL71: 400000 | AO71: Dahiru | AP71: 400000 | AS71: Dahiru | AT71: 400000
A72: Haruna | B72: 20000 | E72: Haruna | F72: 90000 | I72: Haruna | J72: 90000 | M72: Haruna | N72: 80000 | Q72: Haruna | R72: 70000 | U72: Haruna | V72: 60000 | Y72: Haruna | Z72: 50000 | AC72: Haruna | AD72: 40000 | AG72: Haruna | AH72: 30000 | AK72: Haruna | AL72: 20000 | AO72: Haruna | AP72: 10000 | AS72: Haruna
A73: Sani Truck Driver | B73: 30000 | E73: Sani Truck Driver | F73: 30000 | I73: Sani Truck Driver | J73: 30000 | M73: Ali Onuche | N73: 300000 | Q73: Ali Onuche | R73: 300000 | U73: Ali Onuche | V73: 300000 | Y73: Ali Onuche | Z73: 300000 | AC73: Ali Onuche | AD73: 300000 | AG73: Ali Onuche | AH73: 300000 | AK73: Ali Onuche | AL73: 1500000 | AO73: Ali Onuche | AP73: 1500000 | AS73: Ali Onuche | AT73: 1500000
A74: Laraba | B74: 10000 | E74: Laraba | F74: 5000 | I74: Laila Sali | J74: 800000 | M74: Laila Sali | N74: 800000 | Q74: Laila Sali | R74: 800000 | U74: Laila Sali | V74: 800000 | Y74: Laila Sali | Z74: 800000 | AC74: Laila Sali | AD74: 800000 | AG74: Laila Sali | AH74: 800000 | AK74: Laila Sali | AL74: 800000 | AO74: Laila Sali | AP74: 800000 | AS74: Laila Sali | AT74: 800000
A75: Abdulnasir | B75: 0 | E75: Abdulnasir | F75: 60000 | I75: Abdulnasir | J75: 50000 | M75: Abdulnasir | N75: 40000 | Q75: Abdulnasir | R75: 30000 | U75: Abdulnasir | V75: 20000 | Y75: Abdulnasir | Z75: 10000 | AC75: Nana Sali | AD75: 1500000 | AG75: nana Sali | AH75: 1500000 | AK75: nana Sali | AL75: 1500000 | AO75: nana Sali | AP75: 1500000 | AS75: nana Sali | AT75: 1500000
A76: Saadu | B76: 24500 | E76: Saadu | F76: 24500 | I76: Saadu | J76: 24500 | M76: Saadu | N76: 24500 | Q76: Saadu | R76: 24500 | U76: Saadu | V76: 24500 | Y76: Saadu | Z76: 24500 | AC76: Saadu | AD76: 24500 | AG76: Saadu | AH76: 24500 | AK76: Saadu | AL76: 24500 | AO76: Saadu | AP76: 24500 | AS76: Saadu | AT76: 24500
A77: Engr Ayo | B77: 60000 | E77: Engr Ayo | F77: 50000 | I77: Engr Ayo | J77: 40000 | M77: Engr Ayo | N77: 30000 | Q77: Engr Ayo | R77: 20000 | U77: Engr Ayo | V77: 10000 | Y77: Yusuf Musa (Gad) | Z77: 70000 | AC77: Yusuf Musa (Gad) | AD77: 60000 | AG77: Yusuf Musa (Gad) | AH77: 50000 | AK77: Yusuf Musa (Gad) | AL77: 40000 | AO77: Yusuf Musa (Gad) | AP77: 30000 | AS77: Yusuf Musa (Gad) | AT77: 20000
A78: Ali Manager | B78: 100000 | E78: Ali Manager | F78: 40000 | I78: Ali Manager | J78: 40000 | M78: Yusuf Musa (Gad) | N78: 100000 | Q78: Yusuf Musa (Gad) | R78: 90000 | U78: Yusuf Musa (Gad) | V78: 80000 | Z78: 0 | AD78: 0 | AH78: 0 | AK78: nas | AL78: 3000 | AO78: Moon ROOm | AP78: 1200000 | AS78: Moon ROOm | AT78: 1200000
C79: =SUM(B69:B78) -> 1294500 | G79: =SUM(F69:F78) -> 1289500 | K79: =SUM(J69:J78) -> 2004500 | M79: Ali Manager | N79: 20000 | R79: 0 | V79: 0 | AA79: =SUM(Z69:Z78) -> 3014500 | AE79: =SUM(AD69:AD78) -> 4474500 | AI79: =SUM(AH69:AH78) -> 4779500 | AM79: =SUM(AL69:AL78) -> 5307500 | AQ79: =SUM(AP69:AP78) -> 6034500 | AU79: =SUM(AT69:AT78) -> 6074500
A80: Others | E80: Others | I80: Others | O80: =SUM(N69:N79) -> 2594500 | S80: =SUM(R69:R79) -> 2474500 | W80: =SUM(V69:V79) -> 2874500 | Y80: Others | AC80: Others | AG80: Others | AK80: Others | AO80: Others | AS80: Others
A81: Fak Project | B81: 6408765 | E81: Fak Project | F81: 6408765 | I81: Fak Project | J81: 6408765 | M81: Others | Q81: Others | U81: Others | Y81: Fak Project | Z81: 6408765 | AC81: Fak Project | AD81: 6408765 | AG81: Fak Project | AH81: 6408765 | AK81: Fak Project | AL81: 6408765 | AO81: Fak Project | AP81: 6408765 | AS81: Fak Project | AT81: 6408765
A82: Zarewa Motors | B82: 149500 | E82: Zarewa Motors | F82: 149500 | I82: Zarewa Motors | J82: 149500 | M82: Fak Project | N82: 6408765 | Q82: Fak Project | R82: 6408765 | U82: Fak Project | V82: 6408765 | Y82: Zarewa Motors | Z82: 149500 | AC82: Zarewa Motors | AD82: 149500 | AG82: Zarewa Motors | AH82: 149500 | AK82: Zarewa Motors | AL82: 149500 | AO82: Zarewa Motors | AP82: 149500 | AS82: Zarewa Motors | AT82: 149500
A83: Nurul Siraj | B83: 8930616 | E83: Nurul Siraj | F83: 8930616 | I83: Nurul Siraj | J83: 8930616 | M83: Zarewa Motors | N83: 149500 | Q83: Zarewa Motors | R83: 149500 | U83: Zarewa Motors | V83: 149500 | Y83: Nurul Siraj | Z83: 8930616 | AC83: Nurul Siraj | AD83: 8930616 | AG83: Nurul Siraj | AH83: 8930616 | AK83: Nurul Siraj | AL83: 8930616 | AO83: Nurul Siraj | AP83: 8930616 | AS83: Nurul Siraj | AT83: 8930616
A84: Mining (conzonite) | B84: 2750000 | E84: Mining (conzonite) | F84: 2750000 | I84: Mining (conzonite) | J84: 2750000 | M84: Nurul Siraj | N84: 8930616 | Q84: Nurul Siraj | R84: 8930616 | U84: Nurul Siraj | V84: 8930616 | Y84: Mining (conzonite) | Z84: 2750000 | AC84: Mining (conzonite) | AD84: 2750000 | AG84: Mining (conzonite) | AH84: 2750000 | AK84: Mining (conzonite) | AL84: 2750000 | AO84: Mining (conzonite) | AP84: 2750000 | AS84: Mining (conzonite) | AT84: 2750000
A85: uche Lagos | B85: 10000000 | E85: uche Lagos | F85: 5000000 | I85: uche Lagos | J85: 5000000 | M85: Mining (conzonite) | N85: 2750000 | Q85: Mining (conzonite) | R85: 2750000 | U85: Mining (conzonite) | V85: 2750000 | Y85: uche Lagos | Z85: 2287200 | AC85: uche Lagos | AD85: 2287200 | AG85: uche Lagos | AH85: 2287200 | AK85: uche Lagos | AL85: 2287200 | AO85: uche Lagos | AP85: 2287200 | AS85: uche Lagos | AT85: 2287200
A86: Qualitec | B86: 30528000 | E86: Qualitec | F86: 30528000 | I86: Qualitec | J86: 30528000 | M86: uche Lagos | N86: 5000000 | Q86: uche RED 0.55 | R86: 15000000 | U86: uche Lagos | V86: 28480000 | Y86: Coat Lagos | Z86: 0 | AC86: ZUNGERU | AD86: 5853688 | AG86: Global Marori | AH86: 600900 | AK86: Dechemix | AL86: 10964480 | AO86: Strong | AP86: 3743420 | AS86: Strong | AT86: 3743420
A87: Global Marori | B87: 600900 | E87: Global Marori | F87: 600900 | I87: Global Marori | J87: 600900 | M87: Qualitec | N87: 4000000 | Q87: engr ilya | R87: 400000 | U87: Coat Lagos | V87: 66278106 | Y87: ZUNGERU | Z87: 21178000 | AC87: Global Marori | AD87: 600900 | AG87: Maiduguri | AH87: 9425529
A88: Maiduguri | B88: 13152729 | C88: =SUM(B81:B88) -> 72520510 | E88: Maiduguri | F88: 14425529 | G88: =SUM(F81:F88) -> 68793310 | I88: Maiduguri | J88: 14425529 | K88: =SUM(J81:J88) -> 68793310 | M88: Global Marori | N88: 600900 | Q88: Global Marori | R88: 600900 | U88: ZUNGERU | V88: 21178000 | Y88: Engr Rufai | AC88: Maiduguri | AD88: 9425529 | AE88: =SUM(AD81:AD88) -> 36406198 | AI88: =SUM(AH81:AH87) -> 30552510
M89: Maiduguri | N89: 14425529 | O89: =SUM(N82:N89) -> 42265310 | Q89: Maiduguri | R89: 9425529 | S89: =SUM(R82:R89) -> 43665310 | U89: Engr Rufai | V89: 600000 | Y89: Global Marori | Z89: 600900 | AG89: Fix Asset | AK89: Global Marori | AL89: 600900 | AO89: Global Marori | AP89: 600900 | AS89: Global Marori | AT89: 600900
A90: Fix Asset | E90: Fix Asset | I90: Fix Asset | U90: Global Marori | V90: 600900 | Y90: Maiduguri | Z90: 9425529 | AA90: =SUM(Z81:Z90) -> 51730510 | AC90: Fix Asset | AG90: Land and Building | AH90: 93242000 | AK90: Maiduguri | AL90: 9425529 | AM90: =SUM(AL81:AL90) -> 41516990 | AO90: Maiduguri | AP90: 9425529 | AQ90: =SUM(AP81:AP90) -> 34295930 | AS90: Maiduguri | AT90: 9425529 | AU90: =SUM(AT81:AT90) -> 34295930
A91: Land and Building | B91: 93242000 | E91: Land and Building | F91: 93242000 | I91: Land and Building | J91: 93242000 | M91: Fix Asset | Q91: Fix Asset | U91: Maiduguri | V91: 9425529 | W91: =SUM(V82:V91) -> 144801416 | AC91: Land and Building | AD91: 93242000 | AG91: Plant and machineries | AH91: 6972416
A92: Plant and machineries | B92: 6972416 | E92: Plant and machineries | F92: 6972416 | I92: Plant and machineries | J92: 6972416 | M92: Land and Building | N92: 93242000 | Q92: Land and Building | R92: 93242000 | Y92: Fix Asset | AC92: Plant and machineries | AD92: 6972416 | AG92: Furnitures & fittings | AH92: 56448 | AK92: Fix Asset | AO92: Fix Asset | AS92: Fix Asset
A93: Furnitures & fittings | B93: 56448 | E93: Furnitures & fittings | F93: 56448 | I93: Furnitures & fittings | J93: 56448 | M93: Plant and machineries | N93: 6972416 | Q93: Plant and machineries | R93: 6972416 | U93: Fix Asset | Y93: Land and Building | Z93: 93242000 | AC93: Furnitures & fittings | AD93: 56448 | AG93: New machine(steptiles) | AH93: 5625000 | AK93: Land and Building | AL93: 93242000 | AO93: Land and Building | AP93: 93242000 | AS93: Land and Building | AT93: 93242000
A94: New machine(steptiles) | B94: 5625000 | E94: New machine(steptiles) | F94: 5625000 | I94: New machine(steptiles) | J94: 5625000 | M94: Furnitures & fittings | N94: 56448 | Q94: Furnitures & fittings | R94: 56448 | U94: Land and Building | V94: 93242000 | Y94: Plant and machineries | Z94: 6972416 | AC94: New machine(steptiles) | AD94: 5625000 | AG94: Generator | AH94: 534750 | AK94: Plant and machineries | AL94: 6972416 | AO94: Plant and machineries | AP94: 6972416 | AS94: Plant and machineries | AT94: 6972416
A95: Generator | B95: 534750 | C95: =SUM(B91:B95) -> 106430614 | E95: Generator | F95: 534750 | G95: =SUM(F91:F95) -> 106430614 | I95: Generator | J95: 534750 | K95: =SUM(J91:J95) -> 106430614 | M95: New machine(steptiles) | N95: 5625000 | Q95: New machine(steptiles) | R95: 5625000 | U95: Plant and machineries | V95: 6972416 | Y95: Furnitures & fittings | Z95: 56448 | AC95: Generator | AD95: 534750 | AE95: =SUM(AD91:AD95) -> 106430614 | AI95: =SUM(AH90:AH94) -> 106430614 | AK95: Furnitures & fittings | AL95: 56448 | AO95: Furnitures & fittings | AP95: 56448 | AS95: Furnitures & fittings | AT95: 206448
C96: =SUM(C56:C95) -> 334661175 | G96: =SUM(G56:G95) -> 320426330 | K96: =SUM(K56:K95) -> 293412450 | M96: Generator | N96: 534750 | O96: =SUM(N92:N96) -> 106430614 | Q96: Generator | R96: 534750 | S96: =SUM(R92:R96) -> 106430614 | U96: Furnitures & fittings | V96: 56448 | Y96: New machine(steptiles) | Z96: 5625000 | AE96: =SUM(AE56:AE95) -> 363585410 | AI96: =SUM(AI56:AI95) -> 357902435 | AK96: New machine(steptiles) | AL96: 5625000 | AO96: New machine(steptiles) | AP96: 5625000 | AS96: New machine(steptiles) | AT96: 5625000
O97: =SUM(O56:O96) -> 242834450 | S97: =SUM(S56:S96) -> 305602536 | U97: New machine(steptiles) | V97: 5625000 | Y97: Generator | Z97: 534750 | AA97: =SUM(Z93:Z97) -> 106430614 | AG97: Creditors | AK97: Generator | AL97: 534750 | AM97: =SUM(AL93:AL97) -> 106430614 | AO97: Generator | AP97: 534750 | AQ97: =SUM(AP93:AP97) -> 106430614 | AS97: Generator | AT97: 534750 | AU97: =SUM(AT93:AT97) -> 106580614
A98: Creditors | E98: Creditors | I98: Creditors | U98: Generator | V98: 534750 | W98: =SUM(V94:V98) -> 106430614 | AA98: =SUM(AA56:AA97) -> 307485535 | AC98: Creditors | AG98: BOI | AI98: 49119258 | AM98: =SUM(AM56:AM97) -> 3.9791004e+08 | AQ98: =SUM(AQ56:AQ97) -> 3.4712422e+08 | AU98: =SUM(AU56:AU97) -> 348902285
A99: BOI | C99: 69969500 | E99: BOI | G99: 66439500 | I99: BOI | K99: 63033500 | M99: Creditors | Q99: Creditors | W99: =SUM(W56:W98) -> 3.9564863e+08 | AC99: BOI | AE99: 49119258 | AG99: Strong Kano
A100: Strong Kano | C100: 0 | E100: Strong Kano | G100: 0 | I100: Strong Kano | K100: 11942800 | M100: BOI | O100: 59399500 | Q100: BOI | S100: 55966460 | Y100: Creditors | AC100: Strong Kano | AE100: 38939160 | AG100: Zungeru | AI100: 40314222 | AK100: Creditors | AO100: Creditors | AS100: Creditors
A101: Jalingo Branch | C101: 1966293 | E101: Jalingo Branch | G101: 1966293 | I101: Jalingo Branch | K101: 1966293 | M101: Strong Kano | O101: 0 | Q101: Strong Kano | S101: 56665780 | U101: Creditors | Y101: Shuaibu Adamu | AA101: 1800000 | AC101: Jalingo Branch | AE101: 27966293 | AG101: Jalingo Branch | AI101: 27966293 | AK101: BOI | AM101: 49119258 | AO101: BOI | AQ101: 45779343 | AS101: BOI | AU101: 45779343
A102: Shuaibu Adamu | C102: 1800000 | E102: Shuaibu Adamu | G102: 1800000 | I102: Shuaibu Adamu | K102: 1800000 | M102: Shuaibu Adamu | O102: 1800000 | Q102: Shuaibu Adamu | S102: 1800000 | U102: Shuaibu Adamu | W102: 1800000 | Y102: BOI | AA102: 52521951 | AC102: Yola Branch | AE102: 15668727 | AG102: Yola Branch | AI102: 15668727 | AK102: Strong Kano | AM102: 18453960 | AO102: Strong Kano | AQ102: 0 | AS102: Strong Kano | AU102: 0
A103: Yola Branch | C103: 15818000 | E103: Yola Branch | G103: 17656000 | I103: Yola Branch | K103: 17656000 | M103: Jalingo Branch | O103: 1966293 | Q103: Jalingo Branch | S103: 1966293 | U103: BOI | W103: 52521951 | Y103: Strong Kano | AA103: 50669580 | AC103: Ibrahim Abubakar | AE103: 317200 | AG103: Ibrahim Abubakar | AI103: 317200 | AK103: Tanimu | AM103: 1465000 | AO103: Tanimu | AQ103: 1465000 | AS103: Tanimu | AU103: 1465000
A104: Ibrahim Abubakar | C104: 317200 | E104: Ibrahim Abubakar | G104: 317200 | I104: Ibrahim Abubakar | K104: 317200 | M104: Yola Branch | O104: 16656000 | Q104: Yola Branch | S104: 16656000 | U104: Strong Kano | W104: 59449920 | Y104: Jalingo Branch | AA104: 1966293 | AC104: BAWA Abubakar | AE104: 300000 | AG104: BAWA Abubakar | AI104: 300000 | AK104: Haruna | AM104: 250000 | AO104: Haruna | AQ104: 250000 | AS104: Haruna | AU104: 250000
A105: BAWA Abubakar | C105: 300000 | E105: BAWA Abubakar | G105: 300000 | I105: BAWA Abubakar | K105: 300000 | M105: Ibrahim Abubakar | O105: 317200 | Q105: Ibrahim Abubakar | S105: 317200 | U105: Jalingo Branch | W105: 1966293 | Y105: Yola Branch | AA105: 16656000 | AC105: Patrick | AE105: 503000 | AG105: Patrick | AI105: 503000 | AK105: Jalingo Branch | AM105: 3966293 | AO105: Jalingo Branch | AQ105: 3966293 | AS105: Jalingo Branch | AU105: 3966293
A106: Patrick | C106: 503000 | E106: Patrick | G106: 503000 | I106: Patrick | K106: 503000 | M106: BAWA Abubakar | O106: 300000 | Q106: BAWA Abubakar | S106: 300000 | U106: Yola Branch | W106: 16656000 | Y106: Ibrahim Abubakar | AA106: 317200 | AC106: Engr Ozize | AE106: 659600 | AG106: Engr Ozize | AI106: 659600 | AK106: Zungeru | AM106: 78688132 | AO106: Zungeru | AQ106: 78688132 | AS106: Zungeru | AU106: 78688132
...

Sheet Sheet1
C1: Summary Of Kaduna Asset for a year
D2: Overhead | E2: External Expenses | F2: Profit | G2: Asset
B3: 2024 | C3: Aug | D3: 1655578 | E3: 2348000 | F3: 12571620 | G3: 212204601
C4: Sep | D4: 1722954 | E4: 1174500 | F4: -1982566 | G4: 226090314
C5: oct | D5: 1341078 | E5: 1396000 | F5: -5502340 | G5: 191058519
C6: nov | D6: 1118000 | E6: 1615000 | F6: 14511010 | G6: 1.9685628e+08
C7: dec | D7: 2022500 | E7: 678000 | F7: -601835.2 | G7: 1.9531822e+08
B8: 2025 | C8: jan | D8: 1563611 | E8: 303000 | F8: -1019480 | G8: 191783632
C9: feb | D9: 2086500 | E9: 3375000 | F9: -6888480.8 | G9: 187529062
C10: mar | D10: 908000 | E10: 2385000 | F10: -1493487 | G10: 151978382
C11: apr | D11: 1204420 | E11: 2850000 | F11: 2165043 | G11: 150339182
C12: may | D12: 2723000 | E12: 364000 | F12: 1291442 | G12: 156715644
C13: jun | D13: 2944000 | E13: 1564350 | F13: 9738476 | G13: 1.7057536e+08
C14: jul | D14: 2094500 | E14: 752000 | F14: 8642577 | G14: 168642330
C15: aug | D15: 1618100 | E15: 3183000 | F15: 23309926 | G15: 217732991
B16: Total | D16: =SUM(D3:D15) -> 23002241 | E16: =SUM(E3:E15) -> 21987850 | F16: =SUM(F3:F15) -> 54741905 | G16: 217732991

Sheet Stock
B1: END OF THE MONTH OF SEPTEMBER 2023 | H1: END OF THE MONTH OF APRIL STOCK 2024 | P1: END OF THE MONTH OF MAY 2024 | X1: END OF THE MONTH OF JUNE 2024 | AF1: END OF THE MONTH OF JUly 2024 | AM1: END OF THE MONTH OF AUGUST | AT1: END OF THE MONTH OF SEPTEMBER 2024 | BA1: END OF THE MONTH OF OCTOBER 2024 | BH1: END OF THE MONTH OF November 2024 | BO1: END OF THE MONTH OF DECEMBER2024 | BV1: Stock for the end of the month of April 2025 | CC1: Stock for the end of the month of May 2025 | CJ1: Stock for the end of the month of June 2025 | CQ1: Stock for the end of the month of July 2025 | CX1: Stock for the end of the month of August 2025 | DD1: Stock for the end of the month of September 2025 | DL1: Stock for the end of the month of October 2025 | DS1: Stock for the end of the month of November 2025 | DZ1: Stock for the end of the month of December 2025
B2: S/N | C2: CLOUR | D2: COIL NO | E2: KG | F2: REMARK | H2: S/N | I2: COLOUR | J2: COIL NO | K2: KG | L2: REMARK | P2: S/N | Q2: COLOUR | R2: COIL NO | S2: KG | T2: REMARK | X2: S/N | Y2: COLOUR | Z2: COIL NO | AA2: KG | AB2: REMARK | AF2: S/N | AG2: COLOUR | AH2: COIL NO | AI2: KG | AJ2: REMARK | AM2: S/N | AN2: COLOUR | AO2: COIL NO | AP2: KG | AQ2: REMARK | AT2: S/N | AU2: COLOUR | AV2: COIL NO | AW2: KG | AX2: REMARK | BA2: S/N | BB2: COLOUR | BC2: COIL NO | BD2: KG | BE2: REMARK | BH2: S/N | BI2: COLOUR | BJ2: COIL NO | BK2: KG | BL2: REMARK | BO2: S/N | BP2: COLOUR | BQ2: COIL NO | BR2: KG | BS2: REMARK | BV2: S/N | BW2: Colour | BX2: C/No | BY2: KG | BZ2: Remark | CC2: S/N | CD2: Colour | CE2: C/No | CF2: KG | CG2: Remark | CJ2: S/N | CK2: Colour | CL2: C/No | CM2: KG | CN2: Remark | CQ2: S/N | CR2: Colour | CS2: C/No | CT2: KG | CU2: Remark | CX2: S/N | CY2: Colour | CZ2: C/No | DA2: KG | DB2: Remark | DD2: S/N | DE2: COLOUR | DF2: C/No | DG2: KG | DH2: REMARK | DL2: S/N | DM2: Colour | DN2: C/N | DO2: KG | DP2: Remark | DS2: S/N | DT2: COLOUR | DU2: C/NO | DV2: KG | DZ2: S/N | EA2: COLOUR | EB2: C/NO | EC2: KG | ED2: REMARK
B3: 0.45 | H3: 0.45 | Q3: 0.45 | Y3: 0.45 | AG3: 0.45 | AM3: 0.45 | AT3: 0.45 | BA3: 0.45 | BH3: 0.45 | BO3: 0.45 | BV3: 0.45 | CC3: 0.45 | CJ3: 0.45 | CQ3: 0.45 | CX3: 0.45 | DD3: 0.45 | DL3: 0.45 | DS3: 0.55F | DZ3: 0.7
B4: 1 | C4: GB | D4: 1399 | E4: 1766 | H4: 1 | I4: IV | J4: 1257 | K4: 360 | P4: 1 | Q4: GB | R4: 1399 | S4: 1530 | X4: 1 | Y4: GB | Z4: 1399 | AA4: 1515 | AF4: 1 | AG4: GB | AH4: 1399 | AI4: 1445 | AM4: 1 | AN4: GB | AO4: 1399 | AP4: 1421 | AT4: 1 | AU4: IV | AV4: 1257 | AW4: 264 | BA4: 1 | BB4: IV | BC4: 1257 | BD4: 264 | BH4: 1 | BI4: IV | BJ4: 1257 | BK4: 264 | BO4: 1 | BP4: IV | BQ4: 1257 | BR4: 231 | BV4: 1 | BW4: IV | BX4: 1257 | BY4: 170 | CC4: 1 | CD4: IV | CE4: 1257 | CF4: 170 | CJ4: 1 | CK4: IV | CL4: 1257 | CM4: 156 | CQ4: 1 | CR4: GB | CS4: 1399 | CT4: 888 | CX4: 1 | CY4: GB | CZ4: 1399 | DA4: 862 | DD4: 1 | DE4: BG | DF4: 1435 | DG4: 68 | DL4: 1 | DM4: IV | DN4: 1257 | DO4: 84 | DS4: 1 | DT4: HMB | DU4: 1878 | DV4: 778 | DZ4: 1 | EA4: TCR | EB4: 1552 | EC4: 55
B5: 2 | C5: IV | D5: 1257 | E5: 745 | H5: 2 | I5: GB | J5: 1399 | K5: 1671 | P5: 2 | Q5: IV | R5: 1257 | S5: 314 | X5: 2 | Y5: IV | Z5: 1257 | AA5: 307 | AF5: 2 | AG5: IV | AH5: 1257 | AI5: 302 | AM5: 2 | AN5: IV | AO5: 1257 | AP5: 282 | AT5: 2 | AU5: GB | AV5: 1399 | AW5: 1365 | BA5: 2 | BB5: GB | BC5: 1399 | BD5: 1252 | BH5: 2 | BI5: GB | BJ5: 1399 | BK5: 1187 | BO5: 2 | BP5: GB | BQ5: 1399 | BR5: 1154 | BV5: 2 | BW5: GB | BX5: 1399 | BY5: 1101 | CC5: 2 | CD5: GB | CE5: 1399 | CF5: 954 | CJ5: 2 | CK5: GB | CL5: 1399 | CM5: 888 | CQ5: 2 | CR5: BG | CS5: 1435 | CT5: 173 | CX5: 2 | CY5: BG | CZ5: 1435 | DA5: 139 | DD5: 2 | DE5: IV | DF5: 1257 | DG5: 125 | DL5: 2 | DM5: BG | DN5: 1435 | DO5: 50 | DS5: 2 | DT5: PR | DU5: 1811 | DV5: 34 | DZ5: 2 | EA5: DG | EB5: 1594 | EC5: 64
B6: 3 | C6: BG | D6: 1331 | E6: 1064 | H6: 3 | I6: BG | J6: 1435 | K6: 485 | P6: 3 | Q6: BG | R6: 1416 | S6: 388 | X6: 3 | Y6: BG | Z6: 1416 | AA6: 388 | AF6: 3 | AG6: BG | AH6: 1416 | AI6: 388 | AM6: 3 | AN6: BG | AO6: 1416 | AP6: 388 | AT6: 3 | AU6: BG | AV6: 1455 | AW6: 413 | BA6: 3 | BB6: BG | BC6: 1455 | BD6: 413 | BH6: 3 | BI6: BG | BJ6: 1435 | BK6: 379 | BO6: 3 | BP6: BG | BQ6: 1435 | BR6: 388 | BV6: 3 | BW6: BG | BX6: 1435 | BY6: 351 | CC6: 3 | CD6: BG | CE6: 1435 | CF6: 250 | CJ6: 3 | CK6: BG | CL6: 1435 | CM6: 250 | CQ6: 3 | CR6: IV | CS6: 1257 | CT6: 121 | CX6: 3 | CY6: IV | CZ6: 1257 | DA6: 125 | DD6: 3 | DE6: GB | DF6: 1399 | DG6: 847 | DL6: 3 | DM6: GB | DN6: 1399 | DO6: 841 | DT6: PR | DV6: 758 | DZ6: 3 | EA6: IV | EB6: 1597 | EC6: 161
B7: 4 | C7: PR | D7: 1198 | E7: 220 | H7: 4 | I7: BG BIG | J7: 1416 | K7: 388 | P7: 4 | Q7: BG | R7: 1435 | S7: 485 | X7: 4 | Y7: BG | Z7: 1435 | AA7: 453 | AF7: 4 | AG7: BG | AH7: 1435 | AI7: 413 | AM7: 4 | AN7: BG | AO7: 1435 | AP7: 413 | AT7: 4 | AU7: BG | AV7: 1416 | AW7: 388 | BA7: 4 | BB7: BG | BC7: 1416 | BD7: 388 | BH7: 4 | BI7: BG | BJ7: 1415 | BK7: 100 | BO7: 4 | BP7: BG | BQ7: 1415 | BR7: 103 | BY7: =SUM(BY4:BY6) -> 1622 | CF7: 1374 | CM7: 1294 | CT7: =SUM(CT4:CT6) -> 1182 | DA7: =SUM(DA4:DA6) -> 1126 | DG7: =SUM(DG4:DG6) -> 1040 | DO7: =SUM(DO4:DO6) -> 975 | DT7: NB | DV7: 741 | DZ7: 4 | EA7: ST | EB7: 1604 | EC7: 540
BK8: =SUM(BK4:BK7) -> 1930 | BR8: =SUM(BR4:BR7) -> 1876 | BV8: 0.55 | CC8: 0.55 | CJ8: 0.55 | CQ8: 0.55 | DT8: NB | DV8: 389 | DZ8: 5 | EA8: GB | EB8: 1866 | EC8: 225
E9: =SUM(E4:E7) -> 3795 | H9: 5 | I9: BG BIG | J9: 1415 | K9: 652 | P9: 5 | Q9: BG BIG | R9: 1415 | S9: 652 | X9: 5 | Y9: BG BIG | Z9: 1415 | AA9: 652 | AF9: 5 | AG9: BG BIG | AH9: 1415 | AI9: 633 | AM9: 5 | AN9: BG BIG | AO9: 1415 | AP9: 633 | AT9: 5 | AU9: BG | AV9: 1415 | AW9: 633 | BA9: 5 | BB9: BG | BC9: 1415 | BD9: 633 | BH9: 0.55 | BO9: 0.55 | BV9: 4 | BW9: GB | BX9: 1397 | BY9: 78 | CC9: 4 | CD9: GB | CE9: 1441 | CF9: 30 | CJ9: 4 | CK9: TB | CL9: 1571 | CM9: 44 | CQ9: 4 | CR9: TB | CS9: 1571 | CT9: 44 | CX9: 0.55 | DD9: 0.55F | DE9: . | DL9: 0.55 | EC9: 1045
B10: 0.55 | K10: =SUM(K4:K9) -> 3556 | S10: =SUM(S4:S9) -> 3369 | AA10: =SUM(AA4:AA9) -> 3315 | AI10: =SUM(AI4:AI9) -> 3181 | AP10: =SUM(AP4:AP9) -> 3137 | AW10: =SUM(AW4:AW9) -> 3063 | BD10: =SUM(BD4:BD9) -> 2950 | BH10: 5 | BI10: IV | BJ10: 1573 | BK10: 305 | BO10: 5 | BP10: IV | BQ10: 1573 | BR10: 248 | BV10: 5 | BW10: GB | BX10: 1441 | BY10: 30 | CC10: 5 | CD10: GB | CE10: 1397 | CF10: 76 | CJ10: 5 | CK10: GB | CL10: 1441 | CM10: 30 | CQ10: 5 | CR10: GB | CS10: 1441 | CT10: 30 | CX10: 4 | CY10: IV | CZ10: 1441 | DA10: 30 | DD10: 4 | DE10: BB | DF10: 1577 | DG10: 27 | DL10: 4 | DM10: GB | DN10: 1414 | DO10: 30 | DS10: 3 | DT10: BB | DU10: 1577 | DV10: 14
B11: 5 | C11: IV | D11: 1390 | E11: 2113 | H11: 0.55 | Q11: 0.55 | Y11: 0.55 | AG11: 0.55 | AM11: 0.55 | AT11: 0.55 | BA11: 0.55 | BH11: 6 | BI11: IV | BJ11: 1570 | BK11: 129 | BO11: 6 | BP11: IV | BQ11: 1570 | BR11: 129 | BV11: 6 | BW11: TB | BX11: 1571 | BY11: 388 | CC11: 6 | CD11: TB | CE11: 1571 | CF11: 90 | CM11: 74 | CT11: =SUM(CT9:CT10) -> 74 | DA11: 30 | DD11: 5 | DE11: HMB | DF11: 1791 | DG11: 8 | DO11: =SUM(DO10) -> 30 | DV11: =SUM(DV4:DV10) -> 2714 | DZ11: 0.6
B12: 6 | C12: IV | D12: 1380 | E12: 933 | H12: 6 | I12: GB | J12: 1441 | K12: 609 | P12: 6 | Q12: IV | R12: 1503 | S12: 56 | X12: 6 | Y12: IV | Z12: 1503 | AA12: 56 | AF12: 6 | AG12: IV | AH12: 1503 | AI12: 37 | AM12: 6 | AN12: IV | AO12: 1539 | AP12: 488 | AT12: 6 | AU12: IV | AV12: 1573 | AW12: 1370 | BA12: 6 | BB12: IV | BC12: 1573 | BD12: 1340 | BH12: 7 | BI12: GB | BJ12: 1397 | BK12: 78 | BO12: 7 | BP12: GB | BQ12: 1397 | BR12: 78 | BV12: 7 | BW12: PR | BX12: 1598 | BY12: 5 | CC12: 7 | CD12: IV | CE12: 1573 | CF12: 67 | CJ12: 0.55 FULL | CQ12: 0.55F | DE12: NB | DG12: 741 | DZ12: 6 | EA12: IV | EB12: 1455 | EC12: 148
B13: 7 | C13: IV | D13: 1382 | E13: 126 | H13: 7 | I13: GB | J13: 1397 | K13: 78 | P13: 7 | Q13: IV | R13: 1521 | S13: 995 | X13: 7 | Y13: IV | Z13: 1521 | AA13: 1016 | AF13: 7 | AG13: IV | AH13: 1521 | AI13: 39 | AM13: 7 | AN13: IV | AO13: 1512 | AP13: 39 | AT13: 7 | AU13: IV | AV13: 1570 | AW13: 232 | BA13: 7 | BB13: IV | BC13: 1570 | BD13: 220 | BH13: 8 | BI13: GB | BJ13: 1441 | BK13: 30 | BO13: 8 | BP13: GB | BQ13: 1441 | BR13: 30 | BY13: =SUM(BY9:BY12) -> 501 | CF13: 263 | CJ13: 6 | CK13: GB | CL13: 1481 | CM13: 4 | CQ13: 6 | CR13: PL | CS13: 1760 | CT13: 101 | CX13: 0.55F | DE13: NB | DG13: 389 | DL13: 0.55FULL | DS13: 0.7 | EC13: 148
B14: 8 | C14: IV | D14: 1284 | E14: 65 | H14: 8 | I14: GB | J14: 1341 | K14: 27 | P14: 8 | Q14: IV 0.60 | R14: 1455 | S14: 161 | X14: 8 | Y14: IV 0.60 | Z14: 1445 | AA14: 161 | AF14: 8 | AG14: IV 0.60 | AH14: 1445 | AI14: 161 | AM14: 8 | AN14: IV | AO14: 1503 | AP14: 37 | AT14: 8 | AU14: GB | AV14: 1528 | AW14: 296 | BA14: 8 | BB14: GB | BC14: 1528 | BD14: 115 | BH14: 9 | BI14: NB | BJ14: 1554 | BK14: 76 | BO14: 9 | BP14: NB | BQ14: 1554 | BR14: 75 | BV14: 0.55F | CC14: 0.55 FULL | CJ14: 7 | CK14: TCR | CL14: 1508 | CM14: 9 | CQ14: 7 | CR14: HMB | CS14: 1791 | CT14: 8 | CX14: 5 | CY14: BG | CZ14: 1410 | DA14: 52 | DE14: PR | DG14: 105 | DL14: 5 | DM14: PR | DO14: 758 | DS14: 2 | DT14: IV | DU14: 1597 | DV14: 101
B15: 9 | C15: IV | D15: 1316 | E15: 48 | H15: 9 | I15: IV | J15: 1464 | K15: 1250 | P15: 9 | Q15: BG | R15: 1502 | S15: 1451 | X15: 9 | Y15: BG | Z15: 1502 | AA15: 1173 | AF15: 9 | AG15: BG | AH15: 1502 | AI15: 741 | AM15: 9 | AN15: GB | AO15: 1528 | AP15: 686 | AT15: 9 | AU15: GB | AV15: 1397 | AW15: 78 | BA15: 9 | BB15: GB | BC15: 1397 | BD15: 78 | BH15: 10 | BI15: HMB | BJ15: 1523 | BK15: 71 | BO15: 10 | BP15: TB | BQ15: 1571 | BR15: 699 | BV15: 8 | BW15: BG | BX15: 1410 | BY15: 52 | CC15: 8 | CD15: BB | CE15: 1577 | CF15: 149 | CJ15: 8 | CK15: BG | CL15: 1410 | CM15: 52 | CQ15: 8 | CR15: BG | CS15: 1410 | CT15: 52 | CX15: 6 | CY15: TCR | CZ15: 1811 | DA15: 109 | DE15: PR | DG15: 2172 | DL15: 6 | DM15: NB | DO15: 741 | DS15: 3 | DT15: DG | DU15: 1594 | DV15: 64 | DZ15: 0.55F
B16: 10 | C16: IV | D16: 1332 | E16: 37 | H16: 10 | I16: IV | J16: 1434 | K16: 181 | P16: 10 | Q16: BG | R16: 1423 | S16: 144 | X16: 10 | Y16: BG | Z16: 1423 | AA16: 109 | AF16: 10 | AG16: BG | AH16: 1423 | AI16: 109 | AM16: 10 | AN16: GB | AO16: 1397 | AP16: 78 | AT16: 10 | AU16: GB | AV16: 1441 | AW16: 30 | BA16: 10 | BB16: GB | BC16: 1441 | BD16: 30 | BH16: 11 | BI16: TB | BJ16: 1571 | BK16: 999 | BO16: 11 | BP16: BG | BQ16: 1423 | BR16: 90 | BV16: 9 | BW16: BG | BX16: 1586 | BY16: 33 | CC16: 9 | CD16: GB | CE16: 1481 | CF16: 8 | CM16: 65 | CQ16: 9 | CR16: TCR | CS16: 1508 | CT16: 9 | CY16: PR | CZ16: Lagos | DA16: 10308 | DE16: PR | DG16: 1314 | DL16: 7 | DM16: NB | DO16: 389 | DS16: 4 | DT16: ST | DU16: 1604 | DV16: 542 | DZ16: 7 | EA16: HMB | EB16: 1878 | EC16: 732
B17: 11 | C17: IV | D17: 1370 | E17: 56 | H17: 11 | I17: IV | J17: 1390 | K17: 38 | P17: 11 | Q17: TB | R17: 1443 | S17: 341 | X17: 11 | Y17: TB | Z17: 1443 | AA17: 96 | AF17: 11 | AG17: TB | AH17: 1443 | AI17: 52 | AM17: 11 | AN17: GB | AO17: 1441 | AP17: 30 | AT17: 11 | AU17: NB | AV17: 1554 | AW17: 1035 | BA17: 11 | BB17: NB | BC17: 1554 | BD17: 677 | BH17: 12 | BI17: BG | BJ17: 1423 | BK17: 97 | BR17: =SUM(BR10:BR16) -> 1349 | BV17: 10 | BW17: BB | BX17: 1577 | BY17: 194 | CC17: 10 | CD17: TCR | CE17: 1508 | CF17: 9 | CJ17: 0.6 | CQ17: 10 | CR17: TCR | CS17: 1789 | CT17: 1243 | CX17: 7 | CY17: HMB | CZ17: 1791 | DA17: 8 | DE17: PR | DG17: 957 | DL17: 8 | DM17: BB | DN17: 1577 | DO17: 27 | DS17: 5 | DT17: PR | DU17: 1552 | DV17: 55 | EA17: PR | EC17: 758
B18: 12 | C18: GB | D18: 1397 | E18: 1118 | H18: 12 | I18: IV | J18: 1380 | K18: 39 | P18: 12 | Q18: NB | R18: 1438 | S18: 44 | X18: 12 | Y18: NB | Z18: 1438 | AA18: 38 | AF18: 13 | AG18: GB | AH18: 1441 | AI18: 30 | AM18: 12 | AN18: BG | AO18: 1502 | AP18: 271 | AT18: 12 | AU18: HMB | AV18: 1523 | AW18: 343 | BA18: 12 | BB18: HMB | BC18: 1523 | BD18: 711 | BK18: =SUM(BK10:BK17) -> 1785 | BO18: 0.55 FULL | BV18: 11 | BW18: GB | BX18: 1481 | BY18: 21 | CC18: 11 | CD18: BG | CE18: 1586 | CF18: 33 | CJ18: 9 | CK18: IV | CL18: 1445 | CM18: 161 | CQ18: 11 | CR18: TCR | CS18: 1790 | CT18: 2263 | CX18: 8 | CY18: BB | CZ18: 1577 | DA18: 27 | DE18: PR | DG18: 758 | DL18: 9 | DM18: HMB | DN18: 1791 | DO18: 8 | DT18: GB | DU18: 1866 | DV18: 405 | EA18: NB | EC18: 741
B19: 13 | C19: GB | D19: 1330 | E19: 47 | H19: 13 | I19: IV | J19: 1440 | K19: 63 | P19: 13 | Q19: GB | R19: 1441 | S19: 398 | X19: 13 | Y19: GB | Z19: 1441 | AA19: 30 | AF19: 14 | AG19: GB | AH19: 1397 | AI19: 78 | AM19: 13 | AN19: BG | AO19: 1423 | AP19: 109 | AT19: 13 | AU19: TB | AV19: 1443 | AW19: 52 | BA19: 14 | BB19: TB | BC19: 1571 | BD19: 1579 | BH19: 0.55 FULL | BO19: 12 | BP19: BG | BQ19: 1586 | BR19: 56 | BV19: 12 | BW19: PR | BX19: 1508 | BY19: 11 | CC19: 12 | CD19: BG | CE19: 1410 | CF19: 52 | CM19: 161 | CQ19: 12 | CR19: GB | CS19: 1481 | CT19: 4 | DA19: =SUM(DA14:DA18) -> 10504 | DD19: 6 | DE19: TCR | DF19: 1811 | DG19: 102 | DO19: =SUM(DO14:DO18) -> 1923 | DV19: =SUM(DV14:DV18) -> 1167 | EA19: NB | EC19: 389
B20: 14 | C20: BG | D20: 1398 | E20: 1788 | H20: 14 | I20: NB | J20: 1438 | K20: 180 | P20: 14 | Q20: GB | R20: 1397 | S20: 78 | X20: 14 | Y20: GB | Z20: 1397 | AA20: 78 | AF20: 15 | AG20: ST | AH20: 1371 | AI20: 165 | AM20: 14 | AN20: HMB | AO20: 1523 | AP20: 528 | AT20: 14 | AU20: TB | AV20: 1571 | AW20: 1784 | BA20: 15 | BB20: BG | BC20: 1558 | BD20: 299 | BH20: 13 | BI20: BG | BJ20: 1586 | BK20: 56 | BO20: 13 | BP20: IV | BQ20: 1609 | BR20: 334 | BY20: =SUM(BY15:BY19) -> 311 | CF20: 251 | CJ20: 0.7 | CT20: =SUM(CT13:CT19) -> 3680 | DG20: =SUM(DG10:DG19) -> 6573 | DZ20: 8 | EA20: HMB | EB20: 1791 | EC20: 8
B21: 15 | C21: BG | D21: 1326 | E21: 40 | H21: 15 | I21: PR | J21: 1394 | K21: 242 | P21: 15 | Q21: ST | R21: 1371 | S21: 719 | X21: 15 | Y21: ST | Z21: 1371 | AA21: 270 | AF21: 16 | AG21: GB | AH21: 1528 | AI21: 1053 | AM21: 15 | AN21: NB | AO21: 1554 | AP21: 1955 | AT21: 15 | AU21: BG | AV21: 1558 | AW21: 1152 | BA21: 16 | BB21: BG | BC21: 1502 | BD21: 176 | BH21: 14 | BI21: IV | BJ21: 1609 | BK21: 328 | BO21: 14 | BP21: BG | BQ21: 1410 | BR21: 52 | BV21: 0.6 | CC21: 0.6 | CJ21: 10 | CK21: ST | CL21: 1604 | CM21: 963 | CQ21: 0.6 | CX21: 0.6 | DL21: 0.6 | DS21: 0.6 | DZ21: 9 | EA21: BB | EB21: 1577 | EC21: 114
B22: 16 | C22: HMB | D22: 1354 | E22: 662 | H22: 16 | I22: BG | J22: 1423 | K22: 459 | S22: =SUM(S12:S21) -> 4387 | X22: 16 | Y22: GB | Z22: 1528 | AA22: 1694 | AG22: GB | AH22: 1539 | AI22: 1048 | AM22: 16 | AN22: TB | AO22: 1443 | AP22: 52 | AT22: 16 | AU22: BG | AV22: 1502 | AW22: 213 | BA22: 18 | BB22: BG | BC22: 1423 | BD22: 109 | BH22: 15 | BI22: BG | BJ22: 1410 | BK22: 52 | BO22: 15 | BP22: TC R | BQ22: 1598 | BR22: 28 | BV22: 13 | BW22: IV | BX22: 1445 | BY22: 110 | CC22: 13 | CD22: IV | CE22: 1455 | CF22: 161 | CJ22: 11 | CK22: IV | CL22: 1597 | CM22: 101 | CQ22: 13 | CR22: IV | CS22: 1455 | CT22: 161 | CX22: 9 | CY22: IV | CZ22: 1455 | DA22: 148 | DD22: 0.55 | DL22: 10 | DM22: IV | DN22: 1455 | DO22: 148 | DS22: 6 | DT22: IV | DU22: 1455 | DV22: 148 | EC22: =SUM(EC16:EC21) -> 2742
B23: 17 | C23: NB | D23: 1386 | E23: 1432 | H23: 17 | I23: BG | J23: 1326 | K23: 49 | Q23: F 0.55 | X23: 17 | Y23: HMB | Z23: 1523 | AA23: 649 | AF23: 17 | AG23: HMB | AH23: 1523 | AI23: 534 | AM23: 17 | AN23: ST | AO23: 1371 | AP23: 120 | AT23: 17 | AU23: ST | AV23: 1371 | AW23: 76 | BD23: =SUM(BD12:BD22) -> 5334 | BH23: 16 | BI23: TC R | BJ23: 1598 | BK23: 28 | BO23: 16 | BP23: TC R | BQ23: 1508 | BR23: 11 | BY23: =SUM(BY22) -> 110 | CF23: 161 | CJ23: 12 | CK23: TCR | CL23: 1552 | CM23: 55 | CT23: =SUM(CT22) -> 161 | DA23: 148 | DD23: 7 | DE23: GB | DF23: 1441 | DG23: 30 | DO23: =SUM(DO22) -> 148 | DV23: =SUM(DV22) -> 148
B24: 18 | C24: PR | D24: 1394 | E24: 1553 | H24: 18 | I24: TB | J24: 1443 | K24: 438 | P24: 16 | Q24: BG | R24: 1414 | S24: 110 | AA24: =SUM(AA12:AA23) -> 5370 | AI24: =SUM(AI12:AI23) -> 4047 | AP24: =SUM(AP12:AP23) -> 4393 | AT24: 18 | AU24: BG | AV24: 1423 | AW24: 109 | BA24: 0.55 FULL | BH24: 17 | BI24: TC R | BJ24: 1508 | BK24: 11 | BO24: 17 | BP24: BB | BQ24: 1577 | BR24: 194 | BV24: 0.7 | CC24: 0.7 | CJ24: 13 | CK24: DG | CL24: 1594 | CM24: 64 | CQ24: 0.7 | DG24: =SUM(DG23) -> 30 | DZ24: 0.55
B25: 19 | C25: TB | D25: 1387 | E25: 1722 | H25: 19 | I25: HMB | J25: 1354 | K25: 58 | P25: 17 | Q25: BG | R25: 1410 | S25: 142 | Y25: F 0.55 | AG25: F 0.55 | AM25: 0.55 FULL | AW25: =SUM(AW12:AW24) -> 6770 | BA25: 19 | BB25: BG | BC25: 1586 | BD25: 56 | BH25: 18 | BI25: BB | BJ25: 1577 | BK25: 194 | BO25: 18 | BP25: ST | BQ25: 1412 | BR25: 490 | BV25: 14 | BW25: IV | BX25: 1597 | BY25: 107 | CC25: 14 | CD25: ST | CE25: 1604 | CF25: 1112 | CM25: 1183 | CQ25: 14 | CR25: DG | CS25: 1594 | CT25: 64 | CX25: 0.7 | DL25: 0.7 | DS25: 0.55 | DZ25: 10 | EA25: GB | EB25: 1441 | EC25: 30
BH26: 19 | BI26: ST | BJ26: 1412 | BK26: 530 | BR26: =SUM(BR19:BR25) -> 1165 | BV26: 15 | BW26: DG | BX26: 1594 | BY26: 64 | CC26: 15 | CD26: IV | CE26: 1597 | CF26: 101 | CJ26: 0.28 | CQ26: 15 | CR26: IV | CS26: 1597 | CT26: 101 | CX26: 10 | CY26: ST | CZ26: 1604 | DA26: 963 | DD26: 0.6 | DL26: 11 | DM26: PR | DN26: 1552 | DO26: 55 | DS26: 7 | DT26: GB | DU26: 1441 | DV26: 30 | EC26: 30
B27: 20 | C27: ST | D27: 1342 | E27: 1522 | H27: 20 | I27: ST | J27: 1376 | K27: 731 | P27: 18 | Q27: IV | R27: 1480 | S27: 440 | X27: 18 | Y27: BG | Z27: 1414 | AA27: 110 | AF27: 18 | AG27: BG | AH27: 1414 | AI27: 93 | AM27: 18 | AN27: BG | AO27: 1414 | AP27: 93 | AT27: 0.55 FULL | BA27: 20 | BB27: IV | BC27: 1537 | BD27: 49 | BK27: =SUM(BK20:BK26) -> 1199 | BO27: 0.7 | BV27: 16 | BW27: ST | BX27: 1604 | BY27: 1112 | CC27: 16 | CD27: TCR | CE27: 1552 | CF27: 110 | CJ27: 14 | CK27: BG | CL27: 1757 | CM27: 1059 | CQ27: 16 | CR27: TCR | CS27: 1552 | CT27: 55 | CX27: 11 | CY27: DG | CZ27: 1594 | DA27: 64 | DD27: 8 | DE27: IV | DF27: 1455 | DG27: 148 | DL27: 12 | DM27: IV | DN27: 1597 | DO27: 101 | DS27: 8 | DT27: HMB | DU27: 1791 | DV27: 8
E28: =SUM(E11:E27) -> 13262 | K28: =SUM(K12:K27) -> 4442 | P28: 19 | Q28: PR | R28: 1508 | S28: 840 | X28: 19 | Y28: BG | Z28: 1410 | AA28: 95 | AF28: 19 | AG28: BG | AH28: 1410 | AI28: 92 | AM28: 19 | AN28: BG | AO28: 1410 | AP28: 92 | AT28: 19 | AU28: IV | AV28: 1568 | AW28: 2035 | BA28: 21 | BB28: IV | BC28: 1536 | BD28: 76 | BH28: 0.7 | BO28: 19 | BP28: IV(0.6) | BQ28: 1455 | BR28: 165 | BV28: 17 | BW28: TCR | BX28: 1552 | BY28: 110 | CC28: 17 | CD28: DG | CE28: 1594 | CF28: 64 | CJ28: 15 | CK28: IV | CL28: 1709 | CM28: 365 | CQ28: 17 | CR28: ST | CS28: 1604 | CT28: 963 | CX28: 12 | CY28: IV | CZ28: 1597 | DA28: 101 | DG28: =SUM(DG27) -> 148 | DL28: 13 | DM28: GB | DN28: 1866 | DO28: 405 | DV28: =SUM(DV26:DV27) -> 38 | DZ28: 0.45
B29: 0.55 FULL | H29: 0.55 FULL | P29: 20 | Q29: HMB | R29: 1499 | S29: 132 | X29: 20 | Y29: IV | Z29: 1524 | AA29: 1290 | AF29: 20 | AG29: IV | AH29: 1536 | AI29: 119 | AM29: 20 | AN29: IV | AO29: 1536 | AP29: 82 | AT29: 20 | AU29: IV | AV29: 1537 | AW29: 49 | BA29: 22 | BB29: NB | BC29: 1559 | BD29: 333 | BH29: 20 | BI29: IV(0.6) | BJ29: 1455 | BK29: 116 | BO29: 20 | BP29: IV | BQ29: 1597 | BR29: 110 | BY29: =SUM(BY25:BY28) -> 1393 | CF29: 1387 | CJ29: 16 | CK29: IV | CL29: 1613 | CM29: 110 | CT29: =SUM(CT25:CT28) -> 1183 | CX29: 13 | CY29: TCR | CZ29: 1522 | DA29: 55 | DL29: 14 | DM29: DG | DN29: 1594 | DO29: 64 | DZ29: 11 | EA29: GB | EB29: 1399 | EC29: 836
B30: 21 | C30: ST | D30: 1351 | E30: 675 | H30: 21 | I30: IV MILK | J30: 1480 | K30: 440 | P30: 21 | Q30: ST | R30: 1412 | S30: 1717 | X30: 21 | Y30: PR | Z30: 1508 | AA30: 744 | AF30: 21 | AG30: IV | AH30: 1537 | AI30: 49 | AM30: 21 | AN30: IV | AO30: 1537 | AP30: 49 | AT30: 21 | AU30: IV | AV30: 1536 | AW30: 108 | BA30: 23 | BB30: BG | BC30: 1410 | BD30: 52 | BH30: 21 | BI30: IV | BJ30: 1597 | BK30: 107 | BO30: 21 | BP30: TCR | BQ30: 1552 | BR30: 112 | BV30: 0.28 | CC30: 0.28 | CJ30: 17 | CK30: IV | CL30: 1650 | CM30: 92 | CQ30: 0.4AZ | DA30: =SUM(DA26:DA29) -> 1183 | DD30: 0.7 | DL30: 15 | DM30: ST | DN30: 1604 | DO30: 542 | DS30: 0.45 | EC30: 836
BH31: 22 | BI31: TCR | BJ31: 1552 | BK31: 799 | BO31: 22 | BP31: DG | BQ31: 1594 | BR31: 509 | BV31: 18 | BW31: IV | BX31: 1693 | BY31: 752 | CC31: 18 | CD31: IV | CE31: 1693 | CF31: 380 | CJ31: 18 | CK31: GB | CL31: 1734 | CM31: 66 | CQ31: 18 | CR31: IV | CS31: 1788 | CT31: 1950 | DD31: 9 | DE31: ST | DF31: 1604 | DG31: 963 | DO31: =SUM(DO26:DO30) -> 1167 | DS31: 9 | DT31: IV | DU31: 1257 | DV31: 80
B32: 22 | C32: BG | D32: 1364 | E32: 899 | H32: 22 | I32: HMB | J32: 1499 | K32: 566 | S32: =SUM(S24:S30) -> 3381 | X32: 22 | Y32: HMB | Z32: 1499 | AA32: 94 | AF32: 23 | AG32: PR | AH32: 1541 | AI32: 88 | AM32: 22 | AN32: ST | AO32: 1412 | AP32: 1318 | AT32: 22 | AU32: NB | AV32: 1559 | AW32: 333 | BA32: 25 | BB32: TC R | BC32: 1508 | BD32: 11 | BH32: 23 | BI32: DG | BJ32: 1594 | BK32: 547 | BO32: 23 | BP32: ST | BQ32: 1604 | BR32: 1112 | BV32: 19 | BW32: IV | BX32: 1650 | BY32: 92 | CC32: 19 | CD32: IV | CE32: 1619 | CF32: 100 | CJ32: 19 | CK32: TCR | CL32: 1540 | CM32: 92 | CT32: =SUM(CT31) -> 1950 | CX32: 0.4 | DD32: 10 | DE32: IV | DF32: 1597 | DG32: 101 | DS32: 10 | DT32: BG | DU32: 1435 | DV32: 50 | DZ32: 0.4
E33: =SUM(E30:E32) -> 1574 | H33: 23 | I33: BG | J33: 1414 | K33: 1058 | Q33: 0.7 | X33: 23 | Y33: ST | Z33: 1412 | AA33: 1717 | AF33: 24 | AG33: GB | AI33: 31 | AP33: =SUM(AP27:AP32) -> 1634 | AT33: 23 | AU33: BG | AV33: 1410 | AW33: 52 | BA33: 26 | BB33: BB | BC33: 1577 | BD33: 194 | BH33: 24 | BI33: ST | BJ33: 1604 | BK33: 1085 | BR33: =SUM(BR28:BR32) -> 2008 | BV33: 20 | BW33: IV | BX33: 1613 | BY33: 173 | CC33: 20 | CD33: IV | CE33: 1613 | CF33: 173 | CM33: =SUM(CM27:CM32) -> 1784 | CQ33: 0.28 | CX33: 14 | CY33: IV | CZ33: 1788 | DA33: 1950 | DD33: 11 | DE33: DG | DF33: 1594 | DG33: 64 | DL33: 0.4 | DS33: 11 | DT33: GB | DU33: 1399 | DV33: 837 | DZ33: 12 | EA33: DG | EC33: 197
B34: 0.7 | H34: 24 | I34: BG | J34: 1364 | K34: 366 | P34: 22 | Q34: ST | R34: 1376 | S34: 656 | AA34: =SUM(AA27:AA33) -> 4050 | AF34: 25 | AG34: ST | AH34: 1412 | AI34: 1672 | AM34: 0.6 | AT34: 24 | AU34: GB | AV34: 1481 | AW34: 31 | BA34: 27 | BB34: ST | BC34: 1412 | BD34: 756 | BK34: =SUM(BK29:BK33) -> 2654 | BO34: 0.28 | BV34: 21 | BW34: IV | BX34: 1680 | BY34: 130 | CC34: 21 | CD34: IV | CE34: 1709 | CF34: 2035 | CJ34: 0.24 | CQ34: 19 | CR34: IV | CS34: 1650 | CT34: 92 | DA34: 1950 | DD34: 12 | DE34: PR | DF34: 1522 | DG34: 55 | DL34: 16 | DM34: IV | DN34: 1788 | DO34: 1950 | DV34: =SUM(DV31:DV33) -> 967 | DZ34: 13 | EA34: IV | EC34: 382
B35: 23 | C35: ST | D35: 1376 | E35: 771 | H35: 25 | I35: ST | J35: 1412 | K35: 1717 | Y35: 0.7 | AI35: =SUM(AI27:AI34) -> 2144 | AM35: 23 | AN35: IV | AO35: 1445 | AP35: 161 | AT35: 25 | AU35: TC R | AV35: 1508 | AW35: 78 | BD35: =SUM(BD25:BD34) -> 1527 | BH35: 0.28 | BO35: 24 | BP35: IV | BQ35: 1617 | BR35: 831 | BV35: 22 | BW35: IV | BX35: 1619 | BY35: 100 | CC35: 22 | CD35: IV | CE35: 1650 | CF35: 92 | CJ35: 20 | CK35: HMB | CL35: 1516 | CM35: 2882 | CQ35: 20 | CR35: IV | CS35: 1771 | CT35: 346 | DG35: =SUM(DG31:DG34) -> 1183 | EC35: 579
E36: =E35 -> 771 | H36: 26 | I36: IV 0.60 | J36: 1455 | K36: 15 | Q36: 0.28 | X36: 24 | Y36: ST | Z36: 1376 | AA36: 656 | AG36: 0.7 | AM36: 0.7 | AT36: 26 | AU36: BB | AV36: 1577 | AW36: 194 | BA36: 0.7 | BH36: 25 | BI36: IV | BJ36: 1511 | BK36: 595 | BO36: 25 | BP36: IV | BQ36: 1619 | BR36: 1127 | BV36: 23 | BW36: GB | BX36: 1699 | BY36: 542 | CC36: 23 | CD36: GB | CE36: 1734 | CF36: 892 | CJ36: 21 | CK36: HMB | CL36: 1544 | CM36: 545 | CQ36: 21 | CR36: IV | CS36: 1795 | CT36: 3382 | CX36: 0.28 | DS36: 0.4
BH37: 26 | BI37: IV | BJ37: 1618 | BK37: 3186 | BO37: 26 | BP37: GB | BQ37: 1625 | BR37: 1585 | BV37: 24 | BW37: GB | BX37: 1700 | BY37: 3393 | CC37: 24 | CD37: GB | CE37: 1700 | CF37: 595 | CJ37: 22 | CK37: IV | CL37: 1716 | CM37: 178 | CQ37: 22 | CR37: IV | CS37: 1613 | CT37: 110 | CX37: 15 | CY37: IV | CZ37: 1619 | DA37: 100 | DD37: 0.4 | DL37: 0.28 | DS37: 12 | DT37: IV | DU37: 1906 | DV37: 378 | DZ37: 0.28
B38: AZ 0.28 | K38: =SUM(K30:K36) -> 4162 | P38: 23 | Q38: IV | R38: 1511 | S38: 3552 | AF38: 26 | AG38: ST | AH38: 1376 | AI38: 656 | AM38: 24 | AN38: ST | AO38: 1376 | AP38: 656 | AT38: 27 | AU38: ST | AV38: 1412 | AW38: 1216 | BA38: 28 | BB38: IV | BC38: 1455 | BD38: 161 | BH38: 27 | BI38: GB | BJ38: 1555 | BK38: 1011 | BO38: 27 | BP38: TCR | BQ38: 1540 | BR38: 890 | BV38: 25 | BW38: BG | BX38: 1620 | BY38: 244 | CC38: 25 | CD38: TCR | CE38: 1540 | CF38: 382 | CJ38: 23 | CK38: IV | CL38: 1759 | CM38: 3380 | CQ38: 23 | CR38: IV | CS38: 1772 | CT38: 144 | CX38: 16 | CY38: IV | CZ38: 1650 | DA38: 92 | DD38: 13 | DE38: IV | DF38: 1788 | DG38: 1950 | DL38: 17 | DM38: IV | DN38: 1843 | DO38: 2767 | DS38: 13 | DT38: DG | DU38: 1901 | DV38: 196 | DZ38: 14 | EA38: IV | EB38: 1613 | EC38: 110
BH39: 28 | BI39: TCR | BJ39: 1540 | BK39: 909 | BO39: 28 | BP39: BG | BQ39: 1626 | BR39: 435 | BV39: 26 | BW39: TCR | BX39: 1540 | BY39: 858 | CC39: 26 | CD39: BG | CE39: 1738 | CF39: 3144 | CJ39: 24 | CK39: IV | CL39: 1736 | CM39: 2001 | CQ39: 24 | CR39: IV | CS39: 1619 | CT39: 100 | CX39: 17 | CY39: IV | CZ39: 1820 | DA39: 2552 | DG39: =SUM(DG38) -> 1950 | DL39: 18 | DM39: IV | DN39: 1619 | DO39: 100 | DV39: =SUM(DV37:DV38) -> 574 | DZ39: 15 | EA39: IV | EB39: 1619 | EC39: 100
B40: 24 | C40: GB | D40: 1403 | E40: 3120 | H40: 0.7 | P40: 24 | Q40: IV | R40: 1458 | S40: 1310 | Y40: 0.28 | AM40: 25 | AN40: PR | AO40: 1552 | AP40: 799 | AW40: =SUM(AW28:AW38) -> 4096 | BA40: 29 | BB40: TCR | BC40: 1552 | BD40: 799 | BH40: 29 | BI40: BG | BJ40: 1534 | BK40: 851 | BR40: =SUM(BR35:BR39) -> 4868 | BY40: =SUM(BY31:BY39) -> 6284 | CC40: 27 | CD40: BG | CE40: 1620 | CF40: 244 | CJ40: 25 | CK40: IV | CL40: 1577 | CM40: 90 | CQ40: 25 | CR40: GB | CS40: 1734 | CT40: 66 | CX40: 18 | CY40: IV | CZ40: 1795 | DA40: 124 | DL40: 19 | DM40: IV | DN40: 1650 | DO40: 77 | DZ40: 16 | EA40: IV | EB40: 1650 | EC40: 77
BK41: =SUM(BK36:BK40) -> 6552 | BO41: 0.24 | BV41: 0.24 | CF41: 8037 | CJ41: 26 | CK41: GB | CL41: 1750 | CM41: 2008 | CQ41: 26 | CR41: GB | CS41: 1794 | CT41: 1953 | CX41: 19 | CY41: IV | CZ41: 1807 | DA41: 2554 | DD41: 0.28 | DL41: 20 | DM41: IV | DN41: 1613 | DO41: 110 | DS41: 0.35 | DZ41: 17 | EA41: BG | EB41: 1828 | EC41: 98
BH42: 0.24 | BO42: 29 | BP42: PR | BQ42: 1587 | BR42: 1614 | BV42: 27 | BW42: NB | BX42: 1657 | BY42: 617 | CC42: 0.24 | CJ42: 27 | CK42: TCR | CL42: 1752 | CM42: 1506 | CQ42: 27 | CR42: GB | CS42: 1773 | CT42: 235 | CX42: 20 | CY42: IV | CZ42: 1613 | DA42: 110 | DD42: 14 | DE42: IV | DF42: 1613 | DG42: 110 | DL42: 21 | DM42: GB | DN42: 1853 | DO42: 2923 | DS42: 14 | DT42: GB | DU42: 1896 | DV42: 203 | DZ42: 18 | EA42: IV | EB42: 1843 | EC42: 142
B43: 25 | C43: GB | D43: 1346 | E43: 201 | H43: 27 | I43: DG | J43: 1453 | K43: 80 | P43: 25 | Q43: BG | R43: 1468 | S43: 1310 | X43: 25 | Y43: IV | Z43: 1511 | AA43: 3552 | AG43: 0.28 | AP43: =SUM(AP35:AP40) -> 1616 | AT43: 0.6 | BA43: 30 | BB43: ST | BC43: 1376 | BD43: 656 | BH43: 30 | BI43: PR | BJ43: 1587 | BK43: 2204 | BO43: 30 | BP43: TB | BQ43: 1627 | BR43: 1507 | BV43: 28 | BW43: HMB | BX43: 1516 | BY43: 2882 | CC43: 28 | CD43: GB | CE43: 1719 | CF43: 626 | CJ43: 28 | CK43: BG | CL43: 1715 | CM43: 1903 | CQ43: 28 | CR43: TCR | CS43: 1540 | CT43: 237 | CX43: 21 | CY43: BG | CZ43: 1752 | DA43: 254 | DD43: 15 | DE43: IV | DF43: 1619 | DG43: 100 | DL43: 22 | DM43: TB | DN43: 1797 | DO43: 947 | DV43: =SUM(DV42) -> 203 | DZ43: 19 | EA43: TB | EB43: 1889 | EC43: 761
E44: =SUM(E40:E43) -> 3321 | H44: 28 | I44: HMB | J44: 1497 | K44: 859 | P44: 26 | Q44: GB | R44: 1471 | S44: 1690 | X44: 26 | Y44: IV | Z44: 1458 | AA44: 1310 | AG44: PR | AH44: 1540 | AI44: 1982 | AM44: 0.28 | AT44: 28 | AU44: IV | AV44: 1455 | AW44: 161 | BD44: =SUM(BD38:BD43) -> 1616 | BH44: 31 | BI44: TB | BJ44: 1588 | BK44: 205 | BO44: 31 | BP44: PG | BQ44: 1580 | BR44: 1922 | BV44: 29 | BW44: HMB | BX44: 1544 | BY44: 1371 | CC44: 29 | CD44: GB | CE44: 1735 | CF44: 3173 | CJ44: 29 | CK44: PG | CL44: 1634 | CM44: 535 | CQ44: 29 | CR44: BG | CS44: 1757 | CT44: 721 | CX44: 22 | CY44: TCR | CZ44: 1540 | DA44: 237 | DD44: 16 | DE44: IV | DF44: 1830 | DG44: 428 | DL44: 23 | DM44: BG | DN44: 1828 | DO44: 89 | DZ44: 20 | EA44: GB | EB44: 1914 | EC44: 321
B45: AZ 0.24 | H45: 29 | I45: ST | J45: 1376 | K45: 656 | S45: =SUM(S38:S44) -> 7862 | X45: 27 | Y45: BG | Z45: 1468 | AA45: 497 | AF45: 27 | AG45: IV | AH45: 1511 | AI45: 1832 | AM45: 26 | AN45: BG | AO45: 1468 | AP45: 127 | AT45: 0.7 | BA45: 0.28 | BH45: 32 | BI45: PG | BJ45: 1580 | BK45: 1922 | BO45: 32 | BP45: IV | BQ45: 1396 | BR45: 114 | BV45: 30 | BW45: PG | BX45: 1634 | BY45: 2229 | CC45: 30 | CD45: BG | CE45: 1715 | CF45: 3243 | CM45: 15028 | CT45: =SUM(CT34:CT44) -> 7386 | DA45: =SUM(DA37:DA44) -> 6023 | DD45: 17 | DE45: IV | DF45: 1650 | DG45: 92 | DL45: 24 | DM45: BG | DN45: 1826 | DO45: 2485 | DS45: 0.28 | DZ45: 21 | EA45: IV | EB45: 1915 | EC45: 2054
B46: 26 | C46: GB | D46: 1402 | E46: 3530 | K46: =SUM(K43:K45) -> 1595 | Q46: 0.24 | X46: 28 | Y46: GB | Z46: 1471 | AA46: 1690 | AF46: 28 | AG46: BG | AH46: 1534 | AI46: 999 | AM46: 27 | AN46: BG | AO46: 1534 | AP46: 581 | AT46: 29 | AU46: TCR | AV46: 1552 | AW46: 799 | BA46: 31 | BB46: IV | BC46: 1511 | BD46: 1029 | BH46: 33 | BI46: IV | BJ46: 1611 | BK46: 3189 | BO46: 33 | BP46: GB | BQ46: 1579 | BR46: 125 | BV46: 31 | BW46: PR | BX46: 1698 | BY46: 2648 | CC46: 31 | CD46: BG | CE46: 1692 | CF46: 2037 | CJ46: 0.22 | CQ46: 0.24 | DD46: 18 | DE46: BG | DF46: 1828 | DG46: 411 | DL46: 25 | DM46: PR | DN46: 1867 | DO46: 2011 | DS46: 15 | DT46: IV | DU46: 1893 | DV46: 3020 | DZ46: 22 | EA46: GB | EC46: 331
BH47: 34 | BI47: IV | BJ47: 1613 | BK47: 3122 | BO47: 34 | BP47: GB | BQ47: 1614 | BR47: 108 | BV47: 32 | BW47: IV | BX47: 1657 | BY47: 158 | CC47: 32 | CD47: PG | CE47: 1634 | CF47: 1555 | CJ47: 30 | CK47: IV | CL47: 1512 | CM47: 345 | CQ47: 30 | CR47: HMB | CS47: 1516 | CT47: 2882 | CX47: 0.24 | DD47: 19 | DE47: BG | DF47: 1757 | DG47: 254 | DL47: 26 | DM47: PR | DN47: 1540 | DO47: 115 | DS47: 16 | DT47: IV | DU47: 1613 | DV47: 110 | EC47: 3994
B48: 27 | C48: GB | D48: 1339 | E48: 235 | H48: 0.28 | P48: 27 | Q48: GB | R48: 1509 | S48: 2462 | AA48: =SUM(AA43:AA46) -> 7049 | AF48: 29 | AG48: BG | AH48: 1468 | AI48: 498 | AM48: 28 | AN48: GB | AO48: 1542 | AP48: 536 | AT48: 30 | AU48: ST | AV48: 1376 | AW48: 656 | BA48: 32 | BB48: GB | BC48: 1555 | BD48: 1011 | BH48: 35 | BI48: IV | BJ48: 1582 | BK48: 969 | BO48: 35 | BP48: GB | BQ48: 1615 | BR48: 831 | BV48: 33 | BW48: IV | BX48: 1396 | BY48: 114 | CC48: 33 | CD48: IV | CE48: 1727 | CF48: 195 | CJ48: 31 | CK48: IV | CL48: 1335 | CM48: 96 | CQ48: 31 | CR48: HMB | CS48: 1544 | CT48: 506 | CX48: 23 | CY48: GB | CZ48: 1766 | DA48: 129 | DL48: 27 | DM48: PR | DN48: 1810 | DO48: 168 | DS48: 17 | DT48: IV | DU48: 1650 | DV48: 77
B49: 28 | C49: GB | D49: 1391 | E49: 115 | H49: 30 | I49: IV | J49: 1458 | K49: 1345 | P49: 28 | Q49: GB | R49: 1510 | S49: 3250 | Y49: 0.24 | AF49: 30 | AG49: GB | AH49: 1471 | AI49: 1467 | AM49: 29 | AN49: GB | AO49: 1471 | AP49: 314 | AW49: =SUM(AW44:AW48) -> 1616 | BA49: 34 | BB49: TCR | BC49: 1540 | BD49: 1734 | BH49: 36 | BI49: IV | BJ49: 1396 | BK49: 112 | BO49: 36 | BP49: GB | BQ49: 1632 | BR49: 248 | BV49: 34 | BW49: IV | BY49: 113 | CC49: 34 | CD49: IV | CE49: 1716 | CF49: 2633 | CJ49: 32 | CK49: BG | CL49: 1737 | CM49: 1525 | CQ49: 32 | CR49: PG | CS49: 1634 | CT49: 112 | CX49: 24 | CY49: GB | CZ49: 1808 | DA49: 2706 | DD49: 21 | DE49: GB | DF49: 1826 | DG49: 707 | DO49: =SUM(DO38:DO48) -> 11792 | DS49: 19 | DT49: IV | DU49: 1619 | DV49: 100 | DZ49: 0.24
B50: 29 | C50: GB | D50: 1366 | E50: 224 | H50: 31 | I50: GB | J50: 1471 | K50: 2806 | P50: 29 | Q50: GB | R50: 1490 | S50: 325 | X50: 29 | Y50: GB | Z50: 1509 | AA50: 1721 | AI50: =SUM(AI44:AI49) -> 6778 | AM50: 30 | AN50: GB | AO50: 1555 | AP50: 2427 | AT50: 0.28 | BA50: 35 | BB50: BG | BC50: 1534 | BD50: 698 | BH50: 37 | BI50: GB | BJ50: 1579 | BK50: 122 | BO50: 37 | BP50: NB | BQ50: 1460 | BR50: 115 | BV50: 35 | BW50: IV | BY50: 163 | CC50: 35 | CD50: IV | CE50: 1577 | CF50: 90 | CJ50: 33 | CK50: GB | CL50: 1739 | CM50: 861 | CQ50: 33 | CR50: IV | CS50: 1759 | CT50: 2703 | CX50: 25 | CY50: GB | CZ50: 1807 | DA50: 3256 | DD50: 22 | DE50: PR | DF50: 1540 | DG50: 115 | DS50: 20 | DT50: IV | DU50: 1843 | DV50: 1136 | DZ50: 23 | EA50: HMB | EB50: 1516 | EC50: 1033
B51: 30 | C51: IV | D51: 1396 | E51: 299 | H51: 32 | I51: BG | J51: 1468 | K51: 608 | P51: 30 | Q51: GB | R51: 1366 | S51: 94 | X51: 30 | Y51: GB | Z51: 1527 | AA51: 3372 | AG51: 0.24 | AM51: 31 | AN51: PR | AO51: 1540 | AP51: 1745 | AT51: 31 | AU51: IV | AV51: 1511 | AW51: 1029 | BD51: =SUM(BD46:BD50) -> 4472 | BH51: 38 | BI51: GB | BJ51: 1614 | BK51: 2377 | BO51: 38 | BP51: NB | BQ51: 1585 | BR51: 2877 | BV51: 36 | BW51: IV | BX51: 1694 | BY51: 518 | CC51: 36 | CD51: TB | CE51: 1710 | CF51: 2002 | CM51: 2827 | CQ51: 34 | CR51: IV | CS51: 1779 | CT51: 3263 | CX51: 26 | CY51: GB | CZ51: 1735 | DA51: 127 | DD51: 23 | DE51: TB | DF51: 1797 | DG51: 1334 | DL51: 0.24 | DS51: 21 | DT51: BG | DU51: 1826 | DV51: 2501 | DZ51: 24 | EA51: HMB | EB51: 1544 | EC51: 262
B52: 31 | C52: IV | D52: 1281 | E52: 130 | H52: 33 | I52: TB | J52: 1445 | K52: 103 | P52: 31 | Q52: IV | R52: 1469 | S52: 2620 | X52: 31 | Y52: IV | Z52: 1469 | AA52: 2620 | AF52: 31 | AG52: GB | AH52: 1509 | AI52: 977 | AM52: 32 | AN52: IV | AO52: 1511 | AP52: 1063 | AT52: 32 | AU52: GB | AV52: 1555 | AW52: 2146 | BA52: 0.24 | BH52: 39 | BI52: GB | BJ52: 1615 | BK52: 3005 | BO52: 39 | BP52: TB | BQ52: 1538 | BR52: 90 | BV52: 37 | BW52: TCR | BX52: 1587 | BY52: 365 | CC52: 37 | CD52: HMB | CE52: 1544 | CF52: 749 | CJ52: 0.2 | CQ52: 35 | CR52: IV | CS52: 1716 | CT52: 178 | CX52: 27 | CY52: GB | CZ52: 1774 | DA52: 144 | DG52: =SUM(DG42:DG51) -> 3551 | DL52: 28 | DM52: PR | DN52: 1810 | DO52: 168 | DS52: 22 | DT52: BG | DU52: 1828 | DV52: 89 | DZ52: 25 | EA52: BG | EB52: 1802 | EC52: 74
B53: 32 | C53: IV | D53: 1335 | E53: 108 | K53: =SUM(K49:K52) -> 4862 | P53: 32 | Q53: IV | R53: 1491 | S53: 2396 | X53: 32 | Y53: IV | Z53: 1491 | AA53: 2396 | AF53: 32 | AG53: GB | AH53: 1527 | AI53: 1784 | AP53: =SUM(AP45:AP52) -> 6793 | AT53: 33 | AU53: GB | AV53: 1471 | AW53: 92 | BA53: 36 | BB53: PR | BC53: 1587 | BD53: 2688 | BH53: 40 | BI53: GB | BJ53: 1518 | BK53: 212 | BO53: 40 | BP53: BG | BQ53: 1612 | BR53: 959 | BV53: 38 | BW53: BG | BX53: 1692 | BY53: 3337 | CC53: 38 | CD53: HMB | CE53: 1516 | CF53: 2882 | CJ53: 34 | CK53: GB | CL53: 1766 | CM53: 2813 | CQ53: 36 | CR53: IV | CS53: 1577 | CT53: 90 | CX53: 28 | CY53: GB | CZ53: 1779 | DA53: 3263 | DL53: 29 | DM53: IV | DN53: 1779 | DO53: 3263 | DS53: 23 | DT53: GB | DU53: 1895 | DV53: 967 | DZ53: 26 | EA53: TB | EB53: 1849 | EC53: 164
B54: 33 | C54: IV | D54: 1318 | E54: 101 | H54: 0.24 | P54: 33 | Q54: IV | R54: 1492 | S54: 1367 | X54: 33 | Y54: IV | Z54: 1492 | AA54: 310 | AF54: 33 | AG54: IV | AH54: 1469 | AI54: 2620 | AM54: 0.24 | AT54: 34 | AU54: TCR | AV54: 1540 | AW54: 1734 | BA54: 37 | BB54: TB | BC54: 1588 | BD54: 3010 | BH54: 41 | BI54: NB | BJ54: 1460 | BK54: 113 | BO54: 41 | BP54: BG | BQ54: 1476 | BR54: 148 | BV54: 39 | BW54: BG | BX54: 1688 | BY54: 714 | CC54: 39 | CD54: NB | CE54: 1657 | CF54: 272 | CJ54: 35 | CK54: IV | CL54: 1563 | CM54: 83 | CQ54: 37 | CR54: BG | CS54: 1775 | CT54: 925 | CX54: 29 | CY54: IV | CZ54: 1759 | DA54: 164 | DD54: 0.24 | DL54: 30 | DM54: IV | DN54: 1577 | DO54: 90 | DT54: GB | DU54: 1853 | DV54: 1184 | DZ54: 27 | EA54: BG | EB54: 1875 | EC54: 822
B55: 34 | C55: BG | D55: 1336 | E55: 177 | H55: 34 | I55: IV | J55: 1491 | K55: 2396 | P55: 34 | Q55: IV | R55: 1493 | S55: 2290 | X55: 34 | Y55: IV | Z55: 1493 | AA55: 2290 | AF55: 34 | AG55: IV | AH55: 1491 | AI55: 1859 | AM55: 33 | AN55: IV | AO55: 1556 | AP55: 3192 | AT55: 35 | AU55: BG | AV55: 1534 | AW55: 851 | BA55: 38 | BB55: HMB | BC55: 1566 | BD55: 3402 | BH55: 42 | BI55: NB | BJ55: 1585 | BK55: 2957 | BO55: 42 | BP55: BG | BQ55: 1425 | BR55: 77 | BV55: 40 | BW55: GB | BX55: 1667 | BY55: 324 | CC55: 40 | CD55: NB | CE55: 1718 | CF55: 2752 | CJ55: 36 | CK55: IV | CL55: 1714 | CM55: 917 | CQ55: 38 | CR55: BG | CS55: 1715 | CT55: 587 | CX55: 30 | CY55: IV | CZ55: 1823 | DA55: 2695 | DD55: 24 | DE55: IV | DF55: 1779 | DG55: 3263 | DL55: 31 | DM55: IV | DN55: 1823 | DO55: 261 | DS55: 24 | DT55: TB | DU55: 1889 | DV55: 1082 | DZ55: 28 | EA55: HMB | EB55: 1882 | EC55: 3279
B56: 35 | C56: PG | D56: 1285 | E56: 166 | H56: 35 | I56: IV | J56: 1469 | K56: 2620 | P56: 35 | Q56: IV | R56: 1396 | S56: 205 | X56: 35 | Y56: IV | Z56: 1396 | AA56: 205 | AF56: 35 | AG56: IV | AH56: 1396 | AI56: 205 | AM56: 34 | AN56: IV | AO56: 1557 | AP56: 3301 | AW56: =SUM(AW51:AW55) -> 5852 | BA56: 39 | BB56: PG | BC56: 1580 | BD56: 1198 | BH56: 43 | BI56: TB | BJ56: 1538 | BK56: 90 | BO56: 43 | BP56: HMB | BQ56: 1516 | BR56: 3434 | BY56: =SUM(BY42:BY55) -> 15553 | CC56: 41 | CD56: TCR | CE56: 1732 | CF56: 1444 | CJ56: 37 | CK56: TCR | CL56: 1711 | CM56: 293 | CQ56: 39 | CR56: GB | CS56: 1735 | CT56: 135 | CX56: 31 | CY56: IV | CZ56: 1716 | DA56: 178 | DD56: 25 | DE56: IV | DF56: 1577 | DG56: 90 | DL56: 32 | DM56: GB | DN56: 1845 | DO56: 282 | DT56: TCR | DU56: 1540 | DV56: 115 | DZ56: 29 | EA56: IV | EB56: 1888 | EC56: 1683
BH57: 44 | BI57: BG | BJ57: 1612 | BK57: 3024 | BO57: 44 | BP57: HMB | BQ57: 1544 | BR57: 1985 | BV57: 0.22 | CF57: 23653 | CJ57: 38 | CK57: TCR | CL57: 1721 | CM57: 146 | CQ57: 40 | CR57: TCR | CS57: 1752 | CT57: 89 | CX57: 32 | CY57: IV | CZ57: 1577 | DA57: 90 | DD57: 26 | DE57: IV | DF57: 1823 | DG57: 775 | DL57: 33 | DM57: GB | DN57: 1844 | DO57: 1563 | DS57: 25 | DT57: TCR | DU57: 1867 | DV57: 2011 | DZ57: 30 | EA57: TCR | EB57: 1890 | EC57: 2262
BH58: 45 | BI58: BG | BJ58: 1476 | BK58: 625 | BO58: 45 | BP58: HMB | BQ58: 1389 | BR58: 348 | BV58: 41 | BW58: IV | BX58: 1335 | BY58: 102 | CC58: 0.22 | CJ58: 39 | CK58: TCR | CL58: 1747 | CM58: 2538 | CQ58: 41 | CR58: GB | CS58: 1774 | CT58: 3113 | CX58: 33 | CY58: PG | CZ58: 1643 | DA58: 102 | DD58: 27 | DE58: BG | DF58: 1818 | DG58: 3141 | DL58: 34 | DM58: GB | DN58: 1807 | DO58: 521 | DV58: =SUM(DV46:DV57) -> 12392 | DZ58: 31 | EA58: TCR | EB58: 1810 | EC58: 168
B59: 36 | C59: HMB | D59: 1329 | E59: 111 | H59: 36 | I59: IV | J59: 1492 | K59: 2433 | P59: 36 | Q59: IV | R59: 1440 | S59: 164 | X59: 36 | Y59: IV | Z59: 1440 | AA59: 164 | AF59: 36 | AG59: IV | AH59: 1440 | AI59: 164 | AM59: 35 | AN59: IV | AO59: 1396 | AP59: 205 | AT59: 0.24 | BA59: 40 | BB59: IV | BC59: 1578 | BD59: 3181 | BH59: 46 | BI59: BG | BJ59: 1485 | BK59: 139 | BO59: 46 | BP59: HMB | BQ59: 1417 | BR59: 124 | BY59: =SUM(BY58) -> 102 | CC59: 42 | CD59: IV | CE59: 1736 | CF59: 3235 | CJ59: 40 | CK59: NB | CL59: 1717 | CM59: 2299 | CT59: =SUM(CT47:CT58) -> 14583 | CX59: 34 | CY59: TB | CZ59: 1797 | DA59: 2139 | DD59: 28 | DE59: BG | DF59: 1802 | DG59: 130 | DL59: 35 | DM59: NB | DN59: 1841 | DO59: 1688 | DZ59: 32 | EA59: TB | EB59: 1908 | EC59: 3428
B60: 37 | C60: HMB | D60: 1389 | E60: 1044 | H60: 37 | I60: IV | J60: 1493 | K60: 2290 | P60: 37 | Q60: IV | R60: 1281 | S60: 130 | X60: 37 | Y60: IV | Z60: 1281 | AA60: 130 | AF60: 37 | AG60: IV | AH60: 1281 | AI60: 130 | AM60: 36 | AN60: IV | AO60: 1469 | AP60: 644 | AT60: 36 | AU60: IV | AV60: 1557 | AW60: 2253 | BA60: 41 | BB60: IV | BC60: 1582 | BD60: 2417 | BH60: 47 | BI60: HMB | BJ60: 1516 | BK60: 3402 | BR60: =SUM(BR42:BR59) -> 16626 | BV60: 0.2 | CC60: 43 | CD60: IV | CE60: 1512 | CF60: 645 | CJ60: 41 | CK60: HMB | CL60: 1600 | CM60: 2178 | CQ60: 0.22 | CX60: 35 | CY60: TB | CZ60: 1768 | DA60: 1973 | DD60: 29 | DE60: PR | DF60: 1810 | DG60: 1204 | DL60: 36 | DM60: TB | DN60: 1849 | DO60: 3248 | DS60: 0.24 | DZ60: 33 | EA60: GB | EB60: 1909 | EC60: 1074
E61: =SUM(E46:E60) -> 6240 | H61: 38 | I61: IV | J61: 1427 | K61: 904 | P61: 38 | Q61: BG | R61: 1495 | S61: 3053 | X61: 38 | Y61: BG | Z61: 1495 | AA61: 3053 | AF61: 38 | AG61: BG | AH61: 1495 | AI61: 3053 | AM61: 37 | AN61: IV | AO61: 1491 | AP61: 546 | AT61: 37 | AU61: IV | AV61: 1281 | AW61: 130 | BA61: 43 | BB61: IV | BC61: 1281 | BD61: 130 | BH61: 48 | BI61: HMB | BJ61: 1544 | BK61: 1948 | BO61: 0.22 | BV61: 42 | BW61: IV | BX61: 1678 | BY61: 1476 | CC61: 44 | CD61: IV | CE61: 1335 | CF61: 95 | CJ61: 42 | CK61: BG | CL61: 1744 | CM61: 2697 | CQ61: 42 | CR61: IV | CS61: 1325 | CT61: 95 | CX61: 36 | CY61: BG | CZ61: 1802 | DA61: 208 | DD61: 30 | DE61: HMB | DF61: 1516 | DG61: 2882 | DL61: 37 | DM61: TB | DN61: 1833 | DO61: 559 | DS61: 26 | DT61: IV | DU61: 1823 | DV61: 173 | DZ61: 34 | EA61: GB | EB61: 1911 | EC61: 3276
B62: 0.22 | H62: 39 | I62: IV | J62: 1440 | K62: 164 | P62: 39 | Q62: BG | R62: 1496 | S62: 3044 | X62: 39 | Y62: BG | Z62: 1496 | AA62: 3044 | AF62: 39 | AG62: BG | AH62: 1485 | AI62: 225 | AM62: 38 | AN62: IV | AO62: 1280 | AP62: 130 | AT62: 38 | AU62: IV | AV62: 1396 | AW62: 205 | BA62: 44 | BB62: IV | BC62: 1396 | BD62: 205 | BH62: 49 | BI62: HMB | BJ62: 1389 | BK62: 336 | BO62: 47 | BP62: IV | BQ62: 1512 | BR62: 645 | BV62: 43 | BW62: IV | BX62: 1563 | BY62: 93 | CC62: 45 | CD62: GB | CE62: 1739 | CF62: 2726 | CJ62: 43 | CK62: TB | CL62: 1677 | CM62: 121 | CQ62: 43 | CR62: BG | CS62: 1737 | CT62: 1431 | CX62: 37 | CY62: BG | CZ62: 1818 | DA62: 3141 | DD62: 31 | DE62: HMB | DF62: 1544 | DG62: 262 | DL62: 38 | DM62: HMB | DN62: 1516 | DO62: 1588 | DS62: 27 | DT62: IV | DU62: 1885 | DV62: 1540 | DZ62: 35 | EA62: GB | EB62: 1912 | EC62: 2843
B63: 38 | C63: BG | D63: 1348 | E63: 3043 | H63: 40 | I63: IV | J63: 1396 | K63: 205 | P63: 40 | Q63: BG | R63: 1485 | S63: 3027 | X63: 40 | Y63: BG | Z63: 1485 | AA63: 2407 | AF63: 40 | AG63: BG | AH63: 1516 | AI63: 1335 | AM63: 39 | AN63: IV | AO63: 1440 | AP63: 164 | AT63: 39 | AU63: GB | AV63: 1547 | AW63: 1034 | BA63: 45 | BB63: GB | BC63: 1579 | BD63: 150 | BH63: 50 | BI63: HMB | BJ63: 1417 | BK63: 124 | BO63: 48 | BP63: IV | BQ63: 1335 | BR63: 96 | BV63: 44 | BW63: TB | BX63: 1677 | BY63: 564 | CC63: 46 | CD63: BG | CE63: 1737 | CF63: 2988 | CM63: 14085 | CT63: =SUM(CT61:CT62) -> 1526 | CX63: 38 | CY63: TCR | CZ63: 1810 | DA63: 1283 | DD63: 32 | DE63: NB | DF63: 1841 | DG63: 2634 | DL63: 39 | DM63: HMB | DN63: 1544 | DO63: 262 | DS63: 28 | DT63: IV | DU63: 1577 | DV63: 90 | DZ63: 36 | EA63: IV | EB63: 1577 | EC63: 90
BK64: =SUM(BK43:BK63) -> 30197 | BO64: 49 | BP64: IV | BQ64: 1513 | BR64: 2887 | BV64: 45 | BW64: TB | BX64: 1616 | BY64: 632 | CF64: 9689 | CJ64: 0.18 | CQ64: 0.2 | CX64: 39 | CY64: HMB | CZ64: 1544 | DA64: 506 | DD64: 33 | DE64: TB | DF64: 1833 | DG64: 1197 | DL64: 40 | DM64: BG | DN64: 1873 | DO64: 2594 | DS64: 29 | DT64: IV | DU64: 1888 | DV64: 3440 | DZ64: 37 | EA64: BG | EC64: 114
BH65: 0.22 | BO65: 50 | BP65: GB | BQ65: 1514 | BR65: 724 | BV65: 46 | BW65: HMB | BX65: 1600 | BY65: 2553 | CC65: 0.2 | CJ65: 44 | CK65: TCR | CL65: 1753 | CM65: 2352 | CQ65: 44 | CR65: BG | CS65: 1744 | CT65: 2265 | CX65: 40 | CY65: HMB | CZ65: 1516 | DA65: 2882 | DD65: 34 | DE65: GB | DF65: 1807 | DG65: 3256 | DL65: 41 | DM65: BG | DN65: 1802 | DO65: 104 | DS65: 30 | DT65: BG | DU65: 1873 | DV65: 2468 | DZ65: 38 | EA65: NB | EB65: 1894 | EC65: 1228
BH66: 51 | BI66: IV | BJ66: 1512 | BK66: 3016 | BR66: =SUM(BR62:BR65) -> 4352 | BV66: 47 | BW66: GB | BX66: 1664 | BY66: 109 | CC66: 47 | CD66: HMB | CE66: 1600 | CF66: 2377 | CJ66: 45 | CK66: HMB | CL66: 1731 | CM66: 741 | CQ66: 45 | CR66: TB | CS66: 1769 | CT66: 2629 | DA66: =SUM(DA48:DA65) -> 24986 | DD66: 35 | DE66: GB | DF66: 1831 | DG66: 1010 | DO66: =SUM(DO52:DO65) -> 16191 | DS66: 31 | DT66: BG | DU66: 1802 | DV66: 74 | EC66: 21800
B67: 39 | C67: BG | D67: 1294 | E67: 915 | H67: 41 | I67: IV | J67: 1281 | K67: 130 | P67: 41 | Q67: BG | R67: 1516 | S67: 3224 | X67: 41 | Y67: BG | Z67: 1516 | AA67: 3224 | AF67: 41 | AG67: BG | AH67: 1437 | AI67: 84 | AM67: 40 | AN67: IV | AO67: 1427 | AP67: 107 | AT67: 40 | AU67: GB | AV67: 1527 | AW67: 116 | BA67: 46 | BB67: GB | BC67: 1581 | BD67: 387 | BH67: 52 | BI67: IV | BJ67: 1335 | BK67: 96 | BO67: 0.2 | BV67: 48 | BW67: GB | BX67: 1688 | BY67: 3497 | CC67: 48 | CD67: NB | CE67: 1717 | CF67: 2886 | CJ67: 46 | CK67: IV | CL67: 1741 | CM67: 3238 | CQ67: 46 | CR67: NB | CS67: 1717 | CT67: 610 | DG67: =SUM(DG55:DG66) -> 19844 | DS67: 32 | DT67: BG | DV67: 114
BH68: 53 | BI68: GB | BJ68: 1514 | BK68: 2759 | BO68: 51 | BP68: IV | BQ68: 1563 | BR68: 2168 | BV68: 49 | BW68: GB | BX68: 1679 | BY68: 324 | CC68: 49 | CD68: GB | CE68: 1720 | CF68: 2321 | CJ68: 47 | CK68: BG | CL68: 1630 | CM68: 445 | CQ68: 47 | CR68: TCR | CS68: 1711 | CT68: 75 | CX68: 0.22 | DL68: 0.22 | DS68: 33 | DT68: GB | DU68: 1881 | DV68: 3015 | DZ68: 0.22
B69: 40 | C69: BG | D69: 1379 | E69: 583 | H69: 42 | I69: GB | J69: 1490 | K69: 2268 | P69: 42 | Q69: BG | R69: 1437 | S69: 188 | X69: 42 | Y69: BG | Z69: 1437 | AA69: 84 | AF69: 42 | AG69: HMB | AH69: 1389 | AI69: 489 | AM69: 41 | AN69: GB | AO69: 1547 | AP69: 3260 | AT69: 41 | AU69: NB | AV69: 1518 | AW69: 1411 | BA69: 49 | BB69: NB | BC69: 1585 | BD69: 2957 | BK69: =SUM(BK66:BK68) -> 5871 | BO69: 52 | BP69: IV | BQ69: 1593 | BR69: 851 | BV69: 50 | BW69: BG | BX69: 1641 | BY69: 1685 | CC69: 50 | CD69: GB | CE69: 1679 | CF69: 111 | CJ69: 48 | CK69: GB | CL69: 1740 | CM69: 2651 | CQ69: 48 | CR69: TB | CS69: 1677 | CT69: 121 | CX69: 41 | CY69: IV | CZ69: 1335 | DA69: 95 | DD69: 0.22 | DL69: 42 | DM69: PR | DN69: 1747 | DO69: 1614 | DS69: 36 | DT69: TB | DU69: 1849 | DV69: 1211 | DZ69: 39 | EA69: IV | EB69: 1335 | EC69: 95
B70: 41 | C70: PR | D70: 1393 | E70: 2710 | H70: 43 | I70: GB | J70: 1339 | K70: 125 | P70: 43 | Q70: HMB | R70: 1486 | S70: 3072 | X70: 43 | Y70: HMB | Z70: 1486 | AA70: 2680 | AF70: 43 | AG70: HMB | AH70: 1417 | AI70: 143 | AM70: 42 | AN70: GB | AO70: 1527 | AP70: 217 | AT70: 42 | AU70: NB | AV70: 1460 | AW70: 346 | BA70: 50 | BB70: NB | BC70: 1518 | BH70: 0.2 | BO70: 53 | BP70: GB | BQ70: 1589 | BR70: 297 | BY70: =SUM(BY61:BY69) -> 10933 | CC70: 51 | CD70: TB | CE70: 1677 | CF70: 394 | CM70: 9427 | CQ70: 49 | CR70: HMB | CS70: 1600 | CT70: 2178 | CX70: 42 | CY70: IV | CZ70: 1512 | DA70: 345 | DD70: 36 | DE70: GB | DF70: 1806 | DG70: 159 | DL70: 43 | DM70: IV | DN70: 1512 | DO70: 345 | DS70: 37 | DT70: TCR | DU70: 1810 | DV70: 162 | DZ70: 40 | EA70: GB | EB70: 1806 | EC70: 159
E71: =SUM(E63:E70) -> 7251 | H71: 44 | I71: GB | J71: 1366 | K71: 94 | P71: 44 | Q71: HMB | R71: 1489 | S71: 2591 | X71: 44 | Y71: HMB | Z71: 1489 | AA71: 2500 | AF71: 44 | AG71: NB | AH71: 1460 | AI71: 888 | AM71: 43 | AN71: BG | AO71: 1485 | AP71: 169 | AT71: 43 | AU71: TB | AV71: 1538 | AW71: 523 | BA71: 51 | BB71: NB | BC71: 1460 | BD71: 115 | BH71: 54 | BI71: IV | BJ71: 1563 | BK71: 2163 | BO71: 54 | BP71: GB | BQ71: 1504 | BR71: 85 | BV71: 0.18 | CC71: 52 | CD71: TB | CE71: 1616 | CF71: 225 | CQ71: 50 | CR71: IV | CS71: 1776 | CT71: 437 | CX71: 43 | CY71: IV | CZ71: 1799 | DA71: 2884 | DD71: 37 | DE71: GB | DF71: 1805 | DG71: 180 | DL71: 44 | DM71: IV | DN71: 1855 | DO71: 2564 | DS71: 38 | DT71: TCR | DU71: 1890 | DV71: 3215 | DZ71: 41 | EA71: GB | EB71: 1854 | EC71: 447
B72: 0.2 | H72: 45 | I72: BG | J72: 1488 | K72: 1856 | P72: 45 | Q72: HMB | R72: 1389 | S72: 878 | X72: 45 | Y72: HMB | Z72: 1389 | AA72: 878 | AF72: 45 | AG72: NB | AH72: 1494 | AI72: 2989 | AM72: 44 | AN72: BG | AO72: 1495 | AP72: 2704 | AT72: 44 | AU72: BG | AV72: 1495 | AW72: 2290 | BA72: 52 | BB72: TB | BC72: 1538 | BD72: 115 | BH72: 55 | BI72: IV | BJ72: 1593 | BK72: 2764 | BO72: 55 | BP72: BG | BQ72: 1512 | BR72: 202 | BV72: 51 | BW72: BG | BX72: 1630 | BY72: 716 | CC72: 53 | CD72: TCR | CE72: 1711 | CF72: 713 | CJ72: GAUGE | CK72: KG | CL72: COUNT | CM72: NET KG | CN72: AMOUNT | CO72: TOTAL | CQ72: 51 | CR72: IV | CS72: 1563 | CT72: 83 | CX72: 44 | CY72: GB | CZ72: 1806 | DA72: 159 | DD72: 38 | DE72: IV | DF72: 1799 | DG72: 1638 | DL72: 45 | DM72: IV | DN72: 1335 | DO72: 95 | DS72: 39 | DT72: NB | DU72: 1814 | DV72: 745 | DZ72: 42 | EA72: IV | EB72: 1855 | EC72: 1771
BH73: 56 | BI73: GB | BJ73: 1589 | BK73: 2083 | BO73: 56 | BP73: NB | BQ73: 1588 | BR73: 2002 | BY73: =SUM(BY72) -> 716 | CC73: 54 | CD73: BG | CE73: 1614 | CF73: 1317 | CJ73: ALUM (SPOOL 35kg) | CQ73: 52 | CR73: IV | CS73: 1777 | CT73: 3055 | CX73: 45 | CY73: GB | CZ73: 1805 | DA73: 1065 | DD73: 39 | DE73: IV | DF73: 1335 | DG73: 95 | DL73: 46 | DM73: GB | DN73: 1854 | DO73: 2127 | DS73: 40 | DT73: NB | DU73: 1894 | DV73: 3037 | DZ73: 43 | EA73: BG | EB73: 1877 | EC73: 2322
BH74: 57 | BI74: GB | BJ74: 1504 | BK74: 85 | BO74: 57 | BP74: PR | BQ74: 1560 | BR74: 577 | CC74: 55 | CD74: IV | CE74: 1714 | CF74: 2386 | CJ74: 0.45 | CK74: =CM7 -> 1294 | CQ74: 53 | CR74: TCR | CS74: 1747 | CT74: 2483 | DA74: =SUM(DA69:DA73) -> 4548 | DD74: 40 | DE74: IV | DF74: 1512 | DG74: 345 | DL74: 47 | DM74: GB | DN74: 1805 | DO74: 111 | DS74: 41 | DT74: HMB | DU74: 1882 | DV74: 3279 | DZ74: 44 | EA74: GB | EB74: 1887 | EC74: 1034
B75: 42 | C75: IV | D75: 1347 | E75: 3151 | H75: 46 | I75: BG | J75: 1495 | K75: 3053 | P75: 46 | Q75: HMB | R75: 1417 | S75: 143 | X75: 46 | Y75: HMB | Z75: 1417 | AA75: 143 | AF75: 46 | AG75: TB | AH75: 1487 | AI75: 191 | AM75: 45 | AN75: HMB | AO75: 1544 | AP75: 2824 | AT75: 45 | AU75: BG | AV75: 1485 | AW75: 144 | BA75: 53 | BB75: BG | BC75: 1495 | BD75: 1489 | BH75: 58 | BI75: BG | BJ75: 1617 | BK75: 3206 | BO75: 58 | BP75: TB | BQ75: 1616 | BR75: 2056 | CC75: 56 | CD75: IV | CE75: 1563 | CF75: 83 | CJ75: 0.55 | CK75: =CM11 -> 74 | CT75: =SUM(CT65:CT74) -> 13936 | DG75: =SUM(DG70:DG74) -> 2417 | DL75: 48 | DM75: BG | DN75: 1877 | DO75: 2446 | DS75: 42 | DT75: HMB | DU75: 1516 | DV75: 1562 | EC75: 5828
B76: 43 | C76: IV | D76: 1345 | E76: 3070 | H76: 47 | I76: BG | J76: 1496 | K76: 3044 | P76: 47 | Q76: NB | R76: 1460 | S76: 1947 | X76: 47 | Y76: NB | Z76: 1460 | AA76: 1186 | AF76: 47 | AG76: TB | AH76: 1538 | AI76: 1563 | AM76: 46 | AN76: NB | AO76: 1460 | AP76: 406 | AT76: 46 | AU76: HMB | AV76: 1561 | AW76: 3402 | BA76: 54 | BB76: BG | BC76: 1485 | BD76: 144 | BH76: 59 | BI76: NB | BJ76: 1564 | BK76: 2272 | BO76: 59 | BP76: HMB | BQ76: 1600 | BR76: 2621 | BV76: GUAGE | BW76: KG | BX76: COUNT | BY76: NET KG | BZ76: AMOUNT | CA76: TOTAL | CC76: 57 | CD76: TCR | CE76: 1721 | CF76: 352 | CJ76: F0.55 | CK76: =CM16 -> 65 | CQ76: 0.18 | CX76: 0.2 | DL76: 49 | DM76: GB | DN76: 1806 | DO76: 159 | DS76: 43 | DT76: HMB | DU76: 1544 | DV76: 262
BH77: 60 | BI77: PR | BJ77: 1560 | BK77: 1492 | BO77: 60 | BP77: HMB | BQ77: 1349 | BR77: 82 | BV77: Alum (spool 35kg) | CF77: 13165 | CJ77: 0.7 | CK77: =CM19+CM25 -> 1344 | CQ77: 54 | CR77: TCR | CS77: 1755 | CT77: 2141 | CX77: 46 | CY77: GB | CZ77: 1800 | DA77: 1325 | DD77: 0.2 | DO77: =SUM(DO69:DO76) -> 9461 | DV77: =SUM(DV61:DV76) -> 24387 | DZ77: 0.2
B78: 44 | C78: GB | D78: 1359 | E78: 787 | H78: 48 | I78: BG | J78: 1485 | K78: 3027 | P78: 48 | Q78: NB | R78: 1494 | S78: 2993 | X78: 48 | Y78: NB | Z78: 1494 | AA78: 2989 | AF78: 48 | AG78: IV | AH78: 1427 | AI78: 107 | AM78: 47 | AN78: HMB | AO78: 1389 | AP78: 411 | AT78: 47 | AU78: HMB | AV78: 1544 | AW78: 2824 | BA78: 56 | BB78: HMB | BC78: 1544 | BD78: 2824 | BH78: 61 | BI78: TB | BJ78: 1616 | BK78: 3202 | BR78: =SUM(BR68:BR77) -> 10941 | BV78: 0.45 | BW78: =BY7 -> 1622 | CC78: 0.18 | CK78: =SUM(CK74:CK77) -> 2777 | CL78: 8 | CM78: =CK78-(CL78*35) -> 2497 | CN78: 6450 | CO78: =CM78*CN78 -> 16105650 | CQ78: 55 | CR78: BG | CS78: 1630 | CT78: 70 | CX78: 47 | CY78: TCR | CZ78: 1712 | DA78: 75 | DD78: 40 | DE78: IV | DF78: 1777 | DG78: 2271 | DZ78: 45 | EA78: TCR | EB78: 1747 | EC78: 197
B79: 45 | C79: NB | D79: 1369 | E79: 828 | H79: 49 | I79: BG | J79: 1437 | K79: 403 | P79: 49 | Q79: TB | R79: 1487 | S79: 790 | X79: 49 | Y79: TB | Z79: 1487 | AA79: 619 | AI79: =SUM(AI52:AI78) -> 18806 | AM79: 48 | AN79: HMB | AO79: 1417 | AP79: 124 | AT79: 48 | AU79: HMB | AV79: 1389 | AW79: 411 | BA79: 57 | BB79: HMB | BC79: 1389 | BD79: 411 | BH79: 62 | BI79: HMB | BJ79: 1600 | BK79: 2548 | BO79: 0.18 | BV79: 0.55 | BW79: =BY13 -> 501 | CC79: 58 | CD79: BG | CE79: 1630 | CF79: 667 | CQ79: 56 | CR79: GB | CS79: 1740 | CT79: 1995 | CX79: 48 | CY79: TB | CZ79: 1769 | DA79: 1175 | DD79: 41 | DE79: IV | DF79: 1563 | DG79: 83 | DL79: 0.2 | DS79: 0.22 | DZ79: 46 | EA79: NB | EB79: 1816 | EC79: 1194
B80: 46 | C80: BG | D80: 1293 | E80: 801 | H80: 50 | I80: HMB | J80: 1486 | K80: 3072 | P80: 50 | Q80: PG | R80: 1285 | S80: 100 | X80: 50 | Y80: PG | Z80: 1285 | AA80: 100 | AG80: 0.22 | AM80: 49 | AN80: NB | AO80: 1518 | AP80: 1411 | AT80: 49 | AU80: HMB | AV80: 1417 | AW80: 124 | BA80: 58 | BB80: HMB | BC80: 1417 | BD80: 124 | BH80: 63 | BI80: HMB | BJ80: 1349 | BK80: 81 | BO80: 61 | BP80: BG | BQ80: 1630 | BR80: 3437 | BV80: F0.55 | BW80: =BY20 -> 311 | CC80: 59 | CD80: HMB | CE80: 1731 | CF80: 920 | CJ80: ALUZINC (SPOOL60kg) | CQ80: 57 | CR80: IV | CS80: 1741 | CT80: 3102 | CX80: 49 | CY80: BG | CZ80: 1817 | DA80: 3031 | DD80: 42 | DE80: GB | DF80: 1832 | DG80: 1635 | DL80: 50 | DM80: GB | DN80: 1875 | DO80: 3135 | DS80: 44 | DT80: IV | DU80: 1335 | DV80: 95 | DZ80: 47 | EA80: TB | EB80: 1834 | EC80: 564
B81: 47 | C81: HMB | D81: 1349 | E81: 3268 | H81: 51 | I81: HMB | J81: 1489 | K81: 2591 | P81: 51 | Q81: IV | R81: 1427 | S81: 227 | Y81: PR | Z81: 1507 | AA81: 977 | AF81: 49 | AG81: IV | AH81: 1335 | AI81: 96 | AM81: 50 | AN81: TB | AO81: 1538 | AP81: 1427 | AW81: =SUM(AW60:AW80) -> 15213 | BD81: =SUM(BD53:BD80) -> 24947 | BK81: =SUM(BK71:BK80) -> 19896 | BO81: 62 | BP81: BG | BQ81: 1548 | BR81: 167 | BV81: 0.7 | BW81: =BY29+BY23 -> 1503 | CF81: 1587 | CJ81: 0.28 | CK81: =CM33 -> 1784 | CQ81: 58 | CR81: HMB | CS81: 1777 | CT81: 3055 | CX81: 50 | CY81: IV | CZ81: 1563 | DA81: 83 | DD81: 43 | DE81: GB | DF81: 1800 | DG81: 135 | DL81: 51 | DM81: BG | DN81: 1817 | DO81: 2555 | DS81: 45 | DT81: IV | DU81: 1855 | DV81: 2182 | DZ81: 48 | EA81: IV | EB81: 1843 | EC81: 3181
E82: =SUM(E75:E81) -> 11905 | H82: 52 | I82: HMB | J82: 1389 | K82: 878 | S82: =SUM(S48:S81) -> 40580 | X82: 51 | Y82: IV | Z82: 1427 | AA82: 227 | AF82: 50 | AG82: IV | AH82: 1512 | AI82: 3303 | AP82: =SUM(AP55:AP81) -> 21242 | AT82: 0.22 | BA82: 0.22 | BH82: 0.18 | BR82: =SUM(BR80:BR81) -> 3604 | BW82: =SUM(BW78:BW81) -> 3937 | BX82: 14 | BY82: =BW82-(BX82*35) -> 3447 | BZ82: 5800 | CA82: =BZ82*BY82 -> 19992600 | CJ82: 0.24 | CK82: =CM45 -> 15028 | CT82: =SUM(CT77:CT81) -> 10363 | CX82: 51 | CY82: TCR | CZ82: 1747 | DA82: 1757 | DD82: 44 | DE82: NB | DF82: 1816 | DG82: 2384 | DL82: 52 | DM82: BG | DN82: 1744 | DO82: 108 | DS82: 46 | DT82: BG | DU82: 1877 | DV82: 2446 | DZ82: 49 | EA82: IV | EB82: 1512 | EC82: 345
H83: 53 | I83: HMB | J83: 1417 | K83: 143 | Q83: 0.22 | AA83: =SUM(AA50:AA82) -> 37319 | AF83: 51 | AG83: IV | AH83: 1513 | AI83: 2507 | AM83: 0.22 | AT83: 50 | AU83: IV | AV83: 1512 | AW83: 3303 | BA83: 59 | BB83: IV | BC83: 1512 | BD83: 3303 | BH83: 65 | BI83: BG | BJ83: 1548 | BK83: 122 | CJ83: 0.22 | CK83: =CM51 -> 2827 | CX83: 52 | CY83: BG | CZ83: 1744 | DA83: 705 | DD83: 45 | DE83: PR | DF83: 1711 | DG83: 75 | DL83: 53 | DM83: IV | DN83: 1563 | DO83: 83 | DS83: 47 | DT83: GB | DU83: 1887 | DV83: 2459 | DZ83: 50 | EA83: HMB | EB83: 1846 | EC83: 3171
H84: 54 | I84: NB | J84: 1494 | K84: 3159 | P84: 52 | Q84: IV | R84: 1335 | S84: 102 | Y84: 0.22 | AF84: 52 | AG84: GB | AH84: 1514 | AI84: 3285 | AM84: 51 | AN84: IV | AO84: 1512 | AP84: 3303 | AT84: 51 | AU84: IV | AV84: 1513 | AW84: 1912 | BA84: 60 | BB84: IV | BC84: 1513 | BD84: 1390 | BV84: aluzinc(spool 60) | CJ84: 0.2 | CK84: =CM63 -> 14085 | CQ84: GAUGE | CR84: KG | CS84: COUNT | CT84: NET KG | CU84: AMOUNT | CV84: TOTAL | CX84: 53 | CY84: NB | CZ84: 1816 | DA84: 3251 | DD84: 46 | DE84: PR | DF84: 1747 | DG84: 1735 | DL84: 54 | DM84: IV | DN84: 1777 | DO84: 597 | DS84: 48 | DT84: GB | DU84: 1854 | DV84: 447 | DZ84: 51 | EA84: IV | EB84: 1874 | EC84: 3025
B85: GUAGE | C85: KG | D85: UNIT | E85: SPOOL | F85: WORTH | H85: 55 | I85: NB | J85: 1460 | K85: 1947 | P85: 53 | Q85: IV | R85: 1512 | S85: 3303 | X85: 52 | Y85: IV | Z85: 1335 | AA85: 102 | AF85: 53 | AG85: GB | AH85: 1515 | AI85: 2575 | AM85: 52 | AN85: IV | AO85: 1513 | AP85: 2080 | AT85: 52 | AU85: IV | AV85: 1335 | AW85: 102 | BA85: 61 | BB85: IV | BC85: 1335 | BD85: 96 | BO85: GUAGE | BP85: KG | BQ85: COUNT | BR85: NET KG | BS85: AMOUNT | BT85: TOTAL | BV85: 0.28 | BW85: =BY40 -> 6284 | CJ85: 0.18 | CK85: =CM70 -> 9427 | CQ85: ALUM (SPOOL 35kg) | DA85: =SUM(DA77:DA84) -> 11402 | DD85: 47 | DE85: HMB | DF85: 1600 | DG85: 318 | DL85: 55 | DM85: IV | DN85: 1874 | DO85: 3207 | DS85: 49 | DT85: GB | DU85: 1806 | DV85: 159 | DZ85: 52 | EA85: GB | EB85: 1875 | EC85: 1320
B86: 0.45 | C86: =E9 -> 3795 | D86: 4 | H86: 56 | I86: NB | J86: 1403 | K86: 135 | P86: 54 | Q86: IV | R86: 1513 | S86: 3220 | X86: 53 | Y86: IV | Z86: 1512 | AA86: 3303 | AI86: =SUM(AI81:AI85) -> 11766 | AM86: 53 | AN86: IV | AO86: 1335 | AP86: 102 | AT86: 53 | AU86: GB | AV86: 1514 | AW86: 3285 | BA86: 62 | BB86: GB | BC86: 1514 | BD86: 3285 | BO86: Alum (spool 35kg) | BV86: 0.24 | BW86: =BY56 -> 15553 | CC86: GAUGE | CD86: KG | CE86: COUNT | CF86: NET KG | CG86: AMOUNT | CH86: TOTAL | CK86: =SUM(CK81:CK85) -> 43151 | CL86: 35 | CM86: =CK86-(CL86*60) -> 41051 | CN86: 2150 | CO86: =CM86*CN86 -> 88259650 | CQ86: 0.45 | CR86: =CT7 -> 1182 | DD86: 48 | DE86: BG | DF86: 1817 | DG86: 2805 | DL86: 56 | DM86: IV | DN86: 1847 | DO86: 3189 | DT86: GB | DU86: 1805 | DV86: 86 | DZ86: 53 | EA86: BG | EB86: 1883 | EC86: 1718
B87: 0.55 | C87: =E28 -> 13262 | D87: 16 | H87: 57 | I87: TB | J87: 1487 | K87: 2844 | P87: 55 | Q87: BG | R87: 1466 | S87: 2972 | X87: 54 | Y87: IV | Z87: 1513 | AA87: 3220 | AG87: 0.2 | AM87: 54 | AN87: GB | AO87: 1514 | AP87: 3285 | AT87: 54 | AU87: GB | AV87: 1515 | AW87: 1266 | BA87: 63 | BB87: GB | BC87: 1515 | BD87: 457 | BH87: GUAGE | BI87: KG | BJ87: COUNT | BK87: NET KG | BL87: AMOUNT | BM87: TOTAL | BO87: 0.45 | BP87: =BR8 -> 1876 | BV87: 0.22 | BW87: =BY59 -> 102 | CC87: ALUM (SPOOL 35kg) | CQ87: 0.55 | CR87: =CT11 -> 74 | CX87: 0.18 | DD87: 49 | DE87: BG | DF87: 1744 | DG87: 108 | DL87: 57 | DM87: NB | DN87: 1816 | DO87: 1875 | DV87: =SUM(DV80:DV86) -> 7874 | DZ87: 54 | EA87: GB | EB87: 1884 | EC87: 3276
B88: FULL 0.55 | C88: =E33 -> 1574 | D88: 2 | H88: 58 | I88: GB | J88: 1473 | K88: 85 | P88: 56 | Q88: GB | R88: 1514 | S88: 3285 | X88: 55 | Y88: BG | Z88: 1466 | AA88: 0 | AF88: 54 | AG88: TB | AH88: 1517 | AI88: 1859 | AM88: 55 | AN88: GB | AO88: 1515 | AP88: 1266 | AW88: =SUM(AW83:AW87) -> 9868 | BD88: =SUM(BD83:BD87) -> 8531 | BH88: Alum (spool 35kg) | BO88: 0.55 | BP88: =BR17 -> 1349 | BV88: 0.2 | BW88: =BY70 -> 10933 | CC88: 0.45 | CD88: =CF7 -> 1374 | CQ88: F0.55 | CR88: =CT20 -> 3680 | CX88: 54 | CY88: IV | CZ88: 1741 | DA88: 3058 | DD88: 50 | DE88: TB | DF88: 1834 | DG88: 3258 | DL88: 58 | DM88: GB | DN88: 1832 | DO88: 163 | DZ88: 55 | EA88: BG | EB88: 1891 | EC88: 2748
B89: 0.7 | C89: =E36 -> 771 | D89: 1 | H89: 59 | I89: PG | J89: 1285 | K89: 100 | P89: 57 | Q89: GB | R89: 1515 | S89: 3304 | X89: 56 | Y89: GB | Z89: 1514 | AA89: 3285 | AF89: 55 | AG89: HMB | AH89: 1349 | AI89: 805 | AP89: =SUM(AP84:AP88) -> 10036 | AT89: 0.2 | BA89: 0.2 | BH89: 0.45 | BI89: =BK8 -> 1930 | BO89: F0.55 | BP89: =BR26 -> 1165 | BV89: 0.18 | BW89: =BY73 -> 716 | CC89: 0.55 | CD89: =CF13 -> 263 | CQ89: 0.7 | CR89: =CT29+CT23 -> 1344 | CX89: 55 | CY89: HMB | CZ89: 1731 | DA89: 741 | DD89: 51 | DE89: TB | DF89: 1769 | DG89: 831 | DL89: 59 | DM89: GB | DN89: 1850 | DO89: 1159 | DS89: 0.2 | DZ89: 56 | EA89: IV | EB89: 1893 | EC89: 69
C90: =SUM(C86:C89) -> 19402 | D90: =SUM(D86:D89) -> 23 | E90: =D90*35 -> 805 | K90: =SUM(K55:K89) -> 39966 | S90: =SUM(S84:S89) -> 16186 | X90: 57 | Y90: GB | Z90: 1515 | AA90: 3088 | AF90: 56 | AG90: NB | AH90: 1518 | AI90: 1440 | AM90: 0.2 | AT90: 55 | AU90: IV | AV90: 1563 | AW90: 2552 | BA90: 64 | BB90: IV | BC90: 1563 | BD90: 2181 | BH90: 0.55 | BI90: =BK18 -> 1785 | BO90: 0.7 | BP90: =BR33 -> 2008 | BW90: =SUM(BW85:BW89) -> 33588 | BX90: 32 | BY90: =BW90-(BX90*60) -> 31668 | BZ90: 2100 | CA90: =BZ90*BY90 -> 66502800 | CC90: F0.55 | CD90: =CF20+CF23 -> 412 | CJ90: ACCESSORIES | CR90: =SUM(CR86:CR89) -> 6280 | CS90: 9 | CT90: =CR90-(CS90*35) -> 5965 | CU90: 6400 | CV90: =CT90*CU90 -> 38176000 | CX90: 56 | CY90: GB | CZ90: 1740 | DA90: 1757 | DG90: =SUM(DG78:DG89) -> 15638 | DL90: 60 | DM90: GB | DN90: 1875 | DO90: 3135 | DS90: 50 | DT90: IV | DU90: 1563 | DV90: 83 | DZ90: 57 | EA90: PG | EB90: 1907 | EC90: 2668
BH91: F0.55 | BI91: =BK27 -> 1199 | BP91: =SUM(BP87:BP90) -> 6398 | BQ91: 20 | BR91: =BP91-(BQ91*35) -> 5698 | BS91: 6400 | BT91: =BS91*BR91 -> 36467200 | CC91: 0.7 | CD91: =CF29 -> 1387 | CJ91: ITEM | CK91: QUANTITY | CL91: COST | CM91: AMOUNT | CX91: 57 | CY91: TCR | CZ91: 1755 | DA91: 2049 | DL91: 61 | DM91: HMB | DN91: 1846 | DO91: 3185 | DS91: 51 | DT91: IV | DU91: 1874 | DV91: 3207 | EC91: 23476
B92: NET | C92: =C90-E90 -> 18597 | D92: 2900 | F92: =C92*D92 -> 53931300 | H92: 0.22 | Q92: 0.2 | AA92: =SUM(AA85:AA90) -> 12998 | AF92: 57 | AG92: PR | AH92: 1519 | AI92: 1354 | AM92: 56 | AN92: GB | AO92: 1546 | AP92: 2188 | AT92: 56 | AU92: GB | AV92: 1347 | AW92: 88 | BA92: 65 | BB92: GB | BC92: 1589 | BD92: 3288 | BH92: 0.7 | BI92: =BK34 -> 2654 | CA92: =SUM(CA82,CA90) -> 86495400 | CD92: =SUM(CD88:CD91) -> 3436 | CE92: 13 | CF92: =CD92-(CE92*35) -> 2981 | CG92: 6450 | CH92: =CF92*CG92 -> 19227450 | CJ92: NAILS | CK92: 3 | CL92: 40000 | CM92: =CK92*CL92 -> 120000 | CQ92: ALUZINC (SPOOL60kg) | CX92: 58 | CY92: BG | CZ92: 1819 | DA92: 3250 | DD92: 0.18 | DL92: 62 | DM92: TB | DN92: 1834 | DO92: 2585 | DS92: 52 | DT92: IV | DU92: 1777 | DV92: 563
H93: 60 | I93: BG | J93: 1460 | K93: 3330 | P93: 58 | Q93: TB | R93: 1470 | S93: 312 | Y93: 0.2 | AF93: 58 | AG93: IV | AH93: 1347 | AI93: 88 | AM93: 57 | AN93: GB | AO93: 1504 | AP93: 85 | AT93: 57 | AU93: GB | AV93: 1565 | AW93: 2568 | BA93: 68 | BB93: GB | BC93: 1504 | BD93: 85 | BI93: =SUM(BI89:BI92) -> 7568 | BJ93: 30 | BK93: =BI93-(BJ93*35) -> 6518 | BL93: 6400 | BM93: =BL93*BK93 -> 41715200 | BO93: aluzinc(spool 60) | CJ93: SILICON | CK93: 21 | CL93: 2000 | CM93: =CK93*CL93 -> 42000 | CQ93: 0.28 | CR93: =CT45 -> 7386 | DA93: =SUM(DA88:DA92) -> 10855 | DD93: 52 | DE93: BG | DF93: 1819 | DG93: 3165 | DO93: =SUM(DO80:DO92) -> 24976 | DS93: 53 | DT93: IV | DU93: 1847 | DV93: 3189 | DZ93: 0.18
BO94: 0.28 | BP94: =BR40 -> 4868 | BV94: ACCESSORIES | CC94: ALUZINC (SPOOL60kg) | CJ94: WASHER | CK94: 2000 | CL94: 300 | CM94: =CK94*CL94 -> 600000 | CQ94: 0.24 | CR94: =CT59 -> 14583 | DD94: 53 | DE94: HMB | DF94: 1731 | DG94: 680 | DS94: 54 | DT94: BG | DU94: 1744 | DV94: 104 | DZ94: 58 | EA94: HMB | EB94: 1731 | EC94: 680
B95: 0.2 | C95: =E82 -> 11905 | D95: 6 | H95: 61 | I95: IV | J95: 1335 | K95: 108 | P95: 59 | Q95: TB | R95: 1517 | S95: 3210 | X95: 58 | Y95: TB | Z95: 1470 | AA95: 152 | AF95: 59 | AG95: GB 0.20 | AH95: 1422 | AI95: 88 | AM95: 58 | AN95: GB | AO95: 1422 | AP95: 88 | AT95: 58 | AU95: GB | AV95: 1504 | AW95: 84 | BA95: 69 | BB95: NB | BC95: 1564 | BD95: 2662 | BH95: aluzinc(spool 60) | BO95: 0.24 | BP95: =BR60 -> 16626 | BV95: ITEM | BW95: QUANTITY | BX95: COST | BY95: AMOUNT | CC95: 0.28 | CD95: =CF41 -> 8037 | CJ95: FELT | CK95: 1200 | CL95: 260 | CM95: =CK95*CL95 -> 312000 | CQ95: 0.22 | CR95: =CT63 -> 1526 | DD95: 54 | DE95: PR | DF95: 1755 | DG95: 1748 | DL95: 0.18 | DS95: 55 | DT95: BG | DU95: 1891 | DV95: 2748 | DZ95: 59 | EA95: IV | EB95: 1741 | EC95: 1032
B96: 0.22 | C96: =E71 -> 7251 | D96: 4 | K96: =SUM(K93:K95) -> 3438 | P96: 60 | Q96: NB | R96: 1419 | S96: 110 | X96: 59 | Y96: TB | Z96: 1517 | AA96: 2150 | AF96: 60 | AG96: GB | AH96: 1504 | AI96: 85 | AM96: 59 | AN96: IV | AO96: 1545 | AP96: 312 | AT96: 59 | AU96: NB | AV96: 1564 | AW96: 2921 | BA96: 70 | BB96: PR | BC96: 1560 | BD96: 1492 | BH96: 0.28 | BI96: =BK41 -> 6552 | BO96: 0.22 | BP96: =BR66 -> 4352 | BV96: NAILS | BW96: 6 | BX96: 40000 | BY96: =BW96*BX96 -> 240000 | CC96: 0.24 | CD96: =CF57 -> 23653 | CJ96: COPPER NAIL | CK96: 0.5 | CL96: 35000 | CM96: =CK96*CL96 -> 17500 | CQ96: 0.2 | CR96: =CT75 -> 13936 | CX96: GAUGE | CY96: KG | CZ96: COUNT | DA96: NET KG | DB96: AMOUNT | DC96: TOTAL | DD96: 55 | DE96: IV | DF96: 1741 | DG96: 3018 | DL96: 63 | DM96: BG | DN96: 1819 | DO96: 2628 | DS96: 56 | DT96: BG | DU96: 1883 | DV96: 2280 | DZ96: 60 | EA96: BG | EB96: 1819 | EC96: 1862
BH97: 0.24 | BI97: =BK64 -> 30197 | BO97: 0.2 | BP97: =BR78 -> 10941 | BV97: RIVET PIN | BW97: 12 | BX97: 4000 | BY97: =BW97*BX97 -> 48000 | CC97: 0.22 | CD97: =CF64 -> 9689 | CM97: =SUM(CM92:CM96) -> 1091500 | CQ97: 0.18 | CR97: =CT82 -> 10363 | CX97: ALUM (SPOOL 35kg) | DG97: =SUM(DG93:DG96) -> 8611 | DL97: 64 | DM97: PR | DN97: 1755 | DO97: 1748 | DS97: 57 | DT97: GB | DU97: 1884 | DV97: 3371 | DZ97: 61 | EA97: TCR | EB97: 1755 | EC97: 2033
B98: 0.24 | C98: =E61 -> 6240 | D98: 12 | H98: 0.2 | P98: 61 | Q98: HMB | R98: 1349 | S98: 1283 | X98: 60 | Y98: NB | Z98: 1419 | AA98: 100 | AI98: =SUM(AI88:AI96) -> 5719 | AM98: 60 | AN98: IV | AO98: 1347 | AP98: 88 | AT98: 60 | AU98: PR | AV98: 1560 | AW98: 1539 | BA98: 71 | BB98: TB | BC98: 1517 | BD98: 542 | BH98: 0.22 | BI98: =BK69 -> 5871 | BO98: 0.18 | BP98: =BR82 -> 3604 | BV98: FELT | BW98: 60 | BX98: 260 | BY98: =BW98*BX98 -> 15600 | CC98: 0.2 | CD98: =CF77 -> 13165 | CO98: =SUM(CO78,CO86,CM97) -> 105456800 | CR98: =SUM(CR93:CR97) -> 47794 | CS98: 41 | CT98: =CR98-(CS98*60) -> 45334 | CU98: 2090 | CV98: =CT98*CU98 -> 94748060 | CX98: 0.45 | CY98: =DA7 -> 1126 | DL98: 65 | DM98: IV | DN98: 1741 | DO98: 2171 | DS98: 58 | DT98: GB | DU98: 1850 | DV98: 554 | EC98: 5607
B99: 0.28 | C99: =E44 -> 3321 | D99: 2 | H99: 62 | I99: IV | J99: 1448 | K99: 2244 | P99: 62 | Q99: BG | R99: 1467 | S99: 951 | X99: 61 | Y99: HMB | Z99: 1349 | AA99: 1232 | AG99: 0.18 | AM99: 61 | AN99: HMB | AO99: 1544 | AP99: 2824 | AT99: 61 | AU99: TB | AV99: 1517 | AW99: 1587 | BA99: 72 | BB99: BG | BC99: 1574 | BD99: 1195 | BH99: 0.2 | BI99: =BK81 -> 19896 | BP99: =SUM(BP94:BP98) -> 40391 | BQ99: 39 | BR99: =BP99-(BQ99*60) -> 38051 | BS99: 2250 | BT99: =BS99*BR99 -> 85614750 | BV99: SILICON | BW99: 22 | BX99: 2000 | BY99: =BW99*BX99 -> 44000 | CC99: 0.18 | CD99: =CF81 -> 1587 | CX99: 0.55 | CY99: =DA11 -> 30 | DE99: GAUGE | DF99: KG | DG99: COUNT | DH99: NET KG | DI99: AMOUNT | DJ99: TOTAL | DL99: 66 | DM99: HMB | DN99: 1731 | DO99: 680 | DS99: 59 | DT99: GB | DU99: 1875 | DV99: 2555
BH100: 0.18 | BI100: =BK83 -> 122 | BV100: WASHER | BW100: 500 | BX100: 300 | BY100: =BW100*BX100 -> 150000 | CD100: =SUM(CD95:CD99) -> 56131 | CE100: 42 | CF100: =CD100-(CE100*60) -> 53611 | CG100: 2150 | CH100: =CF100*CG100 -> 115263650 | CX100: F0.55 | CY100: =DA19 -> 10504 | DE100: ALUM (SPOOL 35kg) | DO100: =SUM(DO96:DO99) -> 7227 | DS100: 60 | DT100: TB | DU100: 1834 | DV100: 1994 | DZ100: GAUGE | EA100: KG | EB100: COUNT | EC100: NET KG | ED100: AMOUNT | EE100: TOTAL
...

Sheet Pricing
A2: pricing | C2: conv | D2: 6200 | E2: 400
A3: 0.45 | C3: 0.8 | D3: =D2*C3 -> 4960 | E3: =E2+D3 -> 5360 | J3: Kaduna | L3: Yola | N3: Maid | P3: Jalingo
A4: 0.55 | C4: 1 | D4: =D2*C4 -> 6200 | E4: =E2+D4 -> 6600 | I4: Meters Avg | K4: 17000 | M4: 25000 | O4: 26000 | Q4: 8250
C5: 0.97 | D5: =D2*C5 -> 6014 | E5: =E2+D5 -> 6414
A6: 0.55f | C6: 1.75 | D6: =D2*C6 -> 10850 | E6: =E2+D6 -> 11250
C7: 1.6 | D7: =D3*C7 -> 7936 | E7: =E3+D7 -> 13296 | I7: Expenses
C8: 1.7 | D8: =D2*C8 -> 10540 | E8: =E2+D8 -> 10940 | I8: Over Head Avg | J8: 1500000 | K8: =J8/K4 -> 88.235294 | L8: 1350000 | M8: =L8/M4 -> 54 | N8: 850000 | O8: =N8/O4 -> 32.692308 | P8: 530000 | Q8: =P8/Q4 -> 64.242424
C9: 1.72 | D9: =D2*C9 -> 10664 | E9: =E2+D9 -> 11064 | I9: Admin Expenses avg | J9: 1150000 | K9: =J9/K4 -> 67.647059 | L9: 1100000 | M9: =L9/M4 -> 44 | N9: 100000 | O9: =N9/O4 -> 3.8461538 | P9: 600000 | Q9: =P9/Q4 -> 72.727273
A10: 0.7 | C10: 2.3 | D10: =D2*C10 -> 14260 | E10: =D10+E2 -> 14660 | I10: Transport inward | J10: each 1,500m @ 100k | K10: 67 | L10: 150k | M10: 100 | N10: 150k | O10: 100 | P10: 150k | Q10: 100
C11: 2.2 | D11: =D2*C11 -> 13640 | E11: =D11+E2 -> 14040 | K11: =SUM(K8:K10) -> 222.88235 | M11: =SUM(M8:M10) -> 198 | O11: =SUM(O8:O10) -> 136.53846 | Q11: =SUM(Q8:Q10) -> 236.9697
B13: 7.8 x 1.2 | D13: 1820 | E13: 500 | F13: new | I13: Chairman Exp | J13: 1800000 | K13: =J13/K4 -> 105.88235 | L13: 1700000 | M13: =L13/M4 -> 68 | N13: 1400000 | O13: =N13/O4 -> 53.846154 | P13: 630000 | Q13: =P13/Q4 -> 76.363636
A14: 0.18 | B14: =A14*7.8*1.2 -> 1.6848 | C14: 1.75 | D14: =D13*C14 -> 3185 | E14: =E13+D14 -> 3685 | F14: 3700 | K14: =K11+K13 -> 328.76471 | M14: =M11+M13 -> 266 | O14: =O11+O13 -> 190.38462 | Q14: =Q11+Q13 -> 313.33333
A15: 0.2 | B15: =A15*7.8*1.2 -> 1.872 | C15: 1.9 | D15: =D13*C15 -> 3458 | E15: =E13+D15 -> 3958 | F15: 3950
A16: 0.22 | B16: =A16*7.8*1.2 -> 2.0592 | C16: 2.1 | D16: =D13*C16 -> 3822 | E16: =E13+D16 -> 4322 | F16: 4350
A17: 0.24 | B17: =A17*7.8*1.2 -> 2.2464 | C17: 2.3 | D17: =D13*C17 -> 4186 | E17: =D17+E13 -> 4686 | F17: 4800
A18: 0.25 | B18: =A18*7.8*1.2 -> 2.34
A19: 0.26 | B19: =A19*7.8*1.2 -> 2.4336
A20: 0.27 | B20: =A20*7.8*1.2 -> 2.5272
A21: 0.28 | B21: =A21*7.8*1.2 -> 2.6208 | C21: 2.7 | D21: =D13*C21 -> 4914 | E21: =E13+D21 -> 5414 | F21: 5900
I23: 4200
A24: 0.18 | D24: 4075 | E24: 4162.5 | F24: 4197.5 | I24: 4450
A25: 0.2 | D25: 4390 | E25: 4485 | F25: 4523 | I25: 4950
A26: 0.22 | D26: 4810 | E26: 4915 | F26: 4957 | I26: 5350
A27: 0.24 | D27: 5230 | E27: 5345 | F27: 5391 | I27: 6350
A28: 0.28 | D28: 6070 | E28: 6205 | F28: 6259
